Workbook
Name Allkortsfaktura_629_011_192_December_2013: Kontoutdrag_officiella!$A$456:$E$472

Sheet Kontoutdrag_officiella
A1: y | B1: m | C1: d | D1: n | E1: t | F1: g | G1: s | H1: b | L1: c
A2: 2015 | B2: 12 | C2: 30 | D2: PILEGÅRDEN 2 & | E2: -7824 | F2: 0 | G2: =E2 -> -7824 | H2: hyra (inkl. 1k amortering) | L2: Regular
A3: 2015 | B3: 12 | C3: 30 | D3: Periodens köp | E3: -11093.58 | F3: 0 | G3: =E3 -> -11093.58 | H3: spara almänt | L3: Regular
A4: 2015 | B4: 12 | C4: 30 | D4: HSB GÖTEBORG | E4: -4007 | F4: 0 | G4: =E4 -> -4007 | H4: hyra (inkl. 1k amortering) | L4: Regular
A5: 2015 | B5: 12 | C5: 30 | D5: HSB BOKVAR | E5: -207.8 | F5: 0 | G5: =E5 -> -207.8 | H5: hyra (inkl. 1k amortering) | L5: Regular
A6: 2015 | B6: 12 | C6: 30 | D6: FOLKSAM | E6: -153 | F6: 0 | G6: =E6 -> -153 | H6: hemförsäkring | L6: Regular
A7: 2015 | B7: 12 | C7: 30 | D7: 47516877 | E7: 1000 | F7: 0 | G7: =E7 -> 1000 | H7: spara till amortering | L7: Regular
A8: 2015 | B8: 12 | C8: 29 | D8: SV INGENJ | E8: -320 | F8: 0 | G8: =E8 -> -320 | H8: si och akassa | L8: Regular
A9: 2015 | B9: 12 | C9: 29 | D9: COM HEM AB | E9: -299 | F9: 0 | G9: =E9 -> -299 | H9: internet | L9: Regular
A10: 2015 | B10: 12 | C10: 29 | D10: AKADEMIKERFÖ | E10: -298 | F10: 0 | G10: =E10 -> -298 | H10: liv- o sjukförsäkring etc | L10: Regular
A11: 2015 | B11: 12 | C11: 28 | D11: UNICEF | E11: -100 | F11: 0 | G11: =E11 -> -100 | H11: röda korset | L11: Regular
A12: 2015 | B12: 12 | C12: 28 | D12: Månadsbuffert | E12: -5000 | F12: 0 | G12: =E12 -> -5000 | H12: - | L12: Regular
A13: 2015 | B13: 12 | C13: 28 | D13: Månadsbuffert | E13: 5000 | F13: 0 | G13: =E13 -> 5000 | H13: - | L13: Regular
A14: 2015 | B14: 12 | C14: 28 | D14: LUX RÄNTA | E14: -1250 | F14: 0 | G14: =E14 -> -1250 | H14: spara till amortering | L14: Regular
A15: 2015 | B15: 12 | C15: 27 | D15: QSTAR SIML$NGSDALEN | E15: -402.65 | F15: 0 | G15: =E15 -> -402.65 | H15: spara till russel övrigt | L15: Regular
A16: 2015 | B16: 12 | C16: 25 | D16: SVENSSON,KAROL | E16: 60 | F16: 0 | G16: =E16 -> 60 | H16: spara till russel övrigt | L16: Regular
A17: 2015 | B17: 12 | C17: 25 | D17: CITY GROSS VARNAMO | E17: -278.4 | F17: 0 | G17: =E17 -> -278.4 | H17: spara till russel övrigt | L17: Regular
A18: 2015 | B18: 12 | C18: 25 | D18: CITY GROSS VARNAMO | E18: -113 | F18: 0 | G18: =E18 -> -113 | H18: spara till russel övrigt | L18: Regular
A19: 2015 | B19: 12 | C19: 24 | D19: GODJUL MOP | E19: 1000 | F19: 0 | G19: =E19 -> 1000 | H19: presenter | L19: Regular
... A64: 2015 | B64: 11 | C64: 30 | D64: CENTRALA STUDI | E64: -3061 | F64: 0 | G64: =E64 -> -3061 | H64: csn | L64: Regular
A65: 2015 | B65: 11 | C65: 30 | D65: 47516877 | E65: 1000 | F65: 0 | G65: =E65 -> 1000 | H65: spara till amortering | L65: Regular
A66: 2015 | B66: 11 | C66: 28 | D66: PRESSBYR$N 4250148 G@TEBORG | E66: -110 | F66: 0 | G66: =E66 -> -110 | H66: alkohol | L66: Regular
A67: 2015 | B67: 11 | C67: 28 | D67: Marcus Bjerkst | E67: -111 | F67: 0 | G67: =E67 -> -111 | H67: spara till russel övrigt | L67: Regular
A68: 2015 | B68: 11 | C68: 28 | D68: M}ngatan AB G¦teborg | E68: -129 | F68: 0 | G68: =E68 -> -129 | H68: nöjes utemat | L68: Regular
A69: 2015 | B69: 11 | C69: 28 | D69: JOHAN GRADEEN | E69: 79 | F69: 0 | G69: =E69 -> 79 | H69: spara till russel övrigt | L69: Regular
A70: 2015 | B70: 11 | C70: 27 | D70: SV INGENJ | E70: -320 | F70: 0 | G70: =E70 -> -320 | H70: si och akassa | L70: Regular
A71: 2015 | B71: 11 | C71: 27 | D71: COM HEM AB | E71: -299 | F71: 0 | G71: =E71 -> -299 | H71: internet | L71: Regular
A72: 2015 | B72: 11 | C72: 27 | D72: AKADEMIKERFÖ | E72: -303 | F72: 0 | G72: =E72 -> -303 | H72: liv- o sjukförsäkring etc | L72: Regular
A73: 2015 | B73: 11 | C73: 26 | D73: OL REPUBLIKEN GOTEBORG | E73: -141 | F73: 0 | G73: =E73 -> -141 | H73: mat i samband med supa | L73: Regular
A74: 2015 | B74: 11 | C74: 26 | D74: LUX RÄNTA | E74: -1250 | F74: 0 | G74: =E74 -> -1250 | H74: spara till amortering | L74: Regular
A75: 2015 | B75: 11 | C75: 26 | D75: JAFARIS DONUTS G@TEBORG | E75: -70 | F75: 0 | G75: =E75 -> -70 | H75: mat i samband med supa | L75: Regular
A76: 2015 | B76: 11 | C76: 26 | D76: Harrys G¦teborg G¦teborg | E76: -69 | F76: 0 | G76: =E76 -> -69 | H76: mat i samband med supa | L76: Regular
A77: 2015 | B77: 11 | C77: 26 | D77: Harrys G¦teborg G¦teborg | E77: -65 | F77: 0 | G77: =E77 -> -65 | H77: mat i samband med supa | L77: Regular
... A127: 2015 | B127: 10 | C127: 30 | D127: BAHNHOF | E127: -841 | F127: 0 | G127: =E127 -> -841 | H127: internet | L127: Regular
A128: 2015 | B128: 10 | C128: 30 | D128: 47516877 | E128: 1000 | F128: 0 | G128: =E128 -> 1000 | H128: spara till amortering | L128: Regular
A129: 2015 | B129: 10 | C129: 29 | D129: SV INGENJ | E129: -320 | F129: 0 | G129: =E129 -> -320 | H129: si och akassa | L129: Regular
A130: 2015 | B130: 10 | C130: 29 | D130: SILVIS RESTAURANG GOTEBORG | E130: -880 | F130: 0 | G130: =E130 -> -880 | H130: nöjes utemat | L130: Regular
A131: 2015 | B131: 10 | C131: 29 | D131: OLREPUBLIKEN GOTEBORG | E131: -95 | F131: 0 | G131: =E131 -> -95 | H131: lunch utemat | L131: Regular
A132: 2015 | B132: 10 | C132: 29 | D132: MAIDEN JG | E132: 670 | F132: 0 | G132: =E132 -> 670 | H132: spara till russel övrigt | L132: Regular
A133: 2015 | B133: 10 | C133: 29 | D133: iZ *Blixten Co A Stockholm | E133: -40 | F133: 0 | G133: =E133 -> -40 | H133: spara almänt | L133: Regular
A134: 2015 | B134: 10 | C134: 29 | D134: COM HEM AB | E134: -299 | F134: 0 | G134: =E134 -> -299 | H134: internet | L134: Regular
A135: 2015 | B135: 10 | C135: 29 | D135: AKADEMIKERFÖ | E135: -303 | F135: 0 | G135: =E135 -> -303 | H135: liv- o sjukförsäkring etc | L135: Regular
A136: 2015 | B136: 10 | C136: 28 | D136: UNICEF | E136: -100 | F136: 0 | G136: =E136 -> -100 | H136: röda korset | L136: Regular
A137: 2015 | B137: 10 | C137: 28 | D137: OLREPUBLIKEN GOTEBORG | E137: -95 | F137: 0 | G137: =E137 -> -95 | H137: lunch utemat | L137: Regular
A138: 2015 | B138: 10 | C138: 27 | D138: AQUARELLE ASKIM | E138: -830 | F138: 0 | G138: =E138 -> -830 | H138: lunch utemat | L138: Regular
A139: 2015 | B139: 10 | C139: 26 | D139: TICNET.SE 3 TRANAS -4 | E139: -4690 | F139: 0 | G139: =E139 -> -4690 | H139: spara till russel övrigt | L139: Regular
A140: 2015 | B140: 10 | C140: 26 | D140: TICNET.SE 3 TRANAS -1 | E140: -1130 | F140: 0 | G140: =E140 -> -1130 | H140: spara till russel övrigt | L140: Regular
... A198: 2015 | B198: 9 | C198: 30 | D198: FOLKSAM | E198: -151 | F198: 0 | G198: =E198 -> -151 | H198: hemförsäkring | L198: Regular
A199: 2015 | B199: 9 | C199: 30 | D199: 47516877 | E199: 1000 | F199: 0 | G199: =E199 -> 1000 | H199: spara till amortering | L199: Regular
A200: 2015 | B200: 9 | C200: 29 | D200: TICNET.SE 3 TRANAS | E200: -410 | F200: 0 | G200: =E200 -> -410 | H200: spara till russel övrigt | L200: Regular
A201: 2015 | B201: 9 | C201: 29 | D201: SV INGENJ | E201: -320 | F201: 0 | G201: =E201 -> -320 | H201: si och akassa | L201: Regular
A202: 2015 | B202: 9 | C202: 29 | D202: AKADEMIKERFÖ | E202: -303 | F202: 0 | G202: =E202 -> -303 | H202: liv- o sjukförsäkring etc | L202: Regular
A203: 2015 | B203: 9 | C203: 28 | D203: UNICEF | E203: -100 | F203: 0 | G203: =E203 -> -100 | H203: röda korset | L203: Regular
A204: 2015 | B204: 9 | C204: 28 | D204: PILEG$RDENS SERVICEBUT ASKIM | E204: -55 | F204: 0 | G204: =E204 -> -55 | H204: alkohol | L204: Regular
A205: 2015 | B205: 9 | C205: 28 | D205: LUX RÄNTA | E205: -1250 | F205: 0 | G205: =E205 -> -1250 | H205: spara till amortering | L205: Regular
A206: 2015 | B206: 9 | C206: 28 | D206: COM HEM AB | E206: -299 | F206: 0 | G206: =E206 -> -299 | H206: internet | L206: Regular
A207: 2015 | B207: 9 | C207: 25 | D207: Månadsbuffert | E207: -5000 | F207: 0 | G207: =E207 -> -5000 | H207: - | L207: Regular
A208: 2015 | B208: 9 | C208: 25 | D208: Månadsbuffert | E208: 5000 | F208: 0 | G208: =E208 -> 5000 | H208: - | L208: Regular
A209: 2015 | B209: 9 | C209: 25 | D209: BBQ GALORE FOOD AND DE GOTEBORG | E209: -105 | F209: 0 | G209: =E209 -> -105 | H209: lunch utemat | L209: Regular
A210: 2015 | B210: 9 | C210: 24 | D210: OLREPUBLIKEN GOTEBORG | E210: -95 | F210: -95 | G210: =E210 -> -95 | H210: lunch utemat | L210: Regular
A211: 2015 | B211: 9 | C211: 24 | D211: OLREPUBLIKEN GOTEBORG | E211: -95 | F211: 0 | G211: =E211 -> -95 | H211: lunch utemat | L211: Regular
... A245: 2015 | B245: 9 | C245: 3 | D245: GÖTEBORG ENERG | E245: -173 | F245: 0 | G245: =E245 -> -173 | H245: el | L245: Regular
A246: 2015 | B246: 9 | C246: 3 | D246: 47516877 | E246: 1000 | F246: 0 | G246: =E246 -> 1000 | H246: spara till amortering | L246: Regular
A247: 2015 | B247: 9 | C247: 2 | D247: SEB | E247: -10 | F247: 0 | G247: =E247 -> -10 | H247: spara till sommarrussel | L247: Regular
A248: 2015 | B248: 9 | C248: 2 | D248: Metallica | E248: -625 | F248: 0 | G248: =E248 -> -625 | H248: spara till sommarrussel | L248: Regular
A249: 2015 | B249: 9 | C249: 2 | D249: INTERFLORA FRESH GOTEBORG | E249: -129 | F249: 0 | G249: =E249 -> -129 | H249: presenter | L249: Regular
A250: 2015 | B250: 9 | C250: 2 | D250: FDÄISVVSBH | E250: 6341 | F250: 0 | G250: =E250 -> 6341 | H250: hyra (inkl. 1k amortering) | L250: Regular
A251: 2015 | B251: 9 | C251: 1 | D251: LF | E251: -140 | F251: 0 | G251: =E251 -> -140 | H251: hemförsäkring | L251: Regular
A252: 2015 | B252: 9 | C252: 1 | D252: HS 12151444 | E252: -8903 | F252: 0 | G252: =E252 -> -8903 | H252: hyra (inkl. 1k amortering) | L252: Regular
A253: 2015 | B253: 8 | C253: 31 | D253: PILEGÅRDEN 2 & | E253: -7734 | F253: 0 | G253: =E253 -> -7734 | H253: hyra (inkl. 1k amortering) | L253: Regular
A254: 2015 | B254: 8 | C254: 31 | D254: Periodens köp | E254: -8435.39 | F254: 0 | G254: =E254 -> -8435.39 | H254: spara almänt | L254: Regular
A255: 2015 | B255: 8 | C255: 31 | D255: MARIA ERIKSSON | E255: 765 | F255: 0 | G255: =E255 -> 765 | H255: spara till sommarrussel | L255: Regular
A256: 2015 | B256: 8 | C256: 31 | D256: HSB GÖTEBORG | E256: -4007 | F256: 0 | G256: =E256 -> -4007 | H256: hyra (inkl. 1k amortering) | L256: Regular
A257: 2015 | B257: 8 | C257: 31 | D257: HSB BOKVAR | E257: -207.8 | F257: 0 | G257: =E257 -> -207.8 | H257: hyra (inkl. 1k amortering) | L257: Regular
A258: 2015 | B258: 8 | C258: 31 | D258: CENTRALA STUDI | E258: -3064 | F258: 0 | G258: =E258 -> -3064 | H258: csn | L258: Regular
... A293: 2015 | B293: 8 | C293: 16 | D293: onlinepizza.se Stockholm | E293: -690 | F293: 0 | G293: =E293 -> -690 | H293: nöjes utemat | L293: Regular
A294: 2015 | B294: 8 | C294: 16 | D294: 550755373 | E294: 2000 | F294: 0 | G294: =E294 -> 2000 | H294: spara till russel övrigt | L294: Regular
A295: 2015 | B295: 8 | C295: 15 | D295: Norstaske BAB G¦teborg | E295: -218 | F295: 0 | G295: =E295 -> -218 | H295: nöjes utemat | L295: Regular
A296: 2015 | B296: 8 | C296: 15 | D296: MA CUISINE GOTEBORG | E296: -933 | F296: 0 | G296: =E296 -> -933 | H296: nöjes utemat | L296: Regular
A297: 2015 | B297: 8 | C297: 15 | D297: GOTEBURGARE Goteborg | E297: -78 | F297: 0 | G297: =E297 -> -78 | H297: nöjes utemat | L297: Regular
A298: 2015 | B298: 8 | C298: 14 | D298: PRESSBYR$N 4128115 G@TEBORG | E298: -110 | F298: 0 | G298: =E298 -> -110 | H298: alkohol | L298: Regular
A299: 2015 | B299: 8 | C299: 12 | D299: VILDENS VILLTMAT FALKOPING | E299: -200 | F299: 0 | G299: =E299 -> -200 | H299: nöjes utemat | L299: Regular
A300: 2015 | B300: 8 | C300: 12 | D300: REST SISJ@N ASKIM | E300: -80 | F300: 0 | G300: =E300 -> -80 | H300: lunch utemat | L300: Regular
A301: 2015 | B301: 8 | C301: 12 | D301: BANKOMAT 17.19 | E301: -500 | F301: 0 | G301: =E301 -> -500 | H301: spara till russel övrigt | L301: Regular
A302: 2015 | B302: 8 | C302: 10 | D302: AQUARELLE ASKIM | E302: -830 | F302: 0 | G302: =E302 -> -830 | H302: lunch utemat | L302: Regular
A303: 2015 | B303: 8 | C303: 8 | D303: ELITE PLAZA HOTEL Goteborg | E303: -165 | F303: 0 | G303: =E303 -> -165 | H303: nöjes utemat | L303: Regular
A304: 2015 | B304: 8 | C304: 7 | D304: SANNEGARDENS PIZZERIA Goteborg | E304: -424 | F304: 0 | G304: =E304 -> -424 | H304: nöjes utemat | L304: Regular
A305: 2015 | B305: 8 | C305: 7 | D305: BBQ GALORE FOOD AND DE GOTEBORG | E305: -100 | F305: 0 | G305: =E305 -> -100 | H305: lunch utemat | L305: Regular
A306: 2015 | B306: 8 | C306: 6 | D306: BBQ GALORE FOOD AND DE GOTEBORG | E306: -95 | F306: 0 | G306: =E306 -> -95 | H306: lunch utemat | L306: Regular
... A337: 2015 | B337: 7 | C337: 30 | D337: AKADEMIKERFÖ | E337: -303 | F337: 0 | G337: =E337 -> -303 | H337: liv- o sjukförsäkring etc | L337: Regular
A338: 2015 | B338: 7 | C338: 30 | D338: 47516877 | E338: 1000 | F338: 0 | G338: =E338 -> 1000 | H338: spara till amortering | L338: Regular
A339: 2015 | B339: 7 | C339: 29 | D339: COM HEM AB | E339: -404 | F339: 0 | G339: =E339 -> -404 | H339: internet | L339: Regular
A340: 2015 | B340: 7 | C340: 29 | D340: BBQ GALORE FOOD AND DE GOTEBORG | E340: -95 | F340: 0 | G340: =E340 -> -95 | H340: lunch utemat | L340: Regular
A341: 2015 | B341: 7 | C341: 28 | D341: UNICEF | E341: -100 | F341: 0 | G341: =E341 -> -100 | H341: röda korset | L341: Regular
A342: 2015 | B342: 7 | C342: 28 | D342: CDON SVERIGE MALMO 15 | E342: 15265 | F342: 0 | G342: =E342 -> 15265 | H342: spara almänt | L342: Regular
A343: 2015 | B343: 7 | C343: 28 | D343: BBQ GALORE FOOD AND DE GOTEBORG | E343: -95 | F343: 0 | G343: =E343 -> -95 | H343: lunch utemat | L343: Regular
A344: 2015 | B344: 7 | C344: 27 | D344: Månadsbuffert | E344: -5000 | F344: 0 | G344: =E344 -> -5000 | H344: - | L344: Regular
A345: 2015 | B345: 7 | C345: 27 | D345: Månadsbuffert | E345: 5000 | F345: 0 | G345: =E345 -> 5000 | H345: - | L345: Regular
A346: 2015 | B346: 7 | C346: 27 | D346: LUX RÄNTA | E346: -1250 | F346: 0 | G346: =E346 -> -1250 | H346: spara till amortering | L346: Regular
A347: 2015 | B347: 7 | C347: 27 | D347: BBQ GALORE FOOD AND DE GOTEBORG | E347: -95 | F347: 0 | G347: =E347 -> -95 | H347: lunch utemat | L347: Regular
...

Sheet Budget (2015)
B1: Allkonto, plus annat | C1: ' 629 011 192 | F1: Löne | G1: Kontonummer: | H1: ' 629010552 | J1: Clearing HB | K1: ' 6241
B2: Senaste uppdaterad | C2: Idag | D2: Uppd.historik | F2: =CONCATENATE(G8," ",F8) -> Kontoutdrag FEL! 81545,8099999998 | H2: Statad troligt | I2: 38201 | X2: y | Y2: m | Z2: d | AA2: n | AB2: t | AC2: g | AD2: s | AE2: b | AI2: c
B3: 42270 | C3: =TODAY() -> 46136 | D3: (eg. 2009-08-22 - 23), 2009-08-23, 2009-03-26, 2010-07-28 | F3: =F12 -> FEL! | G3: =G13 -> 81111.81 | H3: =F12 -> FEL! | I3: =F12 -> FEL! | J3: =F12 -> FEL! | K3: =F12 -> FEL! | L3: =F12 -> FEL! | M3: =F12 -> FEL! | N3: =F12 -> FEL! | O3: =F12 -> FEL! | P3: =F12 -> FEL! | Q3: =F12 -> FEL! | R3: =F12 -> FEL! | AI3: Regular
B4: Russel/vecka | C4: =D17 -> -2798.0773 | D4: =D15 -> -2798.0773 | G4: =IF(NOT(ROUND(G13,0)=0),G13,"") -> 81111.81 | H4: =IF(G4="","",H13) -> <= detta felar
C6: år | D6: =VALUE(LEFT(RIGHT(sheetname(B1),LEN(sheetname(B1))-SEARCH("(",sheetname(B1),1)),SEARCH(")",sheetname(B1),1)-(1+SEARCH("(",sheetname(B1),1)))) -> #NAME? | E6: (Kvar ref) | F6: Från tidigare | G6: Januari | H6: Februari | I6: Mars | J6: April | K6: Maj | L6: Juni | M6: Juli | N6: Augusti | O6: September | P6: Oktober | Q6: November | R6: December | S6: Summa
B7: Temp (kompensera för utlägg på Lönkonto) | C7: 0 | F7: Betalade kreditfakturor | G7: =0 -> 0 | H7: Saldo Allkonto: | I7: Saldo: | J7: =Kontoutdrag_officiella!N1+0 -> 0 | R7: Saldo Lönekonto: | S7: =Kontoutdrag_officiella!M1+0 -> 0 | U7: : Saldo Lönekonto:
B8: på konto VERKLIGA | C8: =J7+C7+S8 -> -2500 | D8: Utan lägga undan | F8: =C8-C9-J12 -> 81545.81 | G8: =IF((ROUND((F8),2))=0,"Kontoutdrag Stämmer","Kontoutdrag FEL!") -> Kontoutdrag FEL! | I8: Ej fakturerat: | J8: =Kontoutdrag_officiella!O1+0 -> 0 | S8: =S7-2500 -> -2500
B9: Bör vara | C9: =DSUM(Kontoutdrag_officiella!$A:$L,"t",X2:AI3) -> -84045.81 | D9: =C8-C9 -> 81545.81 | F9: <--Ev. Fel | I9: Fakturerat, ej förfallet: | J9: =Kontoutdrag_officiella!P1+0 -> 0
B10: Lägga undan | C10: =S144+1000 -> -83611.81 | D10: =C9-C10 -> -434 | F10: =#REF! -> #REF! | G10: UtLånat | I10: Ofakturerade transaktioner: | J10: 0
C11: Stulet-> | D11: =D9-J12+G7 -> 81545.81 | G11: Kredit ej betald | I11: Fakturerat ej förfallet: | J11: 0
B12: Kvar | C12: =C8-C10 -> 81111.81 | D12: <----------------------- | F12: =IF((ROUND((G12-C12),2))=0,"Stämmer","FEL!") -> FEL! | G12: =J12 -> 0 | H12: =stämmer? | I12: =IF((ROUND((G12-C12),2))=0,"Stämmer","FEL!") -> FEL! | J12: =-1*SUM(J8:J11) -> 0
C13: =C8-G12 -> -2500 | D13: <--Detta är så mycket som finns att spendera | G13: =C12-G12 -> 81111.81 | H13: <= detta felar
C14: Bara a | D14: Både r o a
B15: Russel Kvar | C15: =V160 -> -7027.3173 | D15: =V142 -> -2798.0773 | G15: Pengar in, datum: | H15: 38985 | I15: 39015 | J15: 39045 | K15: 39073 | M15: 39136 | N15: 38799 | O15: 38832 | P15: 38862 | W15: Med sparat
B16: Me kontant | C16: =C15 -> -7027.3173 | D16: =D15 -> -2798.0773 | F16: Idag | G16: Pengar in | H16: Dagar kvar | I16: Veckor kvar | J16: Avrundade Veckor | L16: Eget Val av veckor kvar | N16: 1850/4= | P16: dagar i månaden | S16: Russel | U16: veckor | V16: per vecka | W16: =S17-500*2 -> 131.72
B17: Russel/vecka | C17: =C15/J17 -> -7027.3173 | D17: =D15/J17 -> -2798.0773 | F17: =DAY(TODAY()) -> 24 | G17: 25 | H17: =G17-(IF((G17-F17)<1,IF(F17-G17,F17-P17,F17-P17),F17)) -> 1 | I17: =H17/7 -> 0.14285714 | J17: =ROUNDUP(I17,0) -> 1 | L17: 5 | M17: =D15/L17 -> -559.61545 | N17: =1850/4 -> 462.5 | P17: 31 | S17: =C48 -> 1131.72 | U17: 4.5 | V17: =S17/U17 -> 251.49333 | W17: =W16/U17 -> 29.271111
B18: (Exakt) | C18: =C15/I17 -> -49191.221 | D18: =D15/I17 -> -19586.541 | F18: Kr om dan | G18: =D15/H17 -> -2798.0773 | H18: veckodag | I18: =D15/(I17*5) -> -3917.3082
I19: Ovan fungerar enl. följande, det som finns på konot pytsas ut till olika potter, sen när inkomst kommer så drar man av det och sätter det på nästa månads pyttsar, så det blir en illusion av förskjutning, men allt är i sin ordning för lönen används till nä | S19: Tot ^ | U19: Per mån ^
C20: =C13-C10 -> 81111.81
B21: Buffert, som lönekvot | C21: =C10/C62 -> -2.8781044 | F21: Antalet arbetsdagar under ett år skiftar mellan 224 och 229 beroende på
C22: =C8/C62 -> -0.086055557 | D22: =(C8+10000+20000)/C62 -> 0.94661113 | E22: =SUM(E40:E42)/SUM(C40:C41) -> -5.0599239
A23: In | B23: IN | C23: IN | D23: IN | F23: IN | G23: IN | H23: IN | I23: IN | J23: IN | K23: IN | L23: IN | M23: IN | N23: IN | O23: IN | P23: IN | Q23: IN | R23: IN | S23: IN | W23: Dra in
A24: In | C24: Ändra helst bara varje år | D24: Kompensation av felgissade potter | E24: Kvar ref
A25: In | B25: hyra (inkl. 1k amortering) | C25: =3851+5742+1205+37-635-1250+3333 -> 12283 | E25: =S111 -> -32357 | F25: ='Budget (2014)'!S111+D25 -> 21176.6 | G25: =3851+5742+1205+37-635-1250+3333 -> 12283 | H25: =3851+5742+1205+37-635-1250+3333 -> 12283 | I25: =3851+5742+1205+37-635-1250+3333 -> 12283 | J25: =3851+5742+1205+37-635-1250+3333 -> 12283 | K25: =3851+5742+1205+37-635-1250+3333 -> 12283 | L25: =3851+5742+1205+37-635-1250+3333 -> 12283 | M25: =3851+5742+1205+37-635-1250+3333 -> 12283 | N25: =3851+5742+1205+37-635-1250+3333 -> 12283 | ... R25: =3851+5742+1205+37-635-1250+3333 -> 12283 | S25: =SUM(G25:R25) -> 147396 | T25: hyra (inkl. 1k amortering)
A26: In | B26: si och akassa | C26: =-50+720/2+4+4+2 -> 320 | E26: =S112 -> 0 | F26: ='Budget (2014)'!S112+D26 -> 0 | G26: =-50+720/2+4+4+2 -> 320 | H26: =-50+720/2+4+4+2 -> 320 | I26: =-50+720/2+4+4+2 -> 320 | J26: =-50+720/2+4+4+2 -> 320 | K26: =-50+720/2+4+4+2 -> 320 | L26: =-50+720/2+4+4+2 -> 320 | M26: =-50+720/2+4+4+2 -> 320 | N26: =-50+720/2+4+4+2 -> 320 | ... R26: =-50+720/2+4+4+2 -> 320 | S26: =SUM(G26:R26) -> 3840 | T26: si och akassa
A27: In | B27: hemförsäkring | C27: =108+11 -> 119 | E27: =S113 -> -406 | F27: ='Budget (2014)'!S113+D27 -> -46 | G27: =108+11 -> 119 | H27: =108+11 -> 119 | I27: =108+11 -> 119 | J27: =108+11 -> 119 | K27: =108+11 -> 119 | L27: =108+11 -> 119 | M27: =108+11 -> 119 | N27: =108+11 -> 119 | ... R27: =108+11 -> 119 | S27: =SUM(G27:R27) -> 1428 | T27: hemförsäkring
A28: In | B28: liv- o sjukförsäkring etc | C28: 280 | E28: =S114 -> -349 | F28: ='Budget (2014)'!S114+D28 -> -78 | G28: 280 | H28: 280 | I28: 280 | J28: 280 | K28: 280 | L28: 280 | M28: 280 | N28: 280 | O28: 280 | P28: 280 | Q28: 280 | R28: 280 | S28: =SUM(G28:R28) -> 3360 | T28: liv- o sjukförsäkring etc | W28: =R28 -> 280
A29: In | B29: stockholms stads bostadskö | C29: =225/12 -> 18.75 | E29: =S115 -> 225 | F29: ='Budget (2014)'!S115+D29 -> 0 | G29: =225/12 -> 18.75 | H29: =225/12 -> 18.75 | I29: =225/12 -> 18.75 | J29: =225/12 -> 18.75 | K29: =225/12 -> 18.75 | L29: =225/12 -> 18.75 | M29: =225/12 -> 18.75 | N29: =225/12 -> 18.75 | ... R29: =225/12 -> 18.75 | S29: =SUM(G29:R29) -> 225 | T29: stockholms stads bostadskö
A30: In | B30: csn | C30: =(0*(1000+(216/3))+((120+12923)/12))*0+(120+2917+3037*2+3035)/12 -> 1012.1667 | E30: =S116 -> -89 | F30: ='Budget (2014)'!S116+D30 -> 18 | G30: =(0*(1000+(216/3))+((120+12923)/12))*0+(120+2917+3037*2+3035)/12 -> 1012.1667 | H30: =(0*(1000+(216/3))+((120+12923)/12))*0+(120+2917+3037*2+3035)/12 -> 1012.1667 | I30: =(0*(1000+(216/3))+((120+12923)/12))*0+(120+2917+3037*2+3035)/12 -> 1012.1667 | J30: =(0*(1000+(216/3))+((120+12923)/12))*0+(120+2917+3037*2+3035)/12 -> 1012.1667 | K30: =(0*(1000+(216/3))+((120+12923)/12))*0+(120+2917+3037*2+3035)/12 -> 1012.1667 | L30: =(0*(1000+(216/3))+((120+12923)/12))*0+(120+2917+3037*2+3035)/12 -> 1012.1667 | M30: =(0*(1000+(216/3))+((120+12923)/12))*0+(120+2917+3037*2+3035)/12 -> 1012.1667 | N30: =(0*(1000+(216/3))+((120+12923)/12))*0+(120+2917+3037*2+3035)/12 -> 1012.1667 | ... R30: =(0*(1000+(216/3))+((120+12923)/12))*0+(120+2917+3037*2+3035)/12 -> 1012.1667 | S30: =SUM(G30:R30) -> 12146 | T30: csn
A31: In | B31: röda korset | C31: =100+50 -> 150 | E31: =S117 -> -1874 | F31: ='Budget (2014)'!S117+D31 -> 600 | G31: =100+50 -> 150 | H31: =100+50 -> 150 | I31: =100+50 -> 150 | J31: =100+50 -> 150 | K31: =100+50 -> 150 | L31: =100+50 -> 150 | M31: =100+50 -> 150 | N31: =100+50 -> 150 | ... R31: =100+50 -> 150 | S31: =SUM(G31:R31) -> 1800 | T31: röda korset
A32: In | B32: el | C32: =0*355.9+200 -> 200 | E32: =S118 -> 533 | F32: ='Budget (2014)'!S118+D32 -> 373 | G32: =0*355.9+200 -> 200 | H32: =0*355.9+200 -> 200 | I32: =0*355.9+200 -> 200 | J32: =0*355.9+200 -> 200 | K32: =0*355.9+200 -> 200 | L32: =0*355.9+200 -> 200 | M32: =0*355.9+200 -> 200 | N32: =0*355.9+200 -> 200 | ... R32: =0*355.9+200 -> 200 | S32: =SUM(G32:R32) -> 2400 | T32: el
A33: In | B33: internet | C33: =188*0+299 -> 299 | E33: =S119 -> -1710 | F33: ='Budget (2014)'!S119+D33 -> 0 | G33: =188*0+299 -> 299 | H33: =188*0+299 -> 299 | I33: =188*0+299 -> 299 | J33: =188*0+299 -> 299 | K33: =188*0+299 -> 299 | L33: =188*0+299 -> 299 | M33: =188*0+299 -> 299 | N33: =188*0+299 -> 299 | ... R33: =188*0+299 -> 299 | S33: =SUM(G33:R33) -> 3588 | T33: internet
A34: In | B34: telefonsamtal | C34: =(39+69+120)*0+(299+15+40)*0+339*0+(354-339)*0+220+299-50+50 -> 519 | E34: =S120 -> 5914 | F34: ='Budget (2014)'!S120+D34 -> 255 | G34: =(39+69+120)*0+(299+15+40)*0+339*0+(354-339)*0+220+299-50+50 -> 519 | H34: =(39+69+120)*0+(299+15+40)*0+339*0+(354-339)*0+220+299-50+50 -> 519 | I34: =(39+69+120)*0+(299+15+40)*0+339*0+(354-339)*0+220+299-50+50 -> 519 | J34: =(39+69+120)*0+(299+15+40)*0+339*0+(354-339)*0+220+299-50+50 -> 519 | K34: =(39+69+120)*0+(299+15+40)*0+339*0+(354-339)*0+220+299-50+50 -> 519 | L34: =(39+69+120)*0+(299+15+40)*0+339*0+(354-339)*0+220+299-50+50 -> 519 | M34: =(39+69+120)*0+(299+15+40)*0+339*0+(354-339)*0+220+299-50+50 -> 519 | N34: =(39+69+120)*0+(299+15+40)*0+339*0+(354-339)*0+220+299-50+50 -> 519 | ... R34: =(39+69+120)*0+(299+15+40)*0+339*0+(354-339)*0+220+299-50+50 -> 519 | S34: =SUM(G34:R34) -> 6228 | T34: telefonsamtal | W34: =R34-40 -> 479
A35: In | B35: hygien (disk, tvätt o tvål etc) | C35: =20+10 -> 30 | E35: =S121 -> 720 | F35: ='Budget (2014)'!S121+D35 -> 360 | G35: =20+10 -> 30 | H35: =20+10 -> 30 | I35: =20+10 -> 30 | J35: =20+10 -> 30 | K35: =20+10 -> 30 | L35: =20+10 -> 30 | M35: =20+10 -> 30 | N35: =20+10 -> 30 | ... R35: =20+10 -> 30 | S35: =SUM(G35:R35) -> 360 | T35: hygien (disk, tvätt o tvål etc)
A36: In | B36: hemlagad mat | C36: =850+50-300 -> 600 | E36: =S122 -> 3509.24 | F36: ='Budget (2014)'!S122+D36 -> 3492.93 | G36: =850+50-300 -> 600 | H36: =850+50-300 -> 600 | I36: =850+50-300 -> 600 | J36: =850+50-300 -> 600 | K36: =850+50-300 -> 600 | L36: =850+50-300 -> 600 | M36: =850+50-300 -> 600 | N36: =850+50-300 -> 600 | ... R36: =850+50-300 -> 600 | S36: =SUM(G36:R36) -> 7200 | T36: hemlagad mat
A37: In | B37: hemlagad lunch | C37: =(226/12)*(15+20)*0.5*0+50*0 -> 0 | E37: =S123 -> 0 | F37: ='Budget (2014)'!S123+D37 -> 0 | G37: =(226/12)*(15+20)*0.5*0+50*0 -> 0 | H37: =(226/12)*(15+20)*0.5*0+50*0 -> 0 | I37: =(226/12)*(15+20)*0.5*0+50*0 -> 0 | J37: =(226/12)*(15+20)*0.5*0+50*0 -> 0 | K37: =(226/12)*(15+20)*0.5*0+50*0 -> 0 | L37: =(226/12)*(15+20)*0.5*0+50*0 -> 0 | M37: =(226/12)*(15+20)*0.5*0+50*0 -> 0 | N37: =(226/12)*(15+20)*0.5*0+50*0 -> 0 | ... R37: =(226/12)*(15+20)*0.5*0+50*0 -> 0 | S37: =SUM(G37:R37) -> 0 | T37: hemlagad lunch
A38: In | B38: lunch utemat | C38: =((780/11)*227)/12+10*10 -> 1441.3636 | E38: =S124 -> 4211.7273 | F38: ='Budget (2014)'!S124+D38 -> 2622.3636 | G38: =((780/11)*227)/12+10*10 -> 1441.3636 | H38: =((780/11)*227)/12+10*10 -> 1441.3636 | I38: =((780/11)*227)/12+10*10 -> 1441.3636 | J38: =((780/11)*227)/12+10*10 -> 1441.3636 | K38: =((780/11)*227)/12+10*10 -> 1441.3636 | L38: =((780/11)*227)/12+10*10 -> 1441.3636 | M38: =((780/11)*227)/12+10*10 -> 1441.3636 | N38: =((780/11)*227)/12+10*10 -> 1441.3636 | ... R38: =((780/11)*227)/12+10*10 -> 1441.3636 | S38: =SUM(G38:R38) -> 17296.364 | T38: lunch utemat | V38: russel tot | W38: =R38-45 -> 1396.3636
A39: In | B39: nöjes utemat | C39: =(300*2+250*2)*0+(900+500)*1+0*(45*5*4.5+450)+800-100 -> 2100 | E39: =S125 -> 7655.21 | F39: ='Budget (2014)'!S125+D39 -> 7804.36 | G39: =(300*2+250*2)*0+(900+500)*1+0*(45*5*4.5+450)+800-100 -> 2100 | H39: =(300*2+250*2)*0+(900+500)*1+0*(45*5*4.5+450)+800-100 -> 2100 | I39: =(300*2+250*2)*0+(900+500)*1+0*(45*5*4.5+450)+800-100 -> 2100 | J39: =(300*2+250*2)*0+(900+500)*1+0*(45*5*4.5+450)+800-100 -> 2100 | K39: =(300*2+250*2)*0+(900+500)*1+0*(45*5*4.5+450)+800-100 -> 2100 | L39: =(300*2+250*2)*0+(900+500)*1+0*(45*5*4.5+450)+800-100 -> 2100 | M39: =(300*2+250*2)*0+(900+500)*1+0*(45*5*4.5+450)+800-100 -> 2100 | N39: =(300*2+250*2)*0+(900+500)*1+0*(45*5*4.5+450)+800-100 -> 2100 | ... R39: =(300*2+250*2)*0+(900+500)*1+0*(45*5*4.5+450)+800-100 -> 2100 | S39: =SUM(G39:R39) -> 25200 | T39: nöjes utemat | V39: =C39+C40+C41+C42+C43+C52+C55+C56 -> 4274.9997
A40: In | B40: mat i samband med supa | C40: =2*250*0+1477.49969696969 -> 1477.4997 | E40: =S126 -> -6552.3673 | F40: ='Budget (2014)'!S126+D40 -> 7266.1964 | G40: =2*250*0+1477.49969696969 -> 1477.4997 | H40: =2*250*0+1477.49969696969 -> 1477.4997 | I40: =2*250*0+1477.49969696969 -> 1477.4997 | J40: =2*250*0+1477.49969696969 -> 1477.4997 | K40: =2*250*0+1477.49969696969 -> 1477.4997 | L40: =2*250*0+1477.49969696969 -> 1477.4997 | M40: =2*250*0+1477.49969696969 -> 1477.4997 | N40: =2*250*0+1477.49969696969 -> 1477.4997 | ... R40: =2*250*0+1477.49969696969 -> 1477.4997 | S40: =SUM(G40:R40) -> 17729.996 | T40: mat i samband med supa | W40: =R40-50 -> 1427.4997 | X40: =17-14 -> 3
A41: In | B41: alkohol | C41: =500*2-1000+4.5*55 -> 247.5 | E41: =S127 -> -1188 | F41: ='Budget (2014)'!S127+D41 -> -1699 | G41: =500*2-1000+4.5*55 -> 247.5 | H41: =500*2-1000+4.5*55 -> 247.5 | I41: =500*2-1000+4.5*55 -> 247.5 | J41: =500*2-1000+4.5*55 -> 247.5 | K41: =500*2-1000+4.5*55 -> 247.5 | L41: =500*2-1000+4.5*55 -> 247.5 | M41: =500*2-1000+4.5*55 -> 247.5 | N41: =500*2-1000+4.5*55 -> 247.5 | ... R41: =500*2-1000+4.5*55 -> 247.5 | S41: =SUM(G41:R41) -> 2970 | T41: alkohol | W41: =R41-50 -> 197.5
A42: In | B42: taxi efter supa | C42: =150*0 -> 0 | E42: =S128 -> -988 | F42: ='Budget (2014)'!S128+D42 -> -488 | G42: =150*0 -> 0 | H42: =150*0 -> 0 | I42: =150*0 -> 0 | J42: =150*0 -> 0 | K42: =150*0 -> 0 | L42: =150*0 -> 0 | M42: =150*0 -> 0 | N42: =150*0 -> 0 | ... R42: =150*0 -> 0 | S42: =SUM(G42:R42) -> 0 | T42: taxi efter supa | W42: =R42-0 -> 0
A43: In | B43: Buss etc i samband med supa | C43: =5*0 -> 0 | E43: =S129 -> 0 | F43: ='Budget (2014)'!S129+D43 -> 0 | G43: =5*0 -> 0 | H43: =5*0 -> 0 | I43: =5*0 -> 0 | J43: =5*0 -> 0 | K43: =5*0 -> 0 | L43: =5*0 -> 0 | M43: =5*0 -> 0 | N43: =5*0 -> 0 | ... R43: =5*0 -> 0 | S43: =SUM(G43:R43) -> 0 | T43: Buss etc i samband med supa | W43: =R43-10 -> -10
A44: In | B44: oväntade utgifter | C44: 100 | E44: =S130 -> 1192 | F44: ='Budget (2014)'!S130+D44 -> 24 | G44: 100 | H44: 100 | I44: 100 | J44: 100 | K44: 100 | L44: 100 | M44: 100 | N44: 100 | O44: 100 | P44: 100 | Q44: 100 | R44: 100 | S44: =SUM(G44:R44) -> 1200 | T44: oväntade utgifter
A45: In | B45: Småresor ej supa | C45: =10+(1365*2)/12+(((550*3)-1365)*2/12) -> 285 | E45: =S131 -> -4201 | F45: ='Budget (2014)'!S131+D45 -> -3362 | G45: =10+(1365*2)/12+(((550*3)-1365)*2/12) -> 285 | H45: =10+(1365*2)/12+(((550*3)-1365)*2/12) -> 285 | I45: =10+(1365*2)/12+(((550*3)-1365)*2/12) -> 285 | J45: =10+(1365*2)/12+(((550*3)-1365)*2/12) -> 285 | K45: =10+(1365*2)/12+(((550*3)-1365)*2/12) -> 285 | L45: =10+(1365*2)/12+(((550*3)-1365)*2/12) -> 285 | M45: =10+(1365*2)/12+(((550*3)-1365)*2/12) -> 285 | N45: =10+(1365*2)/12+(((550*3)-1365)*2/12) -> 285 | ... R45: =10+(1365*2)/12+(((550*3)-1365)*2/12) -> 285 | S45: =SUM(G45:R45) -> 3420 | T45: Småresor ej supa
A46: In | B46: resor i samband med utflykt | C46: =50+500*0+250-50 -> 250 | E46: =S132 -> 3204 | F46: ='Budget (2014)'!S132+D46 -> 1453 | G46: =50+500*0+250-50 -> 250 | H46: =50+500*0+250-50 -> 250 | I46: =50+500*0+250-50 -> 250 | J46: =50+500*0+250-50 -> 250 | K46: =50+500*0+250-50 -> 250 | L46: =50+500*0+250-50 -> 250 | M46: =50+500*0+250-50 -> 250 | N46: =50+500*0+250-50 -> 250 | ... R46: =50+500*0+250-50 -> 250 | S46: =SUM(G46:R46) -> 3000 | T46: resor i samband med utflykt | W46: =R46 -> 250
A47: In | B47: värnamoresor+övriga | C47: =200/2+100 -> 200 | E47: =S133 -> -1538 | F47: ='Budget (2014)'!S133+D47 -> -1417 | G47: =200/2+100 -> 200 | H47: =200/2+100 -> 200 | I47: =200/2+100 -> 200 | J47: =200/2+100 -> 200 | K47: =200/2+100 -> 200 | L47: =200/2+100 -> 200 | M47: =200/2+100 -> 200 | N47: =200/2+100 -> 200 | ... R47: =200/2+100 -> 200 | S47: =SUM(G47:R47) -> 2400 | T47: värnamoresor+övriga
A48: In | B48: spara almänt | C48: =444.75+274.75-1.78-115-1-300-50-150+1000+30 -> 1131.72 | E48: =S134 -> -185463.58 | F48: ='Budget (2014)'!S134+D48 -> -8328.16 | G48: =444.75+274.75-1.78-115-1-300-50-150+1000+30+2350 -> 3481.72 | H48: =444.75+274.75-1.78-115-1-300-50-150+1000+30-778 -> 353.72 | I48: =444.75+274.75-1.78-115-1-300-50-150+1000+30+162 -> 1293.72 | J48: =444.75+274.75-1.78-115-1-300-50-150+1000+30-610 -> 521.72 | K48: =444.75+274.75-1.78-115-1-300-50-150+1000+30-1550 -> -418.28 | L48: =444.75+274.75-1.78-115-1-300-50-150+1000+30-778 -> 353.72 | M48: =444.75+274.75-1.78-115-1-300-50-150+1000+30+632 -> 1763.72 | N48: =444.75+274.75-1.78-115-1-300-50-150+1000+30+632+2396 -> 4159.72 | O48: =444.75+274.75-1.78-115-1-300-50-150+1000+30+632-392 -> 1371.72 | P48: =444.75+274.75-1.78-115-1-300-50-150+1000+30+632+940 -> 2703.72 | Q48: =444.75+274.75-1.78-115-1-300-50-150+1000+30+632-878 -> 885.72 | R48: =444.75+274.75-1.78-115-1-300-50-150+1000+30+632-996 -> 767.72 | S48: =SUM(G48:R48) -> 17238.64 | T48: spara almänt
A49: In | B49: spara till amortering | C49: =3*1250+350+(2680*0.25)+870+700-3333-500 -> 2507 | E49: =S135 -> 142824 | F49: ='Budget (2014)'!S135+D49 -> 55475 | G49: =3*1250+350+(2680*0.25)+870+700-3333-500 -> 2507 | H49: =3*1250+350+(2680*0.25)+870+700-3333-500 -> 2507 | I49: =3*1250+350+(2680*0.25)+870+700-3333-500 -> 2507 | J49: =3*1250+350+(2680*0.25)+870+700-3333-500 -> 2507 | K49: =3*1250+350+(2680*0.25)+870+700-3333-500 -> 2507 | L49: =3*1250+350+(2680*0.25)+870+700-3333-500 -> 2507 | M49: =3*1250+350+(2680*0.25)+870+700-3333-500 -> 2507 | N49: =3*1250+350+(2680*0.25)+870+700-3333-500 -> 2507 | ... R49: =3*1250+350+(2680*0.25)+870+700-3333-500 -> 2507 | S49: =SUM(G49:R49) -> 30084 | T49: spara till amortering | V49: SommarRussel plan:
A50: In | B50: spara till sommarrussel | C50: =(3000+3000+9000)/12 -> 1250 | E50: =S136 -> 1351.93 | F50: ='Budget (2014)'!S136+D50 -> -4922.72 | G50: =(3000+3000+9000)/12 -> 1250 | H50: =(3000+3000+9000)/12 -> 1250 | I50: =(3000+3000+9000)/12 -> 1250 | J50: =(3000+3000+9000)/12 -> 1250 | K50: =(3000+3000+9000)/12 -> 1250 | L50: =(3000+3000+9000)/12 -> 1250 | M50: =(3000+3000+9000)/12 -> 1250 | N50: =(3000+3000+9000)/12 -> 1250 | ... R50: =(3000+3000+9000)/12 -> 1250 | S50: =SUM(G50:R50) -> 15000 | T50: spara till sommarrussel | V50: 7600 | W50: =R50 -> 1250
A51: In | B51: spara till dator | C51: =250+100+100-100 -> 350 | E51: =S137 -> 8900 | F51: ='Budget (2014)'!S137+D51 -> 4700 | G51: =250+100+100-100 -> 350 | H51: =250+100+100-100 -> 350 | I51: =250+100+100-100 -> 350 | J51: =250+100+100-100 -> 350 | K51: =250+100+100-100 -> 350 | L51: =250+100+100-100 -> 350 | M51: =250+100+100-100 -> 350 | N51: =250+100+100-100 -> 350 | ... R51: =250+100+100-100 -> 350 | S51: =SUM(G51:R51) -> 4200 | T51: spara till dator | V51: SommarRussel verklighet: | W51: =R51 -> 350
A52: In | B52: spara till russel övrigt | C52: =300+100-50+100 -> 450 | E52: =S138 -> -4339.16 | F52: ='Budget (2014)'!S138+D52 -> -1344.01 | G52: =300+100-50+100 -> 450 | H52: =300+100-50+100 -> 450 | I52: =300+100-50+100 -> 450 | J52: =300+100-50+100 -> 450 | K52: =300+100-50+100 -> 450 | L52: =300+100-50+100 -> 450 | M52: =300+100-50+100 -> 450 | N52: =300+100-50+100 -> 450 | ... R52: =300+100-50+100 -> 450 | S52: =SUM(G52:R52) -> 5400 | T52: spara till russel övrigt | V52: =Kontoutdrag_officiella!#REF! -> #ERROR! | W52: =R52 -> 450
A53: In | B53: kläder | C53: =50+50+20+10+70-50 -> 150 | E53: =S139 -> -3530 | F53: ='Budget (2014)'!S139+D53 -> -1522 | G53: =50+50+20+10+70-50 -> 150 | H53: =50+50+20+10+70-50 -> 150 | I53: =50+50+20+10+70-50 -> 150 | J53: =50+50+20+10+70-50 -> 150 | K53: =50+50+20+10+70-50 -> 150 | L53: =50+50+20+10+70-50 -> 150 | M53: =50+50+20+10+70-50 -> 150 | N53: =50+50+20+10+70-50 -> 150 | ... R53: =50+50+20+10+70-50 -> 150 | S53: =SUM(G53:R53) -> 1800 | T53: kläder | V53: -14746.2 | W53: =R53 -> 150
A54: In | B54: presenter | C54: =500-200+700 -> 1000 | E54: =S140 -> -21032.65 | F54: ='Budget (2014)'!S140+D54 -> -11506.74 | G54: =500-200+700 -> 1000 | H54: =500-200+700 -> 1000 | I54: =500-200+700 -> 1000 | J54: =500-200+700 -> 1000 | K54: =500-200+700 -> 1000 | L54: =500-200+700 -> 1000 | M54: =500-200+700 -> 1000 | N54: =500-200+700 -> 1000 | ... R54: =500-200+700 -> 1000 | S54: =SUM(G54:R54) -> 12000 | T54: presenter | V54: Back | W54: =R54 -> 1000
A55: In | B55: Inträde i samband med supa | C55: =50*0 -> 0 | E55: =S141 -> -5954.16 | F55: ='Budget (2014)'!S141+D55 -> -550 | G55: =50*0 -> 0 | H55: =50*0 -> 0 | I55: =50*0 -> 0 | J55: =50*0 -> 0 | K55: =50*0 -> 0 | L55: =50*0 -> 0 | M55: =50*0 -> 0 | N55: =50*0 -> 0 | ... R55: =50*0 -> 0 | S55: =SUM(G55:R55) -> 0 | T55: Inträde i samband med supa | V55: =V53+V50 -> -7146.2 | W55: =R55 -> 0
A56: In | B56: övrigt i samband med supa | C56: =20*0 -> 0 | E56: =S142 -> 0 | F56: ='Budget (2014)'!S142+D56 -> 0 | G56: =20*0 -> 0 | H56: =20*0 -> 0 | I56: =20*0 -> 0 | J56: =20*0 -> 0 | K56: =20*0 -> 0 | L56: =20*0 -> 0 | M56: =20*0 -> 0 | N56: =20*0 -> 0 | ... R56: =20*0 -> 0 | S56: =SUM(G56:R56) -> 0 | T56: övrigt i samband med supa | V56: Lite oväntat in | W56: =R56 -> 0
A57: In | B57: hushåll, reparationer etc inköp av nya husshållsmaskiner | C57: =(25+50)*0+5*56 -> 280 | E57: =S143 -> 6720 | F57: ='Budget (2014)'!S143+D57 -> 3360 | G57: =(25+50)*0+5*56 -> 280 | H57: =(25+50)*0+5*56 -> 280 | I57: =(25+50)*0+5*56 -> 280 | J57: =(25+50)*0+5*56 -> 280 | K57: =(25+50)*0+5*56 -> 280 | L57: =(25+50)*0+5*56 -> 280 | M57: =(25+50)*0+5*56 -> 280 | N57: =(25+50)*0+5*56 -> 280 | ... R57: =(25+50)*0+5*56 -> 280 | S57: =SUM(G57:R57) -> 3360 | T57: hushåll, reparationer etc inköp av nya husshållsmaskiner | V57: =Kontoutdrag_officiella!G552+Kontoutdrag_officiella!G547 -> -5058
A58: In | B58: Summa | C58: =SUM(C25:C57) -> 29051 | E58: =SUM(E25:E57) -> -84611.81 | F58: =SUM(F25:F57) -> 73716.82 | G58: =SUM(G25:G57) -> 31401 | H58: =SUM(H25:H57) -> 28273 | I58: =SUM(I25:I57) -> 29213 | J58: =SUM(J25:J57) -> 28441 | K58: =SUM(K25:K57) -> 27501 | L58: =SUM(L25:L57) -> 28273 | ... S58: =SUM(S25:S57) -> 352270 | V58: =V57+V55 -> -12204.2 | W58: =SUM(W25:W57) -> 7220.3633
A59: In | B59: Om A-kassa | C59: =C58*0.8 -> 23240.8 | D59: =C58-C59 -> 5810.2 | V59: Om man tar av russel, så ska framtida russel tas in=
B60: Summa utan hyra | C60: =SUM(C26:C57) -> 16768 | D60: =SUM(D26:D54) -> 0 | R60: =K59*C58 -> 0 | V60: =V58+2410.12 -> -9794.08
B61: Summa | C61: =SUM(C25:C57) -> 29051 | D61: =SUM(D25:D57) -> 0 | F61: =SUM(F25:F57) -> 73716.82 | G61: =SUM(G25:G57) -> 31401 | H61: =SUM(H25:H57) -> 28273 | I61: =SUM(I25:I57) -> 29213 | J61: =SUM(J25:J57) -> 28441 | K61: =SUM(K25:K57) -> 27501 | L61: =SUM(L25:L57) -> 28273 | M61: =SUM(M25:M57) -> 29683 | ... R61: =SUM(R25:R57) -> 28687
B62: Planerade Utbetalningar | C62: 29051 | F62: =30599.07-217 -> 30382.07 | G62: =DSUM(Kontoutdrag_officiella!$A:$J,"t",'Villkor 1 år (2015)'!$A799:$J800) -> 31401 | H62: =DSUM(Kontoutdrag_officiella!$A:$J,"t",'Villkor 1 år (2015)'!$A801:$J802) -> 28273 | I62: =DSUM(Kontoutdrag_officiella!$A:$J,"t",'Villkor 1 år (2015)'!$A803:$J804) -> 29213 | J62: =DSUM(Kontoutdrag_officiella!$A:$J,"t",'Villkor 1 år (2015)'!$A805:$J806) -> 28441 | K62: =DSUM(Kontoutdrag_officiella!$A:$J,"t",'Villkor 1 år (2015)'!$A807:$J808) -> 27501 | L62: =DSUM(Kontoutdrag_officiella!$A:$J,"t",'Villkor 1 år (2015)'!$A809:$J810) -> 28273 | M62: =DSUM(Kontoutdrag_officiella!$A:$J,"t",'Villkor 1 år (2015)'!$A811:$J812) -> 29683 | N62: =DSUM(Kontoutdrag_officiella!$A:$J,"t",'Villkor 1 år (2015)'!$A813:$J814) -> 32079 | O62: =DSUM(Kontoutdrag_officiella!$A:$J,"t",'Villkor 1 år (2015)'!$A815:$J816) -> 29291 | P62: =DSUM(Kontoutdrag_officiella!$A:$J,"t",'Villkor 1 år (2015)'!$A817:$J818) -> 30623 | Q62: =DSUM(Kontoutdrag_officiella!$A:$J,"t",'Villkor 1 år (2015)'!$A819:$J820) -> 28805 | R62: =DSUM(Kontoutdrag_officiella!$A:$J,"t",'Villkor 1 år (2015)'!$A821:$J822) -> 28687
B63: Över | C63: =C62-C61 -> 0 | D63: =D62-D61 -> 0 | F63: =F62-F61 -> -43334.75 | G63: =G62-G61 -> 0 | H63: =H62-H61 -> 0 | I63: =I62-I61 -> 0 | J63: =J62-J61 -> 0 | K63: =K62-K61 -> 0 | L63: =L62-L61 -> 0 | M63: =M62-M61 -> 0 | ... R63: =R62-R61 -> 0 | S63: =SUM(F63:R63) -> -43334.75
B64: +/- per år | C64: =C63*12 -> 0 | D64: =D63*12 -> 0 | M64: =M62-L62 -> 1410
B65: In | C65: =C62 -> 29051 | D65: =D62 | G65: Kvar på supa i mån:
B66: Kvar | C66: =C65-C61 -> 0 | D66: =D65-D61 -> 0 | E66: =C66/2 -> 0 | F66: 870.00167 | G66: =E40/C40 -> -4.4347673 | W66: utvald period
B67: Utan hyra | C67: =C66+C25 -> 12283 | D67: =D66+D25 -> 0
B68: Halva kvar (nöje) | C68: =C66/2 -> 0
W70: juni->juli
A71: Ut | B71: UT | C71: UT | D71: UT | F71: UT | G71: UT | H71: UT | I71: UT | J71: UT | K71: UT | L71: UT | M71: UT | N71: UT | O71: UT | P71: UT | Q71: UT | R71: UT | S71: UT | U71: Månader > | V71: 12 | W71: 12
A72: Ut | V72: Snitt/mån | W72: Snitt/mån | X72: Jmfr med plan
A73: Ut | B73: hyra (inkl. 1k amortering) | G73: =DSUM(Kontoutdrag_officiella!$A:$J,"t",'Villkor 1 år (2015)'!$A1:$J2) -> -12400.8 | H73: =DSUM(Kontoutdrag_officiella!$A:$J,"t",'Villkor 1 år (2015)'!$A67:$J68) -> -12182 | I73: =DSUM(Kontoutdrag_officiella!$A:$J,"t",'Villkor 1 år (2015)'!$A133:$J134) -> -12141 | J73: =DSUM(Kontoutdrag_officiella!$A:$J,"t",'Villkor 1 år (2015)'!$A199:$J200) -> -13313.8 | K73: =DSUM(Kontoutdrag_officiella!$A:$J,"t",'Villkor 1 år (2015)'!$A265:$J266) -> -13718.4 | L73: =DSUM(Kontoutdrag_officiella!$A:$J,"t",'Villkor 1 år (2015)'!$A331:$J332) -> -28455 | M73: =DSUM(Kontoutdrag_officiella!$A:$J,"t",'Villkor 1 år (2015)'!$A397:$J398) -> -21110.6 | N73: =DSUM(Kontoutdrag_officiella!$A:$J,"t",'Villkor 1 år (2015)'!$A463:$J464) -> -20892.8 | O73: =DSUM(Kontoutdrag_officiella!$A:$J,"t",'Villkor 1 år (2015)'!$A529:$J530) -> -7001.8 | P73: =DSUM(Kontoutdrag_officiella!$A:$J,"t",'Villkor 1 år (2015)'!$A595:$J596) -> -9926.8 | Q73: =DSUM(Kontoutdrag_officiella!$A:$J,"t",'Villkor 1 år (2015)'!$A661:$J662) -> -21000.8 | R73: =DSUM(Kontoutdrag_officiella!$A:$J,"t",'Villkor 1 år (2015)'!$A727:$J728) -> -28785.8 | S73: =SUM(G73:R73) -> -200929.6 | T73: hyra (inkl. 1k amortering) | U73: =S73-1200 -> -202129.6 | V73: =S73/$V$71 -> -16744.133 | W73: =SUM(S73)/W$71 -> -16744.133 | X73: =C25 -> 12283 | Y73: =C25+V73 -> -4461.1333 | Z73: =S73-7500-3800 -> -212229.6
A74: Ut | B74: si och akassa | G74: =DSUM(Kontoutdrag_officiella!$A:$J,"t",'Villkor 1 år (2015)'!$A3:$J4) -> -320 | H74: =DSUM(Kontoutdrag_officiella!$A:$J,"t",'Villkor 1 år (2015)'!$A69:$J70) -> -320 | I74: =DSUM(Kontoutdrag_officiella!$A:$J,"t",'Villkor 1 år (2015)'!$A135:$J136) -> -320 | J74: =DSUM(Kontoutdrag_officiella!$A:$J,"t",'Villkor 1 år (2015)'!$A201:$J202) -> -320 | K74: =DSUM(Kontoutdrag_officiella!$A:$J,"t",'Villkor 1 år (2015)'!$A267:$J268) -> -320 | L74: =DSUM(Kontoutdrag_officiella!$A:$J,"t",'Villkor 1 år (2015)'!$A333:$J334) -> -320 | M74: =DSUM(Kontoutdrag_officiella!$A:$J,"t",'Villkor 1 år (2015)'!$A399:$J400) -> -320 | N74: =DSUM(Kontoutdrag_officiella!$A:$J,"t",'Villkor 1 år (2015)'!$A465:$J466) -> -320 | O74: =DSUM(Kontoutdrag_officiella!$A:$J,"t",'Villkor 1 år (2015)'!$A531:$J532) -> -320 | P74: =DSUM(Kontoutdrag_officiella!$A:$J,"t",'Villkor 1 år (2015)'!$A597:$J598) -> -320 | Q74: =DSUM(Kontoutdrag_officiella!$A:$J,"t",'Villkor 1 år (2015)'!$A663:$J664) -> -320 | R74: =DSUM(Kontoutdrag_officiella!$A:$J,"t",'Villkor 1 år (2015)'!$A729:$J730) -> -320 | S74: =SUM(G74:R74) -> -3840 | T74: si och akassa | V74: =S74/$V$71 -> -320 | W74: =SUM(S74)/W$71 -> -320 | X74: =C26 -> 320 | Y74: =C26+V74 -> 0 | AA74: =9+1.25-5.4 -> 4.85
A75: Ut | B75: hemförsäkring | G75: =DSUM(Kontoutdrag_officiella!$A:$J,"t",'Villkor 1 år (2015)'!$A5:$J6) -> -130 | H75: =DSUM(Kontoutdrag_officiella!$A:$J,"t",'Villkor 1 år (2015)'!$A71:$J72) -> -130 | I75: =DSUM(Kontoutdrag_officiella!$A:$J,"t",'Villkor 1 år (2015)'!$A137:$J138) -> -130 | J75: =DSUM(Kontoutdrag_officiella!$A:$J,"t",'Villkor 1 år (2015)'!$A203:$J204) -> -130 | K75: =DSUM(Kontoutdrag_officiella!$A:$J,"t",'Villkor 1 år (2015)'!$A269:$J270) -> -130 | L75: =DSUM(Kontoutdrag_officiella!$A:$J,"t",'Villkor 1 år (2015)'!$A335:$J336) -> -130 | M75: =DSUM(Kontoutdrag_officiella!$A:$J,"t",'Villkor 1 år (2015)'!$A401:$J402) -> -130 | N75: =DSUM(Kontoutdrag_officiella!$A:$J,"t",'Villkor 1 år (2015)'!$A467:$J468) -> -130 | O75: =DSUM(Kontoutdrag_officiella!$A:$J,"t",'Villkor 1 år (2015)'!$A533:$J534) -> -291 | P75: =DSUM(Kontoutdrag_officiella!$A:$J,"t",'Villkor 1 år (2015)'!$A599:$J600) -> -153 | Q75: =DSUM(Kontoutdrag_officiella!$A:$J,"t",'Villkor 1 år (2015)'!$A665:$J666) -> -151 | R75: =DSUM(Kontoutdrag_officiella!$A:$J,"t",'Villkor 1 år (2015)'!$A731:$J732) -> -153 | S75: =SUM(G75:R75) -> -1788 | T75: hemförsäkring | V75: =S75/$V$71 -> -149 | W75: =SUM(S75)/W$71 -> -149 | X75: =C27 -> 119 | Y75: =C27+V75 -> -30
A76: Ut | B76: liv- o sjukförsäkring etc | G76: =DSUM(Kontoutdrag_officiella!$A:$J,"t",'Villkor 1 år (2015)'!$A7:$J8) -> -303 | H76: =DSUM(Kontoutdrag_officiella!$A:$J,"t",'Villkor 1 år (2015)'!$A73:$J74) -> -303 | I76: =DSUM(Kontoutdrag_officiella!$A:$J,"t",'Villkor 1 år (2015)'!$A139:$J140) -> -303 | J76: =DSUM(Kontoutdrag_officiella!$A:$J,"t",'Villkor 1 år (2015)'!$A205:$J206) -> -303 | K76: =DSUM(Kontoutdrag_officiella!$A:$J,"t",'Villkor 1 år (2015)'!$A271:$J272) -> -303 | L76: =DSUM(Kontoutdrag_officiella!$A:$J,"t",'Villkor 1 år (2015)'!$A337:$J338) -> -303 | M76: =DSUM(Kontoutdrag_officiella!$A:$J,"t",'Villkor 1 år (2015)'!$A403:$J404) -> -303 | N76: =DSUM(Kontoutdrag_officiella!$A:$J,"t",'Villkor 1 år (2015)'!$A469:$J470) -> -303 | O76: =DSUM(Kontoutdrag_officiella!$A:$J,"t",'Villkor 1 år (2015)'!$A535:$J536) -> -303 | P76: =DSUM(Kontoutdrag_officiella!$A:$J,"t",'Villkor 1 år (2015)'!$A601:$J602) -> -303 | Q76: =DSUM(Kontoutdrag_officiella!$A:$J,"t",'Villkor 1 år (2015)'!$A667:$J668) -> -303 | R76: =DSUM(Kontoutdrag_officiella!$A:$J,"t",'Villkor 1 år (2015)'!$A733:$J734) -> -298 | S76: =SUM(G76:R76) -> -3631 | T76: liv- o sjukförsäkring etc | V76: =S76/$V$71 -> -302.58333 | W76: =SUM(S76)/W$71 -> -302.58333 | X76: =C28 -> 280 | Y76: =C28+V76 -> -22.583333
A77: Ut | B77: stockholms stads bostadskö | G77: =DSUM(Kontoutdrag_officiella!$A:$J,"t",'Villkor 1 år (2015)'!$A9:$J10) -> 0 | H77: =DSUM(Kontoutdrag_officiella!$A:$J,"t",'Villkor 1 år (2015)'!$A75:$J76) -> 0 | I77: =DSUM(Kontoutdrag_officiella!$A:$J,"t",'Villkor 1 år (2015)'!$A141:$J142) -> 0 | J77: =DSUM(Kontoutdrag_officiella!$A:$J,"t",'Villkor 1 år (2015)'!$A207:$J208) -> 0 | K77: =DSUM(Kontoutdrag_officiella!$A:$J,"t",'Villkor 1 år (2015)'!$A273:$J274) -> 0 | L77: =DSUM(Kontoutdrag_officiella!$A:$J,"t",'Villkor 1 år (2015)'!$A339:$J340) -> 0 | M77: =DSUM(Kontoutdrag_officiella!$A:$J,"t",'Villkor 1 år (2015)'!$A405:$J406) -> 0 | N77: =DSUM(Kontoutdrag_officiella!$A:$J,"t",'Villkor 1 år (2015)'!$A471:$J472) -> 0 | O77: =DSUM(Kontoutdrag_officiella!$A:$J,"t",'Villkor 1 år (2015)'!$A537:$J538) -> 0 | P77: =DSUM(Kontoutdrag_officiella!$A:$J,"t",'Villkor 1 år (2015)'!$A603:$J604) -> 0 | Q77: =DSUM(Kontoutdrag_officiella!$A:$J,"t",'Villkor 1 år (2015)'!$A669:$J670) -> 0 | R77: =DSUM(Kontoutdrag_officiella!$A:$J,"t",'Villkor 1 år (2015)'!$A735:$J736) -> 0 | S77: =SUM(G77:R77) -> 0 | T77: stockholms stads bostadskö | V77: =S77/$V$71 -> 0 | W77: =SUM(S77)/W$71 -> 0 | X77: =C29 -> 18.75 | Y77: =C29+V77 -> 18.75
A78: Ut | B78: csn | G78: =DSUM(Kontoutdrag_officiella!$A:$J,"t",'Villkor 1 år (2015)'!$A11:$J12) -> 0 | H78: =DSUM(Kontoutdrag_officiella!$A:$J,"t",'Villkor 1 år (2015)'!$A77:$J78) -> -3064 | I78: =DSUM(Kontoutdrag_officiella!$A:$J,"t",'Villkor 1 år (2015)'!$A143:$J144) -> 0 | J78: =DSUM(Kontoutdrag_officiella!$A:$J,"t",'Villkor 1 år (2015)'!$A209:$J210) -> 0 | K78: =DSUM(Kontoutdrag_officiella!$A:$J,"t",'Villkor 1 år (2015)'!$A275:$J276) -> -3064 | L78: =DSUM(Kontoutdrag_officiella!$A:$J,"t",'Villkor 1 år (2015)'!$A341:$J342) -> 0 | M78: =DSUM(Kontoutdrag_officiella!$A:$J,"t",'Villkor 1 år (2015)'!$A407:$J408) -> 0 | N78: =DSUM(Kontoutdrag_officiella!$A:$J,"t",'Villkor 1 år (2015)'!$A473:$J474) -> -3064 | O78: =DSUM(Kontoutdrag_officiella!$A:$J,"t",'Villkor 1 år (2015)'!$A539:$J540) -> 0 | P78: =DSUM(Kontoutdrag_officiella!$A:$J,"t",'Villkor 1 år (2015)'!$A605:$J606) -> 0 | Q78: =DSUM(Kontoutdrag_officiella!$A:$J,"t",'Villkor 1 år (2015)'!$A671:$J672) -> -3061 | R78: =DSUM(Kontoutdrag_officiella!$A:$J,"t",'Villkor 1 år (2015)'!$A737:$J738) -> 0 | S78: =SUM(G78:R78) -> -12253 | T78: csn | V78: =S78/$V$71 -> -1021.0833 | W78: =SUM(S78)/W$71 -> -1021.0833 | X78: =C30 -> 1012.1667 | Y78: =C30+V78 -> -8.9166667
A79: Ut | B79: röda korset | G79: =DSUM(Kontoutdrag_officiella!$A:$J,"t",'Villkor 1 år (2015)'!$A13:$J14) -> -100 | H79: =DSUM(Kontoutdrag_officiella!$A:$J,"t",'Villkor 1 år (2015)'!$A79:$J80) -> 0 | I79: =DSUM(Kontoutdrag_officiella!$A:$J,"t",'Villkor 1 år (2015)'!$A145:$J146) -> -200 | J79: =DSUM(Kontoutdrag_officiella!$A:$J,"t",'Villkor 1 år (2015)'!$A211:$J212) -> -2924 | K79: =DSUM(Kontoutdrag_officiella!$A:$J,"t",'Villkor 1 år (2015)'!$A277:$J278) -> -350 | L79: =DSUM(Kontoutdrag_officiella!$A:$J,"t",'Villkor 1 år (2015)'!$A343:$J344) -> -100 | M79: =DSUM(Kontoutdrag_officiella!$A:$J,"t",'Villkor 1 år (2015)'!$A409:$J410) -> -100 | N79: =DSUM(Kontoutdrag_officiella!$A:$J,"t",'Villkor 1 år (2015)'!$A475:$J476) -> -100 | O79: =DSUM(Kontoutdrag_officiella!$A:$J,"t",'Villkor 1 år (2015)'!$A541:$J542) -> -100 | P79: =DSUM(Kontoutdrag_officiella!$A:$J,"t",'Villkor 1 år (2015)'!$A607:$J608) -> -100 | Q79: =DSUM(Kontoutdrag_officiella!$A:$J,"t",'Villkor 1 år (2015)'!$A673:$J674) -> -100 | R79: =DSUM(Kontoutdrag_officiella!$A:$J,"t",'Villkor 1 år (2015)'!$A739:$J740) -> -100 | S79: =SUM(G79:R79) -> -4274 | T79: röda korset | V79: =S79/$V$71 -> -356.16667 | W79: =SUM(S79)/W$71 -> -356.16667 | X79: =C31 -> 150 | Y79: =C31+V79 -> -206.16667
A80: Ut | B80: el | G80: =DSUM(Kontoutdrag_officiella!$A:$J,"t",'Villkor 1 år (2015)'!$A15:$J16) -> -443 | H80: =DSUM(Kontoutdrag_officiella!$A:$J,"t",'Villkor 1 år (2015)'!$A81:$J82) -> 0 | I80: =DSUM(Kontoutdrag_officiella!$A:$J,"t",'Villkor 1 år (2015)'!$A147:$J148) -> -200 | J80: =DSUM(Kontoutdrag_officiella!$A:$J,"t",'Villkor 1 år (2015)'!$A213:$J214) -> -256 | K80: =DSUM(Kontoutdrag_officiella!$A:$J,"t",'Villkor 1 år (2015)'!$A279:$J280) -> -182 | L80: =DSUM(Kontoutdrag_officiella!$A:$J,"t",'Villkor 1 år (2015)'!$A345:$J346) -> -266 | M80: =DSUM(Kontoutdrag_officiella!$A:$J,"t",'Villkor 1 år (2015)'!$A411:$J412) -> -201 | N80: =DSUM(Kontoutdrag_officiella!$A:$J,"t",'Villkor 1 år (2015)'!$A477:$J478) -> 0 | O80: =DSUM(Kontoutdrag_officiella!$A:$J,"t",'Villkor 1 år (2015)'!$A543:$J544) -> -441 | P80: =DSUM(Kontoutdrag_officiella!$A:$J,"t",'Villkor 1 år (2015)'!$A609:$J610) -> 0 | Q80: =DSUM(Kontoutdrag_officiella!$A:$J,"t",'Villkor 1 år (2015)'!$A675:$J676) -> -251 | R80: =DSUM(Kontoutdrag_officiella!$A:$J,"t",'Villkor 1 år (2015)'!$A741:$J742) -> 0 | S80: =SUM(G80:R80) -> -2240 | T80: el | V80: =S80/$V$71 -> -186.66667 | W80: =SUM(S80)/W$71 -> -186.66667 | X80: =C32 -> 200 | Y80: =C32+V80 -> 13.333333
A81: Ut | B81: internet | G81: =DSUM(Kontoutdrag_officiella!$A:$J,"t",'Villkor 1 år (2015)'!$A17:$J18) -> -299 | H81: =DSUM(Kontoutdrag_officiella!$A:$J,"t",'Villkor 1 år (2015)'!$A83:$J84) -> -299 | I81: =DSUM(Kontoutdrag_officiella!$A:$J,"t",'Villkor 1 år (2015)'!$A149:$J150) -> -96 | J81: =DSUM(Kontoutdrag_officiella!$A:$J,"t",'Villkor 1 år (2015)'!$A215:$J216) -> 0 | K81: =DSUM(Kontoutdrag_officiella!$A:$J,"t",'Villkor 1 år (2015)'!$A281:$J282) -> 0 | L81: =DSUM(Kontoutdrag_officiella!$A:$J,"t",'Villkor 1 år (2015)'!$A347:$J348) -> 0 | M81: =DSUM(Kontoutdrag_officiella!$A:$J,"t",'Villkor 1 år (2015)'!$A413:$J414) -> -2268 | N81: =DSUM(Kontoutdrag_officiella!$A:$J,"t",'Villkor 1 år (2015)'!$A479:$J480) -> -299 | O81: =DSUM(Kontoutdrag_officiella!$A:$J,"t",'Villkor 1 år (2015)'!$A545:$J546) -> -299 | P81: =DSUM(Kontoutdrag_officiella!$A:$J,"t",'Villkor 1 år (2015)'!$A611:$J612) -> -1140 | Q81: =DSUM(Kontoutdrag_officiella!$A:$J,"t",'Villkor 1 år (2015)'!$A677:$J678) -> -299 | R81: =DSUM(Kontoutdrag_officiella!$A:$J,"t",'Villkor 1 år (2015)'!$A743:$J744) -> -299 | S81: =SUM(G81:R81) -> -5298 | T81: internet | V81: =S81/$V$71 -> -441.5 | W81: =SUM(S81)/W$71 -> -441.5 | X81: =C33 -> 299 | Y81: =C33+V81 -> -142.5
A82: Ut | B82: telefonsamtal | G82: =DSUM(Kontoutdrag_officiella!$A:$J,"t",'Villkor 1 år (2015)'!$A19:$J20) -> -569 | H82: =DSUM(Kontoutdrag_officiella!$A:$J,"t",'Villkor 1 år (2015)'!$A85:$J86) -> 0 | I82: =DSUM(Kontoutdrag_officiella!$A:$J,"t",'Villkor 1 år (2015)'!$A151:$J152) -> 0 | J82: =DSUM(Kontoutdrag_officiella!$A:$J,"t",'Villkor 1 år (2015)'!$A217:$J218) -> 0 | K82: =DSUM(Kontoutdrag_officiella!$A:$J,"t",'Villkor 1 år (2015)'!$A283:$J284) -> 0 | L82: =DSUM(Kontoutdrag_officiella!$A:$J,"t",'Villkor 1 år (2015)'!$A349:$J350) -> 0 | M82: =DSUM(Kontoutdrag_officiella!$A:$J,"t",'Villkor 1 år (2015)'!$A415:$J416) -> 0 | N82: =DSUM(Kontoutdrag_officiella!$A:$J,"t",'Villkor 1 år (2015)'!$A481:$J482) -> 0 | O82: =DSUM(Kontoutdrag_officiella!$A:$J,"t",'Villkor 1 år (2015)'!$A547:$J548) -> 0 | P82: =DSUM(Kontoutdrag_officiella!$A:$J,"t",'Villkor 1 år (2015)'!$A613:$J614) -> 0 | Q82: =DSUM(Kontoutdrag_officiella!$A:$J,"t",'Villkor 1 år (2015)'!$A679:$J680) -> 0 | R82: =DSUM(Kontoutdrag_officiella!$A:$J,"t",'Villkor 1 år (2015)'!$A745:$J746) -> 0 | S82: =SUM(G82:R82) -> -569 | T82: telefonsamtal | V82: =S82/$V$71 -> -47.416667 | W82: =SUM(S82)/W$71 -> -47.416667 | X82: =C34 -> 519 | Y82: =C34+V82 -> 471.58333
A83: Ut | B83: hygien (disk, tvätt o tvål etc) | G83: =DSUM(Kontoutdrag_officiella!$A:$J,"t",'Villkor 1 år (2015)'!$A21:$J22) -> 0 | H83: =DSUM(Kontoutdrag_officiella!$A:$J,"t",'Villkor 1 år (2015)'!$A87:$J88) -> 0 | I83: =DSUM(Kontoutdrag_officiella!$A:$J,"t",'Villkor 1 år (2015)'!$A153:$J154) -> 0 | J83: =DSUM(Kontoutdrag_officiella!$A:$J,"t",'Villkor 1 år (2015)'!$A219:$J220) -> 0 | K83: =DSUM(Kontoutdrag_officiella!$A:$J,"t",'Villkor 1 år (2015)'!$A285:$J286) -> 0 | L83: =DSUM(Kontoutdrag_officiella!$A:$J,"t",'Villkor 1 år (2015)'!$A351:$J352) -> 0 | M83: =DSUM(Kontoutdrag_officiella!$A:$J,"t",'Villkor 1 år (2015)'!$A417:$J418) -> 0 | N83: =DSUM(Kontoutdrag_officiella!$A:$J,"t",'Villkor 1 år (2015)'!$A483:$J484) -> 0 | O83: =DSUM(Kontoutdrag_officiella!$A:$J,"t",'Villkor 1 år (2015)'!$A549:$J550) -> 0 | P83: =DSUM(Kontoutdrag_officiella!$A:$J,"t",'Villkor 1 år (2015)'!$A615:$J616) -> 0 | Q83: =DSUM(Kontoutdrag_officiella!$A:$J,"t",'Villkor 1 år (2015)'!$A681:$J682) -> 0 | R83: =DSUM(Kontoutdrag_officiella!$A:$J,"t",'Villkor 1 år (2015)'!$A747:$J748) -> 0 | S83: =SUM(G83:R83) -> 0 | T83: hygien (disk, tvätt o tvål etc) | V83: =S83/$V$71 -> 0 | W83: =SUM(S83)/W$71 -> 0 | X83: =C35 -> 30 | Y83: =C35+V83 -> 30
A84: Ut | B84: hemlagad mat | G84: =DSUM(Kontoutdrag_officiella!$A:$J,"t",'Villkor 1 år (2015)'!$A23:$J24) -> -608.6 | H84: =DSUM(Kontoutdrag_officiella!$A:$J,"t",'Villkor 1 år (2015)'!$A89:$J90) -> 0 | I84: =DSUM(Kontoutdrag_officiella!$A:$J,"t",'Villkor 1 år (2015)'!$A155:$J156) -> 0 | J84: =DSUM(Kontoutdrag_officiella!$A:$J,"t",'Villkor 1 år (2015)'!$A221:$J222) -> 0 | K84: =DSUM(Kontoutdrag_officiella!$A:$J,"t",'Villkor 1 år (2015)'!$A287:$J288) -> 0 | L84: =DSUM(Kontoutdrag_officiella!$A:$J,"t",'Villkor 1 år (2015)'!$A353:$J354) -> 0 | M84: =DSUM(Kontoutdrag_officiella!$A:$J,"t",'Villkor 1 år (2015)'!$A419:$J420) -> -2272.13 | N84: =DSUM(Kontoutdrag_officiella!$A:$J,"t",'Villkor 1 år (2015)'!$A485:$J486) -> -110 | O84: =DSUM(Kontoutdrag_officiella!$A:$J,"t",'Villkor 1 år (2015)'!$A551:$J552) -> -177.86 | P84: =DSUM(Kontoutdrag_officiella!$A:$J,"t",'Villkor 1 år (2015)'!$A617:$J618) -> -483.14 | Q84: =DSUM(Kontoutdrag_officiella!$A:$J,"t",'Villkor 1 år (2015)'!$A683:$J684) -> -915.3 | R84: =DSUM(Kontoutdrag_officiella!$A:$J,"t",'Villkor 1 år (2015)'!$A749:$J750) -> -2616.66 | S84: =SUM(G84:R84) -> -7183.69 | T84: hemlagad mat | V84: =S84/$V$71 -> -598.64083 | W84: =SUM(S84)/W$71 -> -598.64083 | X84: =C36 -> 600 | Y84: =C36+V84 -> 1.3591667
A85: Ut | B85: hemlagad lunch | G85: =DSUM(Kontoutdrag_officiella!$A:$J,"t",'Villkor 1 år (2015)'!$A25:$J26) -> 0 | H85: =DSUM(Kontoutdrag_officiella!$A:$J,"t",'Villkor 1 år (2015)'!$A91:$J92) -> 0 | I85: =DSUM(Kontoutdrag_officiella!$A:$J,"t",'Villkor 1 år (2015)'!$A157:$J158) -> 0 | J85: =DSUM(Kontoutdrag_officiella!$A:$J,"t",'Villkor 1 år (2015)'!$A223:$J224) -> 0 | K85: =DSUM(Kontoutdrag_officiella!$A:$J,"t",'Villkor 1 år (2015)'!$A289:$J290) -> 0 | L85: =DSUM(Kontoutdrag_officiella!$A:$J,"t",'Villkor 1 år (2015)'!$A355:$J356) -> 0 | M85: =DSUM(Kontoutdrag_officiella!$A:$J,"t",'Villkor 1 år (2015)'!$A421:$J422) -> 0 | N85: =DSUM(Kontoutdrag_officiella!$A:$J,"t",'Villkor 1 år (2015)'!$A487:$J488) -> 0 | O85: =DSUM(Kontoutdrag_officiella!$A:$J,"t",'Villkor 1 år (2015)'!$A553:$J554) -> 0 | P85: =DSUM(Kontoutdrag_officiella!$A:$J,"t",'Villkor 1 år (2015)'!$A619:$J620) -> 0 | Q85: =DSUM(Kontoutdrag_officiella!$A:$J,"t",'Villkor 1 år (2015)'!$A685:$J686) -> 0 | R85: =DSUM(Kontoutdrag_officiella!$A:$J,"t",'Villkor 1 år (2015)'!$A751:$J752) -> 0 | S85: =SUM(G85:R85) -> 0 | T85: hemlagad lunch | V85: =S85/$V$71 -> 0 | W85: =SUM(S85)/W$71 -> 0 | X85: =C37 -> 0 | Y85: =C37+V85 -> 0 | Z85: L ute okt+nov
A86: Ut | B86: lunch utemat | G86: =DSUM(Kontoutdrag_officiella!$A:$J,"t",'Villkor 1 år (2015)'!$A27:$J28) -> -1219 | H86: =DSUM(Kontoutdrag_officiella!$A:$J,"t",'Villkor 1 år (2015)'!$A93:$J94) -> -1299 | I86: =DSUM(Kontoutdrag_officiella!$A:$J,"t",'Villkor 1 år (2015)'!$A159:$J160) -> -1549 | J86: =DSUM(Kontoutdrag_officiella!$A:$J,"t",'Villkor 1 år (2015)'!$A225:$J226) -> -1515 | K86: =DSUM(Kontoutdrag_officiella!$A:$J,"t",'Villkor 1 år (2015)'!$A291:$J292) -> -666 | L86: =DSUM(Kontoutdrag_officiella!$A:$J,"t",'Villkor 1 år (2015)'!$A357:$J358) -> -524 | M86: =DSUM(Kontoutdrag_officiella!$A:$J,"t",'Villkor 1 år (2015)'!$A423:$J424) -> -890 | N86: =DSUM(Kontoutdrag_officiella!$A:$J,"t",'Villkor 1 år (2015)'!$A489:$J490) -> -1470 | O86: =DSUM(Kontoutdrag_officiella!$A:$J,"t",'Villkor 1 år (2015)'!$A555:$J556) -> -2704 | P86: =DSUM(Kontoutdrag_officiella!$A:$J,"t",'Villkor 1 år (2015)'!$A621:$J622) -> -1569 | Q86: =DSUM(Kontoutdrag_officiella!$A:$J,"t",'Villkor 1 år (2015)'!$A687:$J688) -> -1655 | R86: =DSUM(Kontoutdrag_officiella!$A:$J,"t",'Villkor 1 år (2015)'!$A753:$J754) -> -647 | S86: =SUM(G86:R86) -> -15707 | T86: lunch utemat | V86: =S86/$V$71 -> -1308.9167 | W86: =SUM(S86)/W$71 -> -1308.9167 | X86: =C38 -> 1441.3636 | Y86: =C38+V86 -> 132.44697 | Z86: =0.5*(P86+Q86) -> -1612
A87: Ut | B87: nöjes utemat | G87: =DSUM(Kontoutdrag_officiella!$A:$J,"t",'Villkor 1 år (2015)'!$A29:$J30) -> -1517 | H87: =DSUM(Kontoutdrag_officiella!$A:$J,"t",'Villkor 1 år (2015)'!$A95:$J96) -> -2026 | I87: =DSUM(Kontoutdrag_officiella!$A:$J,"t",'Villkor 1 år (2015)'!$A161:$J162) -> -4319.21 | J87: =DSUM(Kontoutdrag_officiella!$A:$J,"t",'Villkor 1 år (2015)'!$A227:$J228) -> -2256 | K87: =DSUM(Kontoutdrag_officiella!$A:$J,"t",'Villkor 1 år (2015)'!$A293:$J294) -> -2544.94 | L87: =DSUM(Kontoutdrag_officiella!$A:$J,"t",'Villkor 1 år (2015)'!$A359:$J360) -> -2730 | M87: =DSUM(Kontoutdrag_officiella!$A:$J,"t",'Villkor 1 år (2015)'!$A425:$J426) -> -1147 | N87: =DSUM(Kontoutdrag_officiella!$A:$J,"t",'Villkor 1 år (2015)'!$A491:$J492) -> -3152 | O87: =DSUM(Kontoutdrag_officiella!$A:$J,"t",'Villkor 1 år (2015)'!$A557:$J558) -> -798 | P87: =DSUM(Kontoutdrag_officiella!$A:$J,"t",'Villkor 1 år (2015)'!$A623:$J624) -> -3218 | Q87: =DSUM(Kontoutdrag_officiella!$A:$J,"t",'Villkor 1 år (2015)'!$A689:$J690) -> -886 | R87: =DSUM(Kontoutdrag_officiella!$A:$J,"t",'Villkor 1 år (2015)'!$A755:$J756) -> -755 | S87: =SUM(G87:R87) -> -25349.15 | T87: nöjes utemat | V87: =S87/$V$71 -> -2112.4292 | W87: =SUM(S87)/W$71 -> -2112.4292 | X87: =C39 -> 2100 | Y87: =C39+V87 -> -12.429167
A88: Ut | B88: mat i samband med supa | G88: =DSUM(Kontoutdrag_officiella!$A:$J,"t",'Villkor 1 år (2015)'!$A31:$J32) -> 0 | H88: =DSUM(Kontoutdrag_officiella!$A:$J,"t",'Villkor 1 år (2015)'!$A97:$J98) -> -1870 | I88: =DSUM(Kontoutdrag_officiella!$A:$J,"t",'Villkor 1 år (2015)'!$A163:$J164) -> -1274.3 | J88: =DSUM(Kontoutdrag_officiella!$A:$J,"t",'Villkor 1 år (2015)'!$A229:$J230) -> -4322.25 | K88: =DSUM(Kontoutdrag_officiella!$A:$J,"t",'Villkor 1 år (2015)'!$A295:$J296) -> -3812 | L88: =DSUM(Kontoutdrag_officiella!$A:$J,"t",'Villkor 1 år (2015)'!$A361:$J362) -> 0 | M88: =DSUM(Kontoutdrag_officiella!$A:$J,"t",'Villkor 1 år (2015)'!$A427:$J428) -> -915 | N88: =DSUM(Kontoutdrag_officiella!$A:$J,"t",'Villkor 1 år (2015)'!$A493:$J494) -> -3289 | O88: =DSUM(Kontoutdrag_officiella!$A:$J,"t",'Villkor 1 år (2015)'!$A559:$J560) -> -1573.51 | P88: =DSUM(Kontoutdrag_officiella!$A:$J,"t",'Villkor 1 år (2015)'!$A625:$J626) -> -10214.5 | Q88: =DSUM(Kontoutdrag_officiella!$A:$J,"t",'Villkor 1 år (2015)'!$A691:$J692) -> -3327 | R88: =DSUM(Kontoutdrag_officiella!$A:$J,"t",'Villkor 1 år (2015)'!$A757:$J758) -> -951 | S88: =SUM(G88:R88) -> -31548.56 | T88: mat i samband med supa | V88: =S88/$V$71 -> -2629.0467 | W88: =SUM(S88)/W$71 -> -2629.0467 | X88: =C40 -> 1477.4997 | Y88: =C40+V88 -> -1151.547
A89: Ut | B89: alkohol | G89: =DSUM(Kontoutdrag_officiella!$A:$J,"t",'Villkor 1 år (2015)'!$A33:$J34) -> -202 | H89: =DSUM(Kontoutdrag_officiella!$A:$J,"t",'Villkor 1 år (2015)'!$A99:$J100) -> -132 | I89: =DSUM(Kontoutdrag_officiella!$A:$J,"t",'Villkor 1 år (2015)'!$A165:$J166) -> -146 | J89: =DSUM(Kontoutdrag_officiella!$A:$J,"t",'Villkor 1 år (2015)'!$A231:$J232) -> -449 | K89: =DSUM(Kontoutdrag_officiella!$A:$J,"t",'Villkor 1 år (2015)'!$A297:$J298) -> -385 | L89: =DSUM(Kontoutdrag_officiella!$A:$J,"t",'Villkor 1 år (2015)'!$A363:$J364) -> 0 | M89: =DSUM(Kontoutdrag_officiella!$A:$J,"t",'Villkor 1 år (2015)'!$A429:$J430) -> -180 | N89: =DSUM(Kontoutdrag_officiella!$A:$J,"t",'Villkor 1 år (2015)'!$A495:$J496) -> -336 | O89: =DSUM(Kontoutdrag_officiella!$A:$J,"t",'Villkor 1 år (2015)'!$A561:$J562) -> -124 | P89: =DSUM(Kontoutdrag_officiella!$A:$J,"t",'Villkor 1 år (2015)'!$A627:$J628) -> -270 | Q89: =DSUM(Kontoutdrag_officiella!$A:$J,"t",'Villkor 1 år (2015)'!$A693:$J694) -> -110 | R89: =DSUM(Kontoutdrag_officiella!$A:$J,"t",'Villkor 1 år (2015)'!$A759:$J760) -> -125 | S89: =SUM(G89:R89) -> -2459 | T89: alkohol | V89: =S89/$V$71 -> -204.91667 | W89: =SUM(S89)/W$71 -> -204.91667 | X89: =C41 -> 247.5 | Y89: =C41+V89 -> 42.583333
A90: Ut | B90: taxi efter supa | G90: =DSUM(Kontoutdrag_officiella!$A:$J,"t",'Villkor 1 år (2015)'!$A35:$J36) -> 0 | H90: =DSUM(Kontoutdrag_officiella!$A:$J,"t",'Villkor 1 år (2015)'!$A101:$J102) -> 0 | I90: =DSUM(Kontoutdrag_officiella!$A:$J,"t",'Villkor 1 år (2015)'!$A167:$J168) -> 0 | J90: =DSUM(Kontoutdrag_officiella!$A:$J,"t",'Villkor 1 år (2015)'!$A233:$J234) -> 0 | K90: =DSUM(Kontoutdrag_officiella!$A:$J,"t",'Villkor 1 år (2015)'!$A299:$J300) -> 0 | L90: =DSUM(Kontoutdrag_officiella!$A:$J,"t",'Villkor 1 år (2015)'!$A365:$J366) -> 0 | M90: =DSUM(Kontoutdrag_officiella!$A:$J,"t",'Villkor 1 år (2015)'!$A431:$J432) -> 0 | N90: =DSUM(Kontoutdrag_officiella!$A:$J,"t",'Villkor 1 år (2015)'!$A497:$J498) -> -200 | O90: =DSUM(Kontoutdrag_officiella!$A:$J,"t",'Villkor 1 år (2015)'!$A563:$J564) -> 0 | P90: =DSUM(Kontoutdrag_officiella!$A:$J,"t",'Villkor 1 år (2015)'!$A629:$J630) -> -300 | Q90: =DSUM(Kontoutdrag_officiella!$A:$J,"t",'Villkor 1 år (2015)'!$A695:$J696) -> 0 | R90: =DSUM(Kontoutdrag_officiella!$A:$J,"t",'Villkor 1 år (2015)'!$A761:$J762) -> 0 | S90: =SUM(G90:R90) -> -500 | T90: taxi efter supa | V90: =S90/$V$71 -> -41.666667 | W90: =SUM(S90)/W$71 -> -41.666667 | X90: =C42 -> 0 | Y90: =C42+V90 -> -41.666667
A91: Ut | B91: Buss etc i samband med supa | G91: =DSUM(Kontoutdrag_officiella!$A:$J,"t",'Villkor 1 år (2015)'!$A37:$J38) -> 0 | H91: =DSUM(Kontoutdrag_officiella!$A:$J,"t",'Villkor 1 år (2015)'!$A103:$J104) -> 0 | I91: =DSUM(Kontoutdrag_officiella!$A:$J,"t",'Villkor 1 år (2015)'!$A169:$J170) -> 0 | J91: =DSUM(Kontoutdrag_officiella!$A:$J,"t",'Villkor 1 år (2015)'!$A235:$J236) -> 0 | K91: =DSUM(Kontoutdrag_officiella!$A:$J,"t",'Villkor 1 år (2015)'!$A301:$J302) -> 0 | L91: =DSUM(Kontoutdrag_officiella!$A:$J,"t",'Villkor 1 år (2015)'!$A367:$J368) -> 0 | M91: =DSUM(Kontoutdrag_officiella!$A:$J,"t",'Villkor 1 år (2015)'!$A433:$J434) -> 0 | N91: =DSUM(Kontoutdrag_officiella!$A:$J,"t",'Villkor 1 år (2015)'!$A499:$J500) -> 0 | O91: =DSUM(Kontoutdrag_officiella!$A:$J,"t",'Villkor 1 år (2015)'!$A565:$J566) -> 0 | P91: =DSUM(Kontoutdrag_officiella!$A:$J,"t",'Villkor 1 år (2015)'!$A631:$J632) -> 0 | Q91: =DSUM(Kontoutdrag_officiella!$A:$J,"t",'Villkor 1 år (2015)'!$A697:$J698) -> 0 | R91: =DSUM(Kontoutdrag_officiella!$A:$J,"t",'Villkor 1 år (2015)'!$A763:$J764) -> 0 | S91: =SUM(G91:R91) -> 0 | T91: Buss etc i samband med supa | V91: =S91/$V$71 -> 0 | W91: =SUM(S91)/W$71 -> 0 | X91: =C43 -> 0 | Y91: =C43+V91 -> 0
A92: Ut | B92: oväntade utgifter | G92: =DSUM(Kontoutdrag_officiella!$A:$J,"t",'Villkor 1 år (2015)'!$A39:$J40) -> 0 | H92: =DSUM(Kontoutdrag_officiella!$A:$J,"t",'Villkor 1 år (2015)'!$A105:$J106) -> -439 | I92: =DSUM(Kontoutdrag_officiella!$A:$J,"t",'Villkor 1 år (2015)'!$A171:$J172) -> 397 | J92: =DSUM(Kontoutdrag_officiella!$A:$J,"t",'Villkor 1 år (2015)'!$A237:$J238) -> 30 | K92: =DSUM(Kontoutdrag_officiella!$A:$J,"t",'Villkor 1 år (2015)'!$A303:$J304) -> -280 | L92: =DSUM(Kontoutdrag_officiella!$A:$J,"t",'Villkor 1 år (2015)'!$A369:$J370) -> 242 | M92: =DSUM(Kontoutdrag_officiella!$A:$J,"t",'Villkor 1 år (2015)'!$A435:$J436) -> 0 | N92: =DSUM(Kontoutdrag_officiella!$A:$J,"t",'Villkor 1 år (2015)'!$A501:$J502) -> 18 | O92: =DSUM(Kontoutdrag_officiella!$A:$J,"t",'Villkor 1 år (2015)'!$A567:$J568) -> 0 | P92: =DSUM(Kontoutdrag_officiella!$A:$J,"t",'Villkor 1 år (2015)'!$A633:$J634) -> 0 | Q92: =DSUM(Kontoutdrag_officiella!$A:$J,"t",'Villkor 1 år (2015)'!$A699:$J700) -> 0 | R92: =DSUM(Kontoutdrag_officiella!$A:$J,"t",'Villkor 1 år (2015)'!$A765:$J766) -> 0 | S92: =SUM(G92:R92) -> -32 | T92: oväntade utgifter | V92: =S92/$V$71 -> -2.6666667 | W92: =SUM(S92)/W$71 -> -2.6666667 | X92: =C44 -> 100 | Y92: =C44+V92 -> 97.333333
A93: Ut | B93: Småresor ej supa | G93: =DSUM(Kontoutdrag_officiella!$A:$J,"t",'Villkor 1 år (2015)'!$A41:$J42) -> -580 | H93: =DSUM(Kontoutdrag_officiella!$A:$J,"t",'Villkor 1 år (2015)'!$A107:$J108) -> 0 | I93: =DSUM(Kontoutdrag_officiella!$A:$J,"t",'Villkor 1 år (2015)'!$A173:$J174) -> -580 | J93: =DSUM(Kontoutdrag_officiella!$A:$J,"t",'Villkor 1 år (2015)'!$A239:$J240) -> -1565 | K93: =DSUM(Kontoutdrag_officiella!$A:$J,"t",'Villkor 1 år (2015)'!$A305:$J306) -> 0 | L93: =DSUM(Kontoutdrag_officiella!$A:$J,"t",'Villkor 1 år (2015)'!$A371:$J372) -> 0 | M93: =DSUM(Kontoutdrag_officiella!$A:$J,"t",'Villkor 1 år (2015)'!$A437:$J438) -> 0 | N93: =DSUM(Kontoutdrag_officiella!$A:$J,"t",'Villkor 1 år (2015)'!$A503:$J504) -> -280 | O93: =DSUM(Kontoutdrag_officiella!$A:$J,"t",'Villkor 1 år (2015)'!$A569:$J570) -> -430 | P93: =DSUM(Kontoutdrag_officiella!$A:$J,"t",'Villkor 1 år (2015)'!$A635:$J636) -> -450 | Q93: =DSUM(Kontoutdrag_officiella!$A:$J,"t",'Villkor 1 år (2015)'!$A701:$J702) -> 0 | R93: =DSUM(Kontoutdrag_officiella!$A:$J,"t",'Villkor 1 år (2015)'!$A767:$J768) -> -374 | S93: =SUM(G93:R93) -> -4259 | T93: Småresor ej supa | V93: =S93/$V$71 -> -354.91667 | W93: =SUM(S93)/W$71 -> -354.91667 | X93: =C45 -> 285 | Y93: =C45+V93 -> -69.916667
A94: Ut | B94: resor i samband med utflykt | G94: =DSUM(Kontoutdrag_officiella!$A:$J,"t",'Villkor 1 år (2015)'!$A43:$J44) -> 0 | H94: =DSUM(Kontoutdrag_officiella!$A:$J,"t",'Villkor 1 år (2015)'!$A109:$J110) -> 0 | I94: =DSUM(Kontoutdrag_officiella!$A:$J,"t",'Villkor 1 år (2015)'!$A175:$J176) -> 0 | J94: =DSUM(Kontoutdrag_officiella!$A:$J,"t",'Villkor 1 år (2015)'!$A241:$J242) -> -500 | K94: =DSUM(Kontoutdrag_officiella!$A:$J,"t",'Villkor 1 år (2015)'!$A307:$J308) -> -749 | L94: =DSUM(Kontoutdrag_officiella!$A:$J,"t",'Villkor 1 år (2015)'!$A373:$J374) -> 0 | M94: =DSUM(Kontoutdrag_officiella!$A:$J,"t",'Villkor 1 år (2015)'!$A439:$J440) -> 0 | N94: =DSUM(Kontoutdrag_officiella!$A:$J,"t",'Villkor 1 år (2015)'!$A505:$J506) -> 0 | O94: =DSUM(Kontoutdrag_officiella!$A:$J,"t",'Villkor 1 år (2015)'!$A571:$J572) -> 0 | P94: =DSUM(Kontoutdrag_officiella!$A:$J,"t",'Villkor 1 år (2015)'!$A637:$J638) -> 0 | Q94: =DSUM(Kontoutdrag_officiella!$A:$J,"t",'Villkor 1 år (2015)'!$A703:$J704) -> 0 | R94: =DSUM(Kontoutdrag_officiella!$A:$J,"t",'Villkor 1 år (2015)'!$A769:$J770) -> 0 | S94: =SUM(G94:R94) -> -1249 | T94: resor i samband med utflykt | V94: =S94/$V$71 -> -104.08333 | W94: =SUM(S94)/W$71 -> -104.08333 | X94: =C46 -> 250 | Y94: =C46+V94 -> 145.91667
A95: Ut | B95: värnamoresor+övriga | G95: =DSUM(Kontoutdrag_officiella!$A:$J,"t",'Villkor 1 år (2015)'!$A45:$J46) -> -416 | H95: =DSUM(Kontoutdrag_officiella!$A:$J,"t",'Villkor 1 år (2015)'!$A111:$J112) -> -505 | I95: =DSUM(Kontoutdrag_officiella!$A:$J,"t",'Villkor 1 år (2015)'!$A177:$J178) -> 0 | J95: =DSUM(Kontoutdrag_officiella!$A:$J,"t",'Villkor 1 år (2015)'!$A243:$J244) -> 0 | K95: =DSUM(Kontoutdrag_officiella!$A:$J,"t",'Villkor 1 år (2015)'!$A309:$J310) -> -552 | L95: =DSUM(Kontoutdrag_officiella!$A:$J,"t",'Villkor 1 år (2015)'!$A375:$J376) -> 0 | M95: =DSUM(Kontoutdrag_officiella!$A:$J,"t",'Villkor 1 år (2015)'!$A441:$J442) -> 0 | N95: =DSUM(Kontoutdrag_officiella!$A:$J,"t",'Villkor 1 år (2015)'!$A507:$J508) -> -569 | O95: =DSUM(Kontoutdrag_officiella!$A:$J,"t",'Villkor 1 år (2015)'!$A573:$J574) -> 0 | P95: =DSUM(Kontoutdrag_officiella!$A:$J,"t",'Villkor 1 år (2015)'!$A639:$J640) -> 0 | Q95: =DSUM(Kontoutdrag_officiella!$A:$J,"t",'Villkor 1 år (2015)'!$A705:$J706) -> -251 | R95: =DSUM(Kontoutdrag_officiella!$A:$J,"t",'Villkor 1 år (2015)'!$A771:$J772) -> -228 | S95: =SUM(G95:R95) -> -2521 | T95: värnamoresor+övriga | V95: =S95/$V$71 -> -210.08333 | W95: =SUM(S95)/W$71 -> -210.08333 | X95: =C47 -> 200 | Y95: =C47+V95 -> -10.083333
A96: Ut | B96: spara almänt | G96: =DSUM(Kontoutdrag_officiella!$A:$J,"t",'Villkor 1 år (2015)'!$A47:$J48) -> 0 | H96: =DSUM(Kontoutdrag_officiella!$A:$J,"t",'Villkor 1 år (2015)'!$A113:$J114) -> 0 | I96: =DSUM(Kontoutdrag_officiella!$A:$J,"t",'Villkor 1 år (2015)'!$A179:$J180) -> 0 | J96: =DSUM(Kontoutdrag_officiella!$A:$J,"t",'Villkor 1 år (2015)'!$A245:$J246) -> 300 | K96: =DSUM(Kontoutdrag_officiella!$A:$J,"t",'Villkor 1 år (2015)'!$A311:$J312) -> -15133 | L96: =DSUM(Kontoutdrag_officiella!$A:$J,"t",'Villkor 1 år (2015)'!$A377:$J378) -> 0 | M96: =DSUM(Kontoutdrag_officiella!$A:$J,"t",'Villkor 1 år (2015)'!$A443:$J444) -> -18357.4 | N96: =DSUM(Kontoutdrag_officiella!$A:$J,"t",'Villkor 1 år (2015)'!$A509:$J510) -> -18046.89 | O96: =DSUM(Kontoutdrag_officiella!$A:$J,"t",'Villkor 1 år (2015)'!$A575:$J576) -> -94353.69 | P96: =DSUM(Kontoutdrag_officiella!$A:$J,"t",'Villkor 1 år (2015)'!$A641:$J642) -> -20387.86 | Q96: =DSUM(Kontoutdrag_officiella!$A:$J,"t",'Villkor 1 år (2015)'!$A707:$J708) -> -17301.64 | R96: =DSUM(Kontoutdrag_officiella!$A:$J,"t",'Villkor 1 år (2015)'!$A773:$J774) -> -11093.58 | S96: =SUM(G96:R96) -> -194374.06 | T96: spara almänt | V96: =S96/$V$71 -> -16197.838 | W96: =SUM(S96)/W$71 -> -16197.838 | X96: =C48 -> 1131.72 | Y96: =C48+V96 -> -15066.118
A97: Ut | B97: spara till amortering | G97: =DSUM(Kontoutdrag_officiella!$A:$J,"t",'Villkor 1 år (2015)'!$A49:$J50) -> -250 | H97: =DSUM(Kontoutdrag_officiella!$A:$J,"t",'Villkor 1 år (2015)'!$A115:$J116) -> -250 | I97: =DSUM(Kontoutdrag_officiella!$A:$J,"t",'Villkor 1 år (2015)'!$A181:$J182) -> -250 | J97: =DSUM(Kontoutdrag_officiella!$A:$J,"t",'Villkor 1 år (2015)'!$A247:$J248) -> -250 | K97: =DSUM(Kontoutdrag_officiella!$A:$J,"t",'Villkor 1 år (2015)'!$A313:$J314) -> 49750 | L97: =DSUM(Kontoutdrag_officiella!$A:$J,"t",'Villkor 1 år (2015)'!$A379:$J380) -> 10015 | M97: =DSUM(Kontoutdrag_officiella!$A:$J,"t",'Villkor 1 år (2015)'!$A445:$J446) -> -250 | N97: =DSUM(Kontoutdrag_officiella!$A:$J,"t",'Villkor 1 år (2015)'!$A511:$J512) -> -1250 | O97: =DSUM(Kontoutdrag_officiella!$A:$J,"t",'Villkor 1 år (2015)'!$A577:$J578) -> 750 | P97: =DSUM(Kontoutdrag_officiella!$A:$J,"t",'Villkor 1 år (2015)'!$A643:$J644) -> -250 | Q97: =DSUM(Kontoutdrag_officiella!$A:$J,"t",'Villkor 1 år (2015)'!$A709:$J710) -> -250 | R97: =DSUM(Kontoutdrag_officiella!$A:$J,"t",'Villkor 1 år (2015)'!$A775:$J776) -> -250 | S97: =SUM(G97:R97) -> 57265 | T97: spara till amortering | V97: =S97/$V$71 -> 4772.0833 | W97: =SUM(S97)/W$71 -> 4772.0833 | X97: =C49 -> 2507 | Y97: =C49+V97 -> 7279.0833
A98: Ut | B98: spara till sommarrussel | G98: =DSUM(Kontoutdrag_officiella!$A:$J,"t",'Villkor 1 år (2015)'!$A51:$J52) -> 0 | H98: =DSUM(Kontoutdrag_officiella!$A:$J,"t",'Villkor 1 år (2015)'!$A117:$J118) -> 0 | I98: =DSUM(Kontoutdrag_officiella!$A:$J,"t",'Villkor 1 år (2015)'!$A183:$J184) -> 0 | J98: =DSUM(Kontoutdrag_officiella!$A:$J,"t",'Villkor 1 år (2015)'!$A249:$J250) -> 0 | K98: =DSUM(Kontoutdrag_officiella!$A:$J,"t",'Villkor 1 år (2015)'!$A315:$J316) -> 0 | L98: =DSUM(Kontoutdrag_officiella!$A:$J,"t",'Villkor 1 år (2015)'!$A381:$J382) -> -12718.25 | M98: =DSUM(Kontoutdrag_officiella!$A:$J,"t",'Villkor 1 år (2015)'!$A447:$J448) -> 1184.06 | N98: =DSUM(Kontoutdrag_officiella!$A:$J,"t",'Villkor 1 år (2015)'!$A513:$J514) -> 3502 | O98: =DSUM(Kontoutdrag_officiella!$A:$J,"t",'Villkor 1 år (2015)'!$A579:$J580) -> -693.16 | P98: =DSUM(Kontoutdrag_officiella!$A:$J,"t",'Villkor 1 år (2015)'!$A645:$J646) -> 0 | Q98: =DSUM(Kontoutdrag_officiella!$A:$J,"t",'Villkor 1 år (2015)'!$A711:$J712) -> 0 | R98: =DSUM(Kontoutdrag_officiella!$A:$J,"t",'Villkor 1 år (2015)'!$A777:$J778) -> 0 | S98: =SUM(G98:R98) -> -8725.35 | T98: spara till sommarrussel | V98: =S98/$V$71 -> -727.1125 | W98: =SUM(S98)/W$71 -> -727.1125 | X98: =C50 -> 1250 | Y98: =C50+V98 -> 522.8875
A99: Ut | B99: spara till dator | G99: =DSUM(Kontoutdrag_officiella!$A:$J,"t",'Villkor 1 år (2015)'!$A53:$J54) -> 0 | H99: =DSUM(Kontoutdrag_officiella!$A:$J,"t",'Villkor 1 år (2015)'!$A119:$J120) -> 0 | I99: =DSUM(Kontoutdrag_officiella!$A:$J,"t",'Villkor 1 år (2015)'!$A185:$J186) -> 0 | J99: =DSUM(Kontoutdrag_officiella!$A:$J,"t",'Villkor 1 år (2015)'!$A251:$J252) -> 0 | K99: =DSUM(Kontoutdrag_officiella!$A:$J,"t",'Villkor 1 år (2015)'!$A317:$J318) -> 0 | L99: =DSUM(Kontoutdrag_officiella!$A:$J,"t",'Villkor 1 år (2015)'!$A383:$J384) -> 0 | M99: =DSUM(Kontoutdrag_officiella!$A:$J,"t",'Villkor 1 år (2015)'!$A449:$J450) -> 0 | N99: =DSUM(Kontoutdrag_officiella!$A:$J,"t",'Villkor 1 år (2015)'!$A515:$J516) -> 0 | O99: =DSUM(Kontoutdrag_officiella!$A:$J,"t",'Villkor 1 år (2015)'!$A581:$J582) -> 0 | P99: =DSUM(Kontoutdrag_officiella!$A:$J,"t",'Villkor 1 år (2015)'!$A647:$J648) -> 0 | Q99: =DSUM(Kontoutdrag_officiella!$A:$J,"t",'Villkor 1 år (2015)'!$A713:$J714) -> 0 | R99: =DSUM(Kontoutdrag_officiella!$A:$J,"t",'Villkor 1 år (2015)'!$A779:$J780) -> 0 | S99: =SUM(G99:R99) -> 0 | T99: spara till dator | V99: =S99/$V$71 -> 0 | W99: =SUM(S99)/W$71 -> 0 | X99: =C51 -> 350 | Y99: =C51+V99 -> 350
A100: Ut | B100: spara till russel övrigt | G100: =DSUM(Kontoutdrag_officiella!$A:$J,"t",'Villkor 1 år (2015)'!$A55:$J56) -> -748.07 | H100: =DSUM(Kontoutdrag_officiella!$A:$J,"t",'Villkor 1 år (2015)'!$A121:$J122) -> -836.6 | I100: =DSUM(Kontoutdrag_officiella!$A:$J,"t",'Villkor 1 år (2015)'!$A187:$J188) -> 0 | J100: =DSUM(Kontoutdrag_officiella!$A:$J,"t",'Villkor 1 år (2015)'!$A253:$J254) -> 0 | K100: =DSUM(Kontoutdrag_officiella!$A:$J,"t",'Villkor 1 år (2015)'!$A319:$J320) -> 0 | L100: =DSUM(Kontoutdrag_officiella!$A:$J,"t",'Villkor 1 år (2015)'!$A385:$J386) -> -354.26 | M100: =DSUM(Kontoutdrag_officiella!$A:$J,"t",'Villkor 1 år (2015)'!$A451:$J452) -> 0 | N100: =DSUM(Kontoutdrag_officiella!$A:$J,"t",'Villkor 1 år (2015)'!$A517:$J518) -> 1500 | O100: =DSUM(Kontoutdrag_officiella!$A:$J,"t",'Villkor 1 år (2015)'!$A583:$J584) -> -790 | P100: =DSUM(Kontoutdrag_officiella!$A:$J,"t",'Villkor 1 år (2015)'!$A649:$J650) -> -6389 | Q100: =DSUM(Kontoutdrag_officiella!$A:$J,"t",'Villkor 1 år (2015)'!$A715:$J716) -> -232 | R100: =DSUM(Kontoutdrag_officiella!$A:$J,"t",'Villkor 1 år (2015)'!$A781:$J782) -> -545.22 | S100: =SUM(G100:R100) -> -8395.15 | T100: spara till russel övrigt | V100: =S100/$V$71 -> -699.59583 | W100: =SUM(S100)/W$71 -> -699.59583 | X100: =C52 -> 450 | Y100: =C52+V100 -> -249.59583
A101: Ut | B101: kläder | G101: =DSUM(Kontoutdrag_officiella!$A:$J,"t",'Villkor 1 år (2015)'!$A57:$J58) -> 0 | H101: =DSUM(Kontoutdrag_officiella!$A:$J,"t",'Villkor 1 år (2015)'!$A123:$J124) -> 0 | I101: =DSUM(Kontoutdrag_officiella!$A:$J,"t",'Villkor 1 år (2015)'!$A189:$J190) -> 0 | J101: =DSUM(Kontoutdrag_officiella!$A:$J,"t",'Villkor 1 år (2015)'!$A255:$J256) -> 0 | K101: =DSUM(Kontoutdrag_officiella!$A:$J,"t",'Villkor 1 år (2015)'!$A321:$J322) -> -249 | L101: =DSUM(Kontoutdrag_officiella!$A:$J,"t",'Villkor 1 år (2015)'!$A387:$J388) -> 0 | M101: =DSUM(Kontoutdrag_officiella!$A:$J,"t",'Villkor 1 år (2015)'!$A453:$J454) -> 0 | N101: =DSUM(Kontoutdrag_officiella!$A:$J,"t",'Villkor 1 år (2015)'!$A519:$J520) -> 0 | O101: =DSUM(Kontoutdrag_officiella!$A:$J,"t",'Villkor 1 år (2015)'!$A585:$J586) -> 0 | P101: =DSUM(Kontoutdrag_officiella!$A:$J,"t",'Villkor 1 år (2015)'!$A651:$J652) -> -3559 | Q101: =DSUM(Kontoutdrag_officiella!$A:$J,"t",'Villkor 1 år (2015)'!$A717:$J718) -> 0 | R101: =DSUM(Kontoutdrag_officiella!$A:$J,"t",'Villkor 1 år (2015)'!$A783:$J784) -> 0 | S101: =SUM(G101:R101) -> -3808 | T101: kläder | V101: =S101/$V$71 -> -317.33333 | W101: =SUM(S101)/W$71 -> -317.33333 | X101: =C53 -> 150 | Y101: =C53+V101 -> -167.33333
A102: Ut | B102: presenter | G102: =DSUM(Kontoutdrag_officiella!$A:$J,"t",'Villkor 1 år (2015)'!$A59:$J60) -> 0 | H102: =DSUM(Kontoutdrag_officiella!$A:$J,"t",'Villkor 1 år (2015)'!$A125:$J126) -> -1985 | I102: =DSUM(Kontoutdrag_officiella!$A:$J,"t",'Villkor 1 år (2015)'!$A191:$J192) -> -111.1 | J102: =DSUM(Kontoutdrag_officiella!$A:$J,"t",'Villkor 1 år (2015)'!$A257:$J258) -> -13146 | K102: =DSUM(Kontoutdrag_officiella!$A:$J,"t",'Villkor 1 år (2015)'!$A323:$J324) -> -1879 | L102: =DSUM(Kontoutdrag_officiella!$A:$J,"t",'Villkor 1 år (2015)'!$A389:$J390) -> -230 | M102: =DSUM(Kontoutdrag_officiella!$A:$J,"t",'Villkor 1 år (2015)'!$A455:$J456) -> -145.01 | N102: =DSUM(Kontoutdrag_officiella!$A:$J,"t",'Villkor 1 år (2015)'!$A521:$J522) -> -640 | O102: =DSUM(Kontoutdrag_officiella!$A:$J,"t",'Villkor 1 år (2015)'!$A587:$J588) -> -129 | P102: =DSUM(Kontoutdrag_officiella!$A:$J,"t",'Villkor 1 år (2015)'!$A653:$J654) -> 0 | Q102: =DSUM(Kontoutdrag_officiella!$A:$J,"t",'Villkor 1 år (2015)'!$A719:$J720) -> -129 | R102: =DSUM(Kontoutdrag_officiella!$A:$J,"t",'Villkor 1 år (2015)'!$A785:$J786) -> -3131.8 | S102: =SUM(G102:R102) -> -21525.91 | T102: presenter | V102: =S102/$V$71 -> -1793.8258 | W102: =SUM(S102)/W$71 -> -1793.8258 | X102: =C54 -> 1000 | Y102: =C54+V102 -> -793.82583
...

Sheet Villkor 1 år (2015)
A1: y | B1: m | D1: d | E1: n | F1: e | G1: t | J1: b | L1: år | M1: =2015 -> 2015 | N1: Steg mellan varje | O1: =21-1 -> 20
A2: =$M$1 -> 2015 | B2: 1 | J2: hyra (inkl. 1k amortering)
A3: y | B3: m | D3: d | E3: n | F3: e | G3: t | J3: b
A4: =$M$1 -> 2015 | B4: 1 | J4: si och akassa
A5: y | B5: m | D5: d | E5: n | F5: e | G5: t | J5: b
A6: =$M$1 -> 2015 | B6: 1 | J6: hemförsäkring
A7: y | B7: m | D7: d | E7: n | F7: e | G7: t | J7: b
A8: =$M$1 -> 2015 | B8: 1 | J8: liv- o sjukförsäkring etc
A9: y | B9: m | D9: d | E9: n | F9: e | G9: t | J9: b
A10: =$M$1 -> 2015 | B10: 1 | J10: stockholms stads bostadskö
A11: y | B11: m | D11: d | E11: n | F11: e | G11: t | J11: b
A12: =$M$1 -> 2015 | B12: 1 | J12: csn
A13: y | B13: m | D13: d | E13: n | F13: e | G13: t | J13: b
A14: =$M$1 -> 2015 | B14: 1 | J14: röda korset
A15: y | B15: m | D15: d | E15: n | F15: e | G15: t | J15: b
A16: =$M$1 -> 2015 | B16: 1 | J16: el
A17: y | B17: m | D17: d | E17: n | F17: e | G17: t | J17: b
A18: =$M$1 -> 2015 | B18: 1 | J18: internet
A19: y | B19: m | D19: d | E19: n | F19: e | G19: t | J19: b
A20: =$M$1 -> 2015 | B20: 1 | J20: telefonsamtal
A21: y | B21: m | D21: d | E21: n | F21: e | G21: t | J21: b
A22: =$M$1 -> 2015 | B22: 1 | J22: hygien (disk, tvätt o tvål etc)
A23: y | B23: m | D23: d | E23: n | F23: e | G23: t | J23: b
A24: =$M$1 -> 2015 | B24: 1 | J24: hemlagad mat
A25: y | B25: m | D25: d | E25: n | F25: e | G25: t | J25: b
A26: =$M$1 -> 2015 | B26: 1 | J26: hemlagad lunch
A27: y | B27: m | D27: d | E27: n | F27: e | G27: t | J27: b
A28: =$M$1 -> 2015 | B28: 1 | J28: lunch utemat
A29: y | B29: m | D29: d | E29: n | F29: e | G29: t | J29: b
A30: =$M$1 -> 2015 | B30: 1 | J30: nöjes utemat
A31: y | B31: m | D31: d | E31: n | F31: e | G31: t | J31: b
A32: =$M$1 -> 2015 | B32: 1 | J32: mat i samband med supa
A33: y | B33: m | D33: d | E33: n | F33: e | G33: t | J33: b
A34: =$M$1 -> 2015 | B34: 1 | J34: alkohol
A35: y | B35: m | D35: d | E35: n | F35: e | G35: t | J35: b
A36: =$M$1 -> 2015 | B36: 1 | J36: taxi efter supa
A37: y | B37: m | D37: d | E37: n | F37: e | G37: t | J37: b
A38: =$M$1 -> 2015 | B38: 1 | J38: Buss etc i samband med supa
A39: y | B39: m | D39: d | E39: n | F39: e | G39: t | J39: b
A40: =$M$1 -> 2015 | B40: 1 | J40: oväntade utgifter
A41: y | B41: m | D41: d | E41: n | F41: e | G41: t | J41: b
A42: =$M$1 -> 2015 | B42: 1 | J42: Småresor ej supa
A43: y | B43: m | D43: d | E43: n | F43: e | G43: t | J43: b
A44: =$M$1 -> 2015 | B44: 1 | J44: resor i samband med utflykt
A45: y | B45: m | D45: d | E45: n | F45: e | G45: t | J45: b
A46: =$M$1 -> 2015 | B46: 1 | J46: värnamoresor+övriga
A47: y | B47: m | D47: d | E47: n | F47: e | G47: t | J47: b
A48: =$M$1 -> 2015 | B48: 1 | J48: spara almänt
A49: y | B49: m | D49: d | E49: n | F49: e | G49: t | J49: b
A50: =$M$1 -> 2015 | B50: 1 | J50: spara till amortering
A51: y | B51: m | D51: d | E51: n | F51: e | G51: t | J51: b
A52: =$M$1 -> 2015 | B52: 1 | J52: spara till sommarrussel
A53: y | B53: m | D53: d | E53: n | F53: e | G53: t | J53: b
A54: =$M$1 -> 2015 | B54: 1 | J54: spara till dator
A55: y | B55: m | D55: d | E55: n | F55: e | G55: t | J55: b
A56: =$M$1 -> 2015 | B56: 1 | J56: spara till russel övrigt
A57: y | B57: m | D57: d | E57: n | F57: e | G57: t | J57: b
A58: =$M$1 -> 2015 | B58: 1 | J58: kläder
A59: y | B59: m | D59: d | E59: n | F59: e | G59: t | J59: b
A60: =$M$1 -> 2015 | B60: 1 | J60: presenter
A61: y | B61: m | D61: d | E61: n | F61: e | G61: t | J61: b
A62: =$M$1 -> 2015 | B62: 1 | J62: Inträde i samband med supa
A63: y | B63: m | D63: d | E63: n | F63: e | G63: t | J63: b
A64: =$M$1 -> 2015 | B64: 1 | J64: övrigt i samband med supa
A65: y | B65: m | D65: d | E65: n | F65: e | G65: t | J65: b
A66: =$M$1 -> 2015 | B66: 1 | J66: hushåll, reparationer etc inköp av nya husshållsmaskiner
A67: y | B67: m | D67: d | E67: n | F67: e | G67: t | J67: b
A68: =$M$1 -> 2015 | B68: 2 | J68: hyra (inkl. 1k amortering)
A69: y | B69: m | D69: d | E69: n | F69: e | G69: t | J69: b
A70: =$M$1 -> 2015 | B70: 2 | J70: si och akassa
A71: y | B71: m | D71: d | E71: n | F71: e | G71: t | J71: b
A72: =$M$1 -> 2015 | B72: 2 | J72: hemförsäkring
A73: y | B73: m | D73: d | E73: n | F73: e | G73: t | J73: b
A74: =$M$1 -> 2015 | B74: 2 | J74: liv- o sjukförsäkring etc
A75: y | B75: m | D75: d | E75: n | F75: e | G75: t | J75: b
A76: =$M$1 -> 2015 | B76: 2 | J76: stockholms stads bostadskö
A77: y | B77: m | D77: d | E77: n | F77: e | G77: t | J77: b
A78: =$M$1 -> 2015 | B78: 2 | J78: csn
A79: y | B79: m | D79: d | E79: n | F79: e | G79: t | J79: b
A80: =$M$1 -> 2015 | B80: 2 | J80: röda korset
A81: y | B81: m | D81: d | E81: n | F81: e | G81: t | J81: b
A82: =$M$1 -> 2015 | B82: 2 | J82: el
A83: y | B83: m | D83: d | E83: n | F83: e | G83: t | J83: b
A84: =$M$1 -> 2015 | B84: 2 | J84: internet
A85: y | B85: m | D85: d | E85: n | F85: e | G85: t | J85: b
A86: =$M$1 -> 2015 | B86: 2 | J86: telefonsamtal
A87: y | B87: m | D87: d | E87: n | F87: e | G87: t | J87: b
A88: =$M$1 -> 2015 | B88: 2 | J88: hygien (disk, tvätt o tvål etc)
A89: y | B89: m | D89: d | E89: n | F89: e | G89: t | J89: b
A90: =$M$1 -> 2015 | B90: 2 | J90: hemlagad mat
A91: y | B91: m | D91: d | E91: n | F91: e | G91: t | J91: b
A92: =$M$1 -> 2015 | B92: 2 | J92: hemlagad lunch
A93: y | B93: m | D93: d | E93: n | F93: e | G93: t | J93: b
A94: =$M$1 -> 2015 | B94: 2 | J94: lunch utemat
A95: y | B95: m | D95: d | E95: n | F95: e | G95: t | J95: b
A96: =$M$1 -> 2015 | B96: 2 | J96: nöjes utemat
A97: y | B97: m | D97: d | E97: n | F97: e | G97: t | J97: b
A98: =$M$1 -> 2015 | B98: 2 | J98: mat i samband med supa
A99: y | B99: m | D99: d | E99: n | F99: e | G99: t | J99: b
A100: =$M$1 -> 2015 | B100: 2 | J100: alkohol
...

Sheet Budget (2014)
B1: Allkonto, plus annat | C1: ' 629 011 192 | F1: Löne | G1: Kontonummer: | H1: ' 629010552 | J1: Clearing HB | K1: ' 6241
B2: Senaste uppdaterad | C2: Idag | D2: Uppd.historik | F2: =CONCATENATE(G8," ",F8) -> Kontoutdrag FEL! 81545,8099999998 | H2: Statad troligt | I2: 38201 | X2: y | Y2: m | Z2: d | AA2: n | AB2: t | AC2: g | AD2: s | AE2: b | AI2: c
B3: 41905 | C3: =TODAY() -> 46136 | D3: (eg. 2009-08-22 - 23), 2009-08-23, 2009-03-26, 2010-07-28 | F3: =F12 -> FEL! | G3: =G13 -> -77216.82 | H3: =F12 -> FEL! | I3: =F12 -> FEL! | J3: =F12 -> FEL! | K3: =F12 -> FEL! | L3: =F12 -> FEL! | M3: =F12 -> FEL! | N3: =F12 -> FEL! | O3: =F12 -> FEL! | P3: =F12 -> FEL! | Q3: =F12 -> FEL! | R3: =F12 -> FEL! | AI3: Regular
B4: Russel/vecka | C4: =D17 -> 16186.486 | D4: =D15 -> 16186.486 | G4: =IF(NOT(ROUND(G13,0)=0),G13,"") -> -77216.82 | H4: =IF(G4="","",H13) -> <= detta felar
C6: år | D6: =VALUE(LEFT(RIGHT(sheetname(B1),LEN(sheetname(B1))-SEARCH("(",sheetname(B1),1)),SEARCH(")",sheetname(B1),1)-(1+SEARCH("(",sheetname(B1),1)))) -> #NAME? | E6: (Kvar ref) | F6: Från tidigare | G6: Januari | H6: Februari | I6: Mars | J6: April | K6: Maj | L6: Juni | M6: Juli | N6: Augusti | O6: September | P6: Oktober | Q6: November | R6: December | S6: Summa
B7: Temp (kompensera för utlägg på Lönkonto) | C7: 0 | F7: Betalade kreditfakturor | G7: =0 -> 0 | H7: Saldo Allkonto: | I7: Saldo: | J7: =Kontoutdrag_officiella!N1+0 -> 0 | R7: Saldo Lönekonto: | S7: =Kontoutdrag_officiella!M1+0 -> 0 | U7: : Saldo Lönekonto:
B8: på konto VERKLIGA | C8: =J7+C7+S8 -> -2500 | D8: Utan lägga undan | F8: =C8-C9-J12 -> 81545.81 | G8: =IF((ROUND((F8),2))=0,"Kontoutdrag Stämmer","Kontoutdrag FEL!") -> Kontoutdrag FEL! | I8: Ej fakturerat: | J8: =Kontoutdrag_officiella!O1+0 -> 0 | S8: =S7-2500 -> -2500
B9: Bör vara | C9: =DSUM(Kontoutdrag_officiella!$A:$L,"t",X2:AI3) -> -84045.81 | D9: =C8-C9 -> 81545.81 | F9: <--Ev. Fel | I9: Fakturerat, ej förfallet: | J9: =Kontoutdrag_officiella!P1+0 -> 0
B10: Lägga undan | C10: =S144+1000 -> 74716.82 | D10: =C9-C10 -> -158762.63 | F10: =#REF! -> #REF! | G10: UtLånat | I10: Ofakturerade transaktioner: | J10: 0
C11: Stulet-> | D11: =D9-J12+G7 -> 81545.81 | G11: Kredit ej betald | I11: Fakturerat ej förfallet: | J11: 0
B12: Kvar | C12: =C8-C10 -> -77216.82 | D12: <----------------------- | F12: =IF((ROUND((G12-C12),2))=0,"Stämmer","FEL!") -> FEL! | G12: =J12 -> 0 | H12: =stämmer? | I12: =IF((ROUND((G12-C12),2))=0,"Stämmer","FEL!") -> FEL! | J12: =-1*SUM(J8:J11) -> 0
C13: =C8-G12 -> -2500 | D13: <--Detta är så mycket som finns att spendera | G13: =C12-G12 -> -77216.82 | H13: <= detta felar
C14: Bara a | D14: Både r o a
B15: Russel Kvar | C15: =V160 -> 12333.556 | D15: =V142 -> 16186.486 | G15: Pengar in, datum: | H15: 38985 | I15: 39015 | J15: 39045 | K15: 39073 | M15: 39136 | N15: 38799 | O15: 38832 | P15: 38862 | W15: Med sparat
B16: Me kontant | C16: =C15 -> 12333.556 | D16: =D15 -> 16186.486 | F16: Idag | G16: Pengar in | H16: Dagar kvar | I16: Veckor kvar | J16: Avrundade Veckor | L16: Eget Val av veckor kvar | N16: 1850/4= | P16: dagar i månaden | S16: Russel | U16: veckor | V16: per vecka | W16: =S17-500*2 -> 131.72
B17: Russel/vecka | C17: =C15/J17 -> 12333.556 | D17: =D15/J17 -> 16186.486 | F17: =DAY(TODAY()) -> 24 | G17: 25 | H17: =G17-(IF((G17-F17)<1,IF(F17-G17,F17-P17,F17-P17),F17)) -> 1 | I17: =H17/7 -> 0.14285714 | J17: =ROUNDUP(I17,0) -> 1 | L17: 5 | M17: =D15/L17 -> 3237.2973 | N17: =1850/4 -> 462.5 | P17: 31 | S17: =C48 -> 1131.72 | U17: 4.5 | V17: =S17/U17 -> 251.49333 | W17: =W16/U17 -> 29.271111
B18: (Exakt) | C18: =C15/I17 -> 86334.895 | D18: =D15/I17 -> 113305.4 | F18: Kr om dan | G18: =D15/H17 -> 16186.486 | H18: veckodag | I18: =D15/(I17*5) -> 22661.081
I19: Ovan fungerar enl. följande, det som finns på konot pytsas ut till olika potter, sen när inkomst kommer så drar man av det och sätter det på nästa månads pyttsar, så det blir en illusion av förskjutning, men allt är i sin ordning för lönen används till nä | S19: Tot ^ | U19: Per mån ^
C20: =C13-C10 -> -77216.82
B21: Buffert, som lönekvot | C21: =C10/C62 -> 2.571919 | F21: Antalet arbetsdagar under ett år skiftar mellan 224 och 229 beroende på
C22: =C8/C62 -> -0.086055557 | D22: =(C8+10000+20000)/C62 -> 0.94661113 | E22: =SUM(E40:E42)/SUM(C40:C41) -> 2.9444622
A23: In | B23: IN | C23: IN | D23: IN | F23: IN | G23: IN | H23: IN | I23: IN | J23: IN | K23: IN | L23: IN | M23: IN | N23: IN | O23: IN | P23: IN | Q23: IN | R23: IN | S23: IN | W23: Dra in
A24: In | C24: Ändra helst bara varje år | D24: Kompensation av felgissade potter | E24: Kvar ref
A25: In | B25: hyra (inkl. 1k amortering) | C25: =3851+5742+1205+37-635-1250+3333 -> 12283 | E25: =S111 -> 21176.6 | F25: =0+D25 -> 0 | G25: =3851+5742+1205+37-635-1250+3333 -> 12283 | H25: =3851+5742+1205+37-635-1250+3333 -> 12283 | I25: =3851+5742+1205+37-635-1250+3333 -> 12283 | J25: =3851+5742+1205+37-635-1250+3333 -> 12283 | K25: =3851+5742+1205+37-635-1250+3333 -> 12283 | L25: =3851+5742+1205+37-635-1250+3333 -> 12283 | M25: =3851+5742+1205+37-635-1250+3333 -> 12283 | N25: 12283 | O25: =3851+5742+1205+37-635-1250+3333 -> 12283 | P25: 12283 | Q25: =3851+5742+1205+37-635-1250+3333 -> 12283 | R25: 12283 | S25: =SUM(G25:R25) -> 147396 | T25: hyra (inkl. 1k amortering)
A26: In | B26: si och akassa | C26: =-50+720/2+4+4+2 -> 320 | E26: =S112 -> 0 | F26: =0+D26 -> 0 | G26: =-50+720/2+4+4+2 -> 320 | H26: =-50+720/2+4+4+2 -> 320 | I26: =-50+720/2+4+4+2 -> 320 | J26: =-50+720/2+4+4+2 -> 320 | K26: =-50+720/2+4+4+2 -> 320 | L26: =-50+720/2+4+4+2 -> 320 | M26: =-50+720/2+4+4+2 -> 320 | N26: 320 | O26: =-50+720/2+4+4+2 -> 320 | P26: 320 | Q26: =-50+720/2+4+4+2 -> 320 | R26: 320 | S26: =SUM(G26:R26) -> 3840 | T26: si och akassa
A27: In | B27: hemförsäkring | C27: =108+11 -> 119 | E27: =S113 -> -46 | F27: =0+D27 -> 0 | G27: =108+11 -> 119 | H27: =108+11 -> 119 | I27: =108+11 -> 119 | J27: =108+11 -> 119 | K27: =108+11 -> 119 | L27: =108+11 -> 119 | M27: =108+11 -> 119 | N27: 119 | O27: =108+11 -> 119 | P27: 119 | Q27: =108+11 -> 119 | R27: 119 | S27: =SUM(G27:R27) -> 1428 | T27: hemförsäkring
A28: In | B28: liv- o sjukförsäkring etc | C28: 280 | E28: =S114 -> -78 | F28: =0+D28 -> 0 | G28: 280 | H28: 280 | I28: 280 | J28: 280 | K28: 280 | L28: 280 | M28: 280 | N28: 280 | O28: 280 | P28: 280 | Q28: 280 | R28: 280 | S28: =SUM(G28:R28) -> 3360 | T28: liv- o sjukförsäkring etc | W28: =R28 -> 280
A29: In | B29: stockholms stads bostadskö | C29: =225/12 -> 18.75 | E29: =S115 -> 0 | F29: =0+D29 -> 0 | G29: =225/12 -> 18.75 | H29: =225/12 -> 18.75 | I29: =225/12 -> 18.75 | J29: =225/12 -> 18.75 | K29: =225/12 -> 18.75 | L29: =225/12 -> 18.75 | M29: =225/12 -> 18.75 | N29: 18.75 | O29: =225/12 -> 18.75 | P29: 18.75 | Q29: =225/12 -> 18.75 | R29: 18.75 | S29: =SUM(G29:R29) -> 225 | T29: stockholms stads bostadskö
A30: In | B30: csn | C30: =(0*(1000+(216/3))+((120+12923)/12))*0+(120+2917+3037*2+3035)/12 -> 1012.1667 | E30: =S116 -> 18 | F30: =0+D30 -> 0 | G30: =(0*(1000+(216/3))+((120+12923)/12))*0+(120+2917+3037*2+3035)/12 -> 1012.1667 | H30: =(0*(1000+(216/3))+((120+12923)/12))*0+(120+2917+3037*2+3035)/12 -> 1012.1667 | I30: =(0*(1000+(216/3))+((120+12923)/12))*0+(120+2917+3037*2+3035)/12 -> 1012.1667 | J30: =(0*(1000+(216/3))+((120+12923)/12))*0+(120+2917+3037*2+3035)/12 -> 1012.1667 | K30: =(0*(1000+(216/3))+((120+12923)/12))*0+(120+2917+3037*2+3035)/12 -> 1012.1667 | L30: =(0*(1000+(216/3))+((120+12923)/12))*0+(120+2917+3037*2+3035)/12 -> 1012.1667 | M30: =(0*(1000+(216/3))+((120+12923)/12))*0+(120+2917+3037*2+3035)/12 -> 1012.1667 | N30: 1012.1667 | O30: =(0*(1000+(216/3))+((120+12923)/12))*0+(120+2917+3037*2+3035)/12 -> 1012.1667 | P30: 1012.1667 | Q30: =(0*(1000+(216/3))+((120+12923)/12))*0+(120+2917+3037*2+3035)/12 -> 1012.1667 | R30: 1012.1667 | S30: =SUM(G30:R30) -> 12146 | T30: csn
A31: In | B31: röda korset | C31: =100+50 -> 150 | E31: =S117 -> 600 | F31: =0+D31 -> 0 | G31: =100+50 -> 150 | H31: =100+50 -> 150 | I31: =100+50 -> 150 | J31: =100+50 -> 150 | K31: =100+50 -> 150 | L31: =100+50 -> 150 | M31: =100+50 -> 150 | N31: 150 | O31: =100+50 -> 150 | P31: 150 | Q31: =100+50 -> 150 | R31: 150 | S31: =SUM(G31:R31) -> 1800 | T31: röda korset
A32: In | B32: el | C32: =0*355.9+200 -> 200 | E32: =S118 -> 373 | F32: =0+D32 -> 0 | G32: =0*355.9+200 -> 200 | H32: =0*355.9+200 -> 200 | I32: =0*355.9+200 -> 200 | J32: =0*355.9+200 -> 200 | K32: =0*355.9+200 -> 200 | L32: =0*355.9+200 -> 200 | M32: =0*355.9+200 -> 200 | N32: 200 | O32: =0*355.9+200 -> 200 | P32: 200 | Q32: =0*355.9+200 -> 200 | R32: 200 | S32: =SUM(G32:R32) -> 2400 | T32: el
A33: In | B33: internet | C33: =188*0+299 -> 299 | E33: =S119 -> 0 | F33: =0+D33 -> 0 | G33: =188*0+299 -> 299 | H33: =188*0+299 -> 299 | I33: =188*0+299 -> 299 | J33: =188*0+299 -> 299 | K33: =188*0+299 -> 299 | L33: =188*0+299 -> 299 | M33: =188*0+299 -> 299 | N33: 299 | O33: =188*0+299 -> 299 | P33: 299 | Q33: =188*0+299 -> 299 | R33: 299 | S33: =SUM(G33:R33) -> 3588 | T33: internet
A34: In | B34: telefonsamtal | C34: =(39+69+120)*0+(299+15+40)*0+339*0+(354-339)*0+220+299-50+50 -> 519 | E34: =S120 -> 255 | F34: =0+D34 -> 0 | G34: =(39+69+120)*0+(299+15+40)*0+339*0+(354-339)*0+220+299-50 -> 469 | H34: =(39+69+120)*0+(299+15+40)*0+339*0+(354-339)*0+220+299-50 -> 469 | I34: =(39+69+120)*0+(299+15+40)*0+339*0+(354-339)*0+220+299-50+50 -> 519 | J34: =(39+69+120)*0+(299+15+40)*0+339*0+(354-339)*0+220+299-50+50 -> 519 | K34: =(39+69+120)*0+(299+15+40)*0+339*0+(354-339)*0+220+299-50+50 -> 519 | L34: =(39+69+120)*0+(299+15+40)*0+339*0+(354-339)*0+220+299-50+50 -> 519 | M34: =(39+69+120)*0+(299+15+40)*0+339*0+(354-339)*0+220+299-50+50 -> 519 | N34: 519 | O34: =(39+69+120)*0+(299+15+40)*0+339*0+(354-339)*0+220+299-50+50 -> 519 | P34: 519 | Q34: =(39+69+120)*0+(299+15+40)*0+339*0+(354-339)*0+220+299-50+50 -> 519 | R34: 519 | S34: =SUM(G34:R34) -> 6128 | T34: telefonsamtal | W34: =R34-40 -> 479
A35: In | B35: hygien (disk, tvätt o tvål etc) | C35: =20+10 -> 30 | E35: =S121 -> 360 | F35: =0+D35 -> 0 | G35: =20+10 -> 30 | H35: =20+10 -> 30 | I35: =20+10 -> 30 | J35: =20+10 -> 30 | K35: =20+10 -> 30 | L35: =20+10 -> 30 | M35: =20+10 -> 30 | N35: 30 | O35: =20+10 -> 30 | P35: 30 | Q35: =20+10 -> 30 | R35: 30 | S35: =SUM(G35:R35) -> 360 | T35: hygien (disk, tvätt o tvål etc)
A36: In | B36: hemlagad mat | C36: =850+50-300 -> 600 | E36: =S122 -> 3492.93 | F36: =0+D36 -> 0 | G36: =850+50 -> 900 | H36: =850+50 -> 900 | I36: =850+50-300 -> 600 | J36: =850+50-300 -> 600 | K36: =850+50-300 -> 600 | L36: =850+50-300 -> 600 | M36: =850+50-300 -> 600 | N36: 600 | O36: =850+50-300 -> 600 | P36: 600 | Q36: =850+50-300 -> 600 | R36: 600 | S36: =SUM(G36:R36) -> 7800 | T36: hemlagad mat
A37: In | B37: hemlagad lunch | C37: =(226/12)*(15+20)*0.5*0+50*0 -> 0 | E37: =S123 -> 0 | F37: =0+D37 -> 0 | G37: =(226/12)*(15+20)*0.5*0+50*0 -> 0 | H37: =(226/12)*(15+20)*0.5*0+50*0 -> 0 | I37: =(226/12)*(15+20)*0.5*0+50*0 -> 0 | J37: =(226/12)*(15+20)*0.5*0+50*0 -> 0 | K37: =(226/12)*(15+20)*0.5*0+50*0 -> 0 | L37: =(226/12)*(15+20)*0.5*0+50*0 -> 0 | M37: =(226/12)*(15+20)*0.5*0+50*0 -> 0 | N37: 0 | O37: =(226/12)*(15+20)*0.5*0+50*0 -> 0 | P37: 0 | Q37: =(226/12)*(15+20)*0.5*0+50*0 -> 0 | R37: 0 | S37: =SUM(G37:R37) -> 0 | T37: hemlagad lunch
A38: In | B38: lunch utemat | C38: =((780/11)*227)/12+10*10 -> 1441.3636 | E38: =S124 -> 2622.3636 | F38: =0+D38 -> 0 | G38: =((780/11)*227)/12+10*10 -> 1441.3636 | H38: =((780/11)*227)/12+10*10 -> 1441.3636 | I38: =((780/11)*227)/12+10*10 -> 1441.3636 | J38: =((780/11)*227)/12+10*10 -> 1441.3636 | K38: =((780/11)*227)/12+10*10 -> 1441.3636 | L38: =((780/11)*227)/12+10*10 -> 1441.3636 | M38: =((780/11)*227)/12+10*10 -> 1441.3636 | N38: 1441.3636 | O38: =((780/11)*227)/12+10*10 -> 1441.3636 | P38: 1441.3636 | Q38: =((780/11)*227)/12+10*10 -> 1441.3636 | R38: 1441.3636 | S38: =SUM(G38:R38) -> 17296.364 | T38: lunch utemat | V38: russel tot | W38: =R38-45 -> 1396.3636
A39: In | B39: nöjes utemat | C39: =(300*2+250*2)*0+(900+500)*1+0*(45*5*4.5+450)+800-100 -> 2100 | E39: =S125 -> 7804.36 | F39: =0+D39 -> 0 | G39: =(300*2+250*2)*0+(900+500)*1+0*(45*5*4.5+450)+6000 -> 7400 | H39: =(300*2+250*2)*0+(900+500)*1+0*(45*5*4.5+450) -> 1400 | I39: =(300*2+250*2)*0+(900+500)*1+0*(45*5*4.5+450)+800 -> 2200 | J39: =(300*2+250*2)*0+(900+500)*1+0*(45*5*4.5+450)+800+2500 -> 4700 | K39: =(300*2+250*2)*0+(900+500)*1+0*(45*5*4.5+450)+800+2500 -> 4700 | L39: =(300*2+250*2)*0+(900+500)*1+0*(45*5*4.5+450)+800-100 -> 2100 | M39: =(300*2+250*2)*0+(900+500)*1+0*(45*5*4.5+450)+800-100 -> 2100 | N39: 2100 | O39: =(300*2+250*2)*0+(900+500)*1+0*(45*5*4.5+450)+800-100 -> 2100 | P39: =2100 -> 2100 | Q39: =(300*2+250*2)*0+(900+500)*1+0*(45*5*4.5+450)+800-100 -> 2100 | R39: 2100 | S39: =SUM(G39:R39) -> 35100 | T39: nöjes utemat | V39: =C39+C40+C41+C42+C43+C52+C55+C56 -> 4274.9997
A40: In | B40: mat i samband med supa | C40: =2*250*0+1477.49969696969 -> 1477.4997 | E40: =S126 -> 7266.1964 | F40: =0+D40 -> 0 | G40: =2*250*0+1477.49969696969 -> 1477.4997 | H40: =2*250*0+1477.49969696969 -> 1477.4997 | I40: =2*250*0+1477.49969696969 -> 1477.4997 | J40: =2*250*0+1477.49969696969 -> 1477.4997 | K40: =2*250*0+1477.49969696969 -> 1477.4997 | L40: =2*250*0+1477.49969696969 -> 1477.4997 | M40: =2*250*0+1477.49969696969 -> 1477.4997 | N40: 1477.4997 | O40: =2*250*0+1477.49969696969 -> 1477.4997 | P40: 1477.4997 | Q40: =2*250*0+1477.49969696969 -> 1477.4997 | R40: 1477.4997 | S40: =SUM(G40:R40) -> 17729.996 | T40: mat i samband med supa | W40: =R40-50 -> 1427.4997 | X40: =17-14 -> 3
A41: In | B41: alkohol | C41: =500*2-1000+4.5*55 -> 247.5 | E41: =S127 -> -1699 | F41: =0+D41 -> 0 | G41: =500*2-1000+4.5*55 -> 247.5 | H41: =500*2-1000+4.5*55 -> 247.5 | I41: =500*2-1000+4.5*55 -> 247.5 | J41: =500*2-1000+4.5*55 -> 247.5 | K41: =500*2-1000+4.5*55 -> 247.5 | L41: =500*2-1000+4.5*55 -> 247.5 | M41: =500*2-1000+4.5*55 -> 247.5 | N41: 247.5 | O41: =500*2-1000+4.5*55 -> 247.5 | P41: 247.5 | Q41: =500*2-1000+4.5*55 -> 247.5 | R41: 247.5 | S41: =SUM(G41:R41) -> 2970 | T41: alkohol | W41: =R41-50 -> 197.5
A42: In | B42: taxi efter supa | C42: =150*0 -> 0 | E42: =S128 -> -488 | F42: =0+D42 -> 0 | G42: =150*0 -> 0 | H42: =150*0 -> 0 | I42: =150*0 -> 0 | J42: =150*0 -> 0 | K42: =150*0 -> 0 | L42: =150*0 -> 0 | M42: =150*0 -> 0 | N42: 0 | O42: =150*0 -> 0 | P42: 0 | Q42: =150*0 -> 0 | R42: 0 | S42: =SUM(G42:R42) -> 0 | T42: taxi efter supa | W42: =R42-0 -> 0
A43: In | B43: Buss etc i samband med supa | C43: =5*0 -> 0 | E43: =S129 -> 0 | F43: =0+D43 -> 0 | G43: =5*0 -> 0 | H43: =5*0 -> 0 | I43: =5*0 -> 0 | J43: =5*0 -> 0 | K43: =5*0 -> 0 | L43: =5*0 -> 0 | M43: =5*0 -> 0 | N43: 0 | O43: =5*0 -> 0 | P43: 0 | Q43: =5*0 -> 0 | R43: 0 | S43: =SUM(G43:R43) -> 0 | T43: Buss etc i samband med supa | W43: =R43-10 -> -10
A44: In | B44: oväntade utgifter | C44: 100 | E44: =S130 -> 24 | F44: =0+D44 -> 0 | G44: 100 | H44: 100 | I44: 100 | J44: 100 | K44: 100 | L44: 100 | M44: 100 | N44: 100 | O44: 100 | P44: 100 | Q44: 100 | R44: 100 | S44: =SUM(G44:R44) -> 1200 | T44: oväntade utgifter
A45: In | B45: Småresor ej supa | C45: =10+(1365*2)/12+(((550*3)-1365)*2/12) -> 285 | E45: =S131 -> -3362 | F45: =0+D45 -> 0 | G45: =10+(1365*2)/12+(((550*3)-1365)*2/12) -> 285 | H45: =10+(1365*2)/12+(((550*3)-1365)*2/12) -> 285 | I45: =10+(1365*2)/12+(((550*3)-1365)*2/12) -> 285 | J45: =10+(1365*2)/12+(((550*3)-1365)*2/12) -> 285 | K45: =10+(1365*2)/12+(((550*3)-1365)*2/12) -> 285 | L45: =10+(1365*2)/12+(((550*3)-1365)*2/12) -> 285 | M45: =10+(1365*2)/12+(((550*3)-1365)*2/12) -> 285 | N45: 285 | O45: =10+(1365*2)/12+(((550*3)-1365)*2/12) -> 285 | P45: 285 | Q45: =10+(1365*2)/12+(((550*3)-1365)*2/12) -> 285 | R45: 285 | S45: =SUM(G45:R45) -> 3420 | T45: Småresor ej supa
A46: In | B46: resor i samband med utflykt | C46: =50+500*0+250-50 -> 250 | E46: =S132 -> 1453 | F46: =0+D46 -> 0 | G46: =50+500*0+250 -> 300 | H46: =50+500*0+250 -> 300 | I46: =50+500*0+250 -> 300 | J46: =50+500*0+250 -> 300 | K46: =50+500*0+250 -> 300 | L46: =50+500*0+250-50 -> 250 | M46: =50+500*0+250-50 -> 250 | N46: 250 | O46: =50+500*0+250-50 -> 250 | P46: 250 | Q46: =50+500*0+250-50 -> 250 | R46: 250 | S46: =SUM(G46:R46) -> 3250 | T46: resor i samband med utflykt | W46: =R46 -> 250
A47: In | B47: värnamoresor+övriga | C47: =200/2+100 -> 200 | E47: =S133 -> -1417 | F47: =0+D47 -> 0 | G47: =200/2 -> 100 | H47: =200/2 -> 100 | I47: =200/2 -> 100 | J47: =200/2 -> 100 | K47: =200/2 -> 100 | L47: =200/2 -> 100 | M47: =200/2 -> 100 | N47: 100 | O47: =200/2 -> 100 | P47: 100 | Q47: =200/2 -> 100 | R47: 100 | S47: =SUM(G47:R47) -> 1200 | T47: värnamoresor+övriga
A48: In | B48: spara almänt | C48: =444.75+274.75-1.78-115-1-300-50-150+1000+30 -> 1131.72 | E48: =S134 -> -8328.16 | F48: =0+D48 -> 0 | G48: =444.75+274.75-1.78-115-1-6000 -> -5398.28 | H48: =444.75+274.75-1.78-115-1+460 -> 1061.72 | I48: =444.75+274.75-1.78-115-1-300-50+1276+124 -> 1651.72 | J48: =444.75+274.75-1.78-115-1-300-50+460-2500 -> -1788.28 | K48: =444.75+274.75-1.78-115-1-300-50+460-2500 -> -1788.28 | L48: =444.75+274.75-1.78-115-1-300-50-150 -> 101.72 | M48: =444.75+274.75-1.78-115-1-300-50-150 -> 101.72 | N48: =101.72+750+54 -> 905.72 | O48: =444.75+274.75-1.78-115-1-300-50-150+5102-2500 -> 2703.72 | P48: =101.72*0-3922.28 -> -3922.28 | Q48: =444.75+274.75-1.78-115-1-300-50-150+3118 -> 3219.72 | R48: =101.72+1930 -> 2031.72 | S48: =SUM(G48:R48) -> -1119.36 | T48: spara almänt
A49: In | B49: spara till amortering | C49: =3*1250+350+(2680*0.25)+870+700-3333-500 -> 2507 | E49: =S135 -> 55475 | F49: =0+D49 -> 0 | G49: =3*1250+350+(2680*0.25)+870+700-3333 -> 3007 | H49: =3*1250+350+(2680*0.25)+870+700-3333 -> 3007 | I49: =3*1250+350+(2680*0.25)+870+700-3333 -> 3007 | J49: =3*1250+350+(2680*0.25)+870+700-3333 -> 3007 | K49: =3*1250+350+(2680*0.25)+870+700-3333 -> 3007 | L49: =3*1250+350+(2680*0.25)+870+700-3333-500+(1930*0.5) -> 3472 | M49: =3*1250+350+(2680*0.25)+870+700-3333-500+(1930*0.5) -> 3472 | N49: =2507+750 -> 3257 | O49: =3*1250+350+(2680*0.25)+870+700-3333-500 -> 2507 | P49: 2507 | Q49: =3*1250+350+(2680*0.25)+870+700-3333-500 -> 2507 | R49: 2507 | S49: =SUM(G49:R49) -> 35264 | T49: spara till amortering | V49: SommarRussel plan:
A50: In | B50: spara till sommarrussel | C50: =(3000+3000+9000)/12 -> 1250 | E50: =S136 -> -4922.72 | F50: =0+D50 -> 0 | G50: =(3000+3000+9000)/12 -> 1250 | H50: =(3000+3000+9000)/12 -> 1250 | I50: =(3000+3000+9000)/12 -> 1250 | J50: =(3000+3000+9000)/12 -> 1250 | K50: =(3000+3000+9000)/12 -> 1250 | L50: =(3000+3000+9000)/12 -> 1250 | M50: =4421+(3000+3000+9000)/12 -> 5671 | N50: 1250 | O50: =(3000+3000+9000)/12+2500 -> 3750 | P50: 1250 | Q50: =(3000+3000+9000)/12 -> 1250 | R50: 1250 | S50: =SUM(G50:R50) -> 21921 | T50: spara till sommarrussel | V50: 7600 | W50: =R50 -> 1250
A51: In | B51: spara till dator | C51: =250+100+100-100 -> 350 | E51: =S137 -> 4700 | F51: =0+D51 -> 0 | G51: =250+100+100 -> 450 | H51: =250+100+100 -> 450 | I51: =250+100+100 -> 450 | J51: =250+100+100 -> 450 | K51: =250+100+100 -> 450 | L51: =250+100+100-100 -> 350 | M51: =250+100+100-100 -> 350 | N51: 350 | O51: =250+100+100-100 -> 350 | P51: 350 | Q51: =250+100+100-100 -> 350 | R51: 350 | S51: =SUM(G51:R51) -> 4700 | T51: spara till dator | V51: SommarRussel verklighet: | W51: =R51 -> 350
A52: In | B52: spara till russel övrigt | C52: =300+100-50+100 -> 450 | E52: =S138 -> -1344.01 | F52: =0+D52 -> 0 | G52: =300+100 -> 400 | H52: =300+100 -> 400 | I52: =300+100 -> 400 | J52: =300+100 -> 400 | K52: =300+100 -> 400 | L52: =300+100-50+965 -> 1315 | M52: =300+100-50+965 -> 1315 | N52: 350 | O52: =300+100-50 -> 350 | P52: 350 | Q52: =300+100-50 -> 350 | R52: 350 | S52: =SUM(G52:R52) -> 6380 | T52: spara till russel övrigt | V52: =Kontoutdrag_officiella!#REF! -> #ERROR! | W52: =R52 -> 350
A53: In | B53: kläder | C53: =50+50+20+10+70-50 -> 150 | E53: =S139 -> -1522 | F53: =0+D53 -> 0 | G53: =50+50+20+10+70 -> 200 | H53: =50+50+20+10+70 -> 200 | I53: =50+50+20+10+70 -> 200 | J53: =50+50+20+10+70 -> 200 | K53: =50+50+20+10+70 -> 200 | L53: =50+50+20+10+70-50 -> 150 | M53: =50+50+20+10+70-50 -> 150 | N53: 150 | O53: =50+50+20+10+70-50 -> 150 | P53: 150 | Q53: =50+50+20+10+70-50 -> 150 | R53: 150 | S53: =SUM(G53:R53) -> 2050 | T53: kläder | V53: -14746.2 | W53: =R53 -> 150
A54: In | B54: presenter | C54: =500-200+700 -> 1000 | E54: =S140 -> -11506.74 | F54: =0+D54 -> 0 | G54: 500 | H54: 500 | I54: =500-200 -> 300 | J54: =500-200 -> 300 | K54: =500-200 -> 300 | L54: =500-200 -> 300 | M54: =500-200 -> 300 | N54: 300 | O54: =500-200 -> 300 | P54: 300 | Q54: =500-200 -> 300 | R54: 300 | S54: =SUM(G54:R54) -> 4000 | T54: presenter | V54: Back | W54: =R54 -> 300
A55: In | B55: Inträde i samband med supa | C55: =50*0 -> 0 | E55: =S141 -> -550 | F55: =0+D55 -> 0 | G55: =50*0 -> 0 | H55: =50*0 -> 0 | I55: =50*0 -> 0 | J55: =50*0 -> 0 | K55: =50*0 -> 0 | L55: =50*0 -> 0 | M55: =50*0 -> 0 | N55: 0 | O55: =50*0 -> 0 | P55: 0 | Q55: =50*0 -> 0 | R55: 0 | S55: =SUM(G55:R55) -> 0 | T55: Inträde i samband med supa | V55: =V53+V50 -> -7146.2 | W55: =R55 -> 0
A56: In | B56: övrigt i samband med supa | C56: =20*0 -> 0 | E56: =S142 -> 0 | F56: =0+D56 -> 0 | G56: =20*0 -> 0 | H56: =20*0 -> 0 | I56: =20*0 -> 0 | J56: =20*0 -> 0 | K56: =20*0 -> 0 | L56: =20*0 -> 0 | M56: =20*0 -> 0 | N56: 0 | O56: =20*0 -> 0 | P56: 0 | Q56: =20*0 -> 0 | R56: 0 | S56: =SUM(G56:R56) -> 0 | T56: övrigt i samband med supa | V56: Lite oväntat in | W56: =R56 -> 0
A57: In | B57: hushåll, reparationer etc inköp av nya husshållsmaskiner | C57: =(25+50)*0+5*56 -> 280 | E57: =S143 -> 3360 | F57: =0+D57 -> 0 | G57: =(25+50)*0+5*56 -> 280 | H57: =(25+50)*0+5*56 -> 280 | I57: =(25+50)*0+5*56 -> 280 | J57: =(25+50)*0+5*56 -> 280 | K57: =(25+50)*0+5*56 -> 280 | L57: =(25+50)*0+5*56 -> 280 | M57: =(25+50)*0+5*56 -> 280 | N57: 280 | O57: =(25+50)*0+5*56 -> 280 | P57: 280 | Q57: =(25+50)*0+5*56 -> 280 | R57: 280 | S57: =SUM(G57:R57) -> 3360 | T57: hushåll, reparationer etc inköp av nya husshållsmaskiner | V57: =Kontoutdrag_officiella!G552+Kontoutdrag_officiella!G547 -> -5058
A58: In | B58: Summa | C58: =SUM(C25:C57) -> 29051 | E58: =SUM(E25:E57) -> 73716.82 | F58: =0+D58 -> 0 | G58: =SUM(G25:G57) -> 28121 | H58: =SUM(H25:H57) -> 28581 | I58: =SUM(I25:I57) -> 29521 | J58: =SUM(J25:J57) -> 28581 | K58: =SUM(K25:K57) -> 28581 | L58: =SUM(L25:L57) -> 29051 | M58: =SUM(M25:M57) -> 33472 | N58: =SUM(N25:N57) -> 28675 | O58: =SUM(O25:O57) -> 32223 | P58: 27121 | Q58: =SUM(Q25:Q57) -> 30239 | R58: =SUM(R25:R57) -> 29051 | S58: =SUM(S25:S57) -> 349193 | V58: =V57+V55 -> -12204.2 | W58: =SUM(W25:W57) -> 6420.3633
A59: In | B59: Om A-kassa | C59: =C58*0.8 -> 23240.8 | D59: =C58-C59 -> 5810.2 | V59: Om man tar av russel, så ska framtida russel tas in=
B60: Summa utan hyra | C60: =SUM(C26:C57) -> 16768 | D60: =SUM(D26:D54) -> 0 | R60: =K59*C58 -> 0 | V60: =V58+2410.12 -> -9794.08
B61: Summa | C61: =SUM(C25:C57) -> 29051 | D61: =SUM(D25:D57) -> 0 | F61: =SUM(F25:F57) -> 0 | G61: =SUM(G25:G57) -> 28121 | H61: =SUM(H25:H57) -> 28581 | I61: =SUM(I25:I57) -> 29521 | J61: =SUM(J25:J57) -> 28581 | K61: =SUM(K25:K57) -> 28581 | L61: =SUM(L25:L57) -> 29051 | M61: =SUM(M25:M57) -> 33472 | ... R61: =SUM(R25:R57) -> 29051
B62: Planerade Utbetalningar | C62: 29051 | F62: =30599.07-217 -> 30382.07 | G62: =DSUM(Kontoutdrag_officiella!$A:$J,"t",'Villkor 1 år (2014)'!$A799:$J800) -> 0 | H62: =DSUM(Kontoutdrag_officiella!$A:$J,"t",'Villkor 1 år (2014)'!$A801:$J802) -> 28581 | I62: =DSUM(Kontoutdrag_officiella!$A:$J,"t",'Villkor 1 år (2014)'!$A803:$J804) -> 29521 | J62: =DSUM(Kontoutdrag_officiella!$A:$J,"t",'Villkor 1 år (2014)'!$A805:$J806) -> 28581 | K62: =DSUM(Kontoutdrag_officiella!$A:$J,"t",'Villkor 1 år (2014)'!$A807:$J808) -> 28581 | L62: =DSUM(Kontoutdrag_officiella!$A:$J,"t",'Villkor 1 år (2014)'!$A809:$J810) -> 29051 | M62: =DSUM(Kontoutdrag_officiella!$A:$J,"t",'Villkor 1 år (2014)'!$A811:$J812) -> 29051 | N62: =DSUM(Kontoutdrag_officiella!$A:$J,"t",'Villkor 1 år (2014)'!$A813:$J814) -> 28675 | O62: =DSUM(Kontoutdrag_officiella!$A:$J,"t",'Villkor 1 år (2014)'!$A815:$J816) -> 32223 | P62: =DSUM(Kontoutdrag_officiella!$A:$J,"t",'Villkor 1 år (2014)'!$A817:$J818) -> 23097 | Q62: =DSUM(Kontoutdrag_officiella!$A:$J,"t",'Villkor 1 år (2014)'!$A819:$J820) -> 30239 | R62: =DSUM(Kontoutdrag_officiella!$A:$J,"t",'Villkor 1 år (2014)'!$A821:$J822) -> 29051
B63: Över | C63: =C62-C61 -> 0 | D63: =D62-D61 -> 0 | F63: =F62-F61 -> 30382.07 | G63: =G62-G61 -> -28121 | H63: =H62-H61 -> 0 | I63: =I62-I61 -> 0 | J63: =J62-J61 -> 0 | K63: =K62-K61 -> 0 | L63: =L62-L61 -> 0 | M63: =M62-M61 -> -4421 | ... R63: =R62-R61 -> 0 | S63: =SUM(F63:R63) -> -2159.93
B64: +/- per år | C64: =C63*12 -> 0 | D64: =D63*12 -> 0 | M64: =M62-L62 -> 0
B65: In | C65: =C62 -> 29051 | D65: =D62 | G65: Kvar på supa i mån:
B66: Kvar | C66: =C65-C61 -> 0 | D66: =D65-D61 -> 0 | E66: =C66/2 -> 0 | F66: 870.00167 | G66: =E40/C40 -> 4.9179004 | W66: utvald period
B67: Utan hyra | C67: =C66+C25 -> 12283 | D67: =D66+D25 -> 0
B68: Halva kvar (nöje) | C68: =C66/2 -> 0
W70: juni->juli
A71: Ut | B71: UT | C71: UT | D71: UT | F71: UT | G71: UT | H71: UT | I71: UT | J71: UT | K71: UT | L71: UT | M71: UT | N71: UT | O71: UT | P71: UT | Q71: UT | R71: UT | S71: UT | U71: Månader > | V71: 12 | W71: 12
A72: Ut | V72: Snitt/mån | W72: Snitt/mån | X72: Jmfr med plan
A73: Ut | B73: hyra (inkl. 1k amortering) | G73: =DSUM(Kontoutdrag_officiella!$A:$J,"t",'Villkor 1 år (2014)'!$A1:$J2) -> -10661.6 | H73: =DSUM(Kontoutdrag_officiella!$A:$J,"t",'Villkor 1 år (2014)'!$A67:$J68) -> -10445.8 | I73: =DSUM(Kontoutdrag_officiella!$A:$J,"t",'Villkor 1 år (2014)'!$A133:$J134) -> -10370.8 | J73: =DSUM(Kontoutdrag_officiella!$A:$J,"t",'Villkor 1 år (2014)'!$A199:$J200) -> -10348.8 | K73: =DSUM(Kontoutdrag_officiella!$A:$J,"t",'Villkor 1 år (2014)'!$A265:$J266) -> -10341.8 | L73: =DSUM(Kontoutdrag_officiella!$A:$J,"t",'Villkor 1 år (2014)'!$A331:$J332) -> -10334.8 | M73: =DSUM(Kontoutdrag_officiella!$A:$J,"t",'Villkor 1 år (2014)'!$A397:$J398) -> -10327.8 | N73: =DSUM(Kontoutdrag_officiella!$A:$J,"t",'Villkor 1 år (2014)'!$A463:$J464) -> -10320.8 | O73: =DSUM(Kontoutdrag_officiella!$A:$J,"t",'Villkor 1 år (2014)'!$A529:$J530) -> -10240.8 | P73: =DSUM(Kontoutdrag_officiella!$A:$J,"t",'Villkor 1 år (2014)'!$A595:$J596) -> -11492.8 | Q73: =DSUM(Kontoutdrag_officiella!$A:$J,"t",'Villkor 1 år (2014)'!$A661:$J662) -> -8884.8 | R73: =DSUM(Kontoutdrag_officiella!$A:$J,"t",'Villkor 1 år (2014)'!$A727:$J728) -> -12448.8 | S73: =SUM(G73:R73) -> -126219.4 | T73: hyra (inkl. 1k amortering) | U73: =S73-1200 -> -127419.4 | V73: =S73/$V$71 -> -10518.283 | W73: =SUM(S73)/W$71 -> -10518.283 | X73: =C25 -> 12283 | Y73: =C25+V73 -> 1764.7167 | Z73: =S73-7500-3800 -> -137519.4
A74: Ut | B74: si och akassa | G74: =DSUM(Kontoutdrag_officiella!$A:$J,"t",'Villkor 1 år (2014)'!$A3:$J4) -> -320 | H74: =DSUM(Kontoutdrag_officiella!$A:$J,"t",'Villkor 1 år (2014)'!$A69:$J70) -> -320 | I74: =DSUM(Kontoutdrag_officiella!$A:$J,"t",'Villkor 1 år (2014)'!$A135:$J136) -> -320 | J74: =DSUM(Kontoutdrag_officiella!$A:$J,"t",'Villkor 1 år (2014)'!$A201:$J202) -> -320 | K74: =DSUM(Kontoutdrag_officiella!$A:$J,"t",'Villkor 1 år (2014)'!$A267:$J268) -> -320 | L74: =DSUM(Kontoutdrag_officiella!$A:$J,"t",'Villkor 1 år (2014)'!$A333:$J334) -> -320 | M74: =DSUM(Kontoutdrag_officiella!$A:$J,"t",'Villkor 1 år (2014)'!$A399:$J400) -> -320 | N74: =DSUM(Kontoutdrag_officiella!$A:$J,"t",'Villkor 1 år (2014)'!$A465:$J466) -> -320 | O74: =DSUM(Kontoutdrag_officiella!$A:$J,"t",'Villkor 1 år (2014)'!$A531:$J532) -> -320 | P74: =DSUM(Kontoutdrag_officiella!$A:$J,"t",'Villkor 1 år (2014)'!$A597:$J598) -> -320 | Q74: =DSUM(Kontoutdrag_officiella!$A:$J,"t",'Villkor 1 år (2014)'!$A663:$J664) -> -320 | R74: =DSUM(Kontoutdrag_officiella!$A:$J,"t",'Villkor 1 år (2014)'!$A729:$J730) -> -320 | S74: =SUM(G74:R74) -> -3840 | T74: si och akassa | V74: =S74/$V$71 -> -320 | W74: =SUM(S74)/W$71 -> -320 | X74: =C26 -> 320 | Y74: =C26+V74 -> 0 | AA74: =9+1.25-5.4 -> 4.85
A75: Ut | B75: hemförsäkring | G75: =DSUM(Kontoutdrag_officiella!$A:$J,"t",'Villkor 1 år (2014)'!$A5:$J6) -> -119 | H75: =DSUM(Kontoutdrag_officiella!$A:$J,"t",'Villkor 1 år (2014)'!$A71:$J72) -> -119 | I75: =DSUM(Kontoutdrag_officiella!$A:$J,"t",'Villkor 1 år (2014)'!$A137:$J138) -> -119 | J75: =DSUM(Kontoutdrag_officiella!$A:$J,"t",'Villkor 1 år (2014)'!$A203:$J204) -> -119 | K75: =DSUM(Kontoutdrag_officiella!$A:$J,"t",'Villkor 1 år (2014)'!$A269:$J270) -> -119 | L75: =DSUM(Kontoutdrag_officiella!$A:$J,"t",'Villkor 1 år (2014)'!$A335:$J336) -> -119 | M75: =DSUM(Kontoutdrag_officiella!$A:$J,"t",'Villkor 1 år (2014)'!$A401:$J402) -> -119 | N75: =DSUM(Kontoutdrag_officiella!$A:$J,"t",'Villkor 1 år (2014)'!$A467:$J468) -> -119 | O75: =DSUM(Kontoutdrag_officiella!$A:$J,"t",'Villkor 1 år (2014)'!$A533:$J534) -> -132 | P75: =DSUM(Kontoutdrag_officiella!$A:$J,"t",'Villkor 1 år (2014)'!$A599:$J600) -> -130 | Q75: =DSUM(Kontoutdrag_officiella!$A:$J,"t",'Villkor 1 år (2014)'!$A665:$J666) -> -130 | R75: =DSUM(Kontoutdrag_officiella!$A:$J,"t",'Villkor 1 år (2014)'!$A731:$J732) -> -130 | S75: =SUM(G75:R75) -> -1474 | T75: hemförsäkring | V75: =S75/$V$71 -> -122.83333 | W75: =SUM(S75)/W$71 -> -122.83333 | X75: =C27 -> 119 | Y75: =C27+V75 -> -3.8333333
A76: Ut | B76: liv- o sjukförsäkring etc | G76: =DSUM(Kontoutdrag_officiella!$A:$J,"t",'Villkor 1 år (2014)'!$A7:$J8) -> -285 | H76: =DSUM(Kontoutdrag_officiella!$A:$J,"t",'Villkor 1 år (2014)'!$A73:$J74) -> -285 | I76: =DSUM(Kontoutdrag_officiella!$A:$J,"t",'Villkor 1 år (2014)'!$A139:$J140) -> 0 | J76: =DSUM(Kontoutdrag_officiella!$A:$J,"t",'Villkor 1 år (2014)'!$A205:$J206) -> -570 | K76: =DSUM(Kontoutdrag_officiella!$A:$J,"t",'Villkor 1 år (2014)'!$A271:$J272) -> -285 | L76: =DSUM(Kontoutdrag_officiella!$A:$J,"t",'Villkor 1 år (2014)'!$A337:$J338) -> -285 | M76: =DSUM(Kontoutdrag_officiella!$A:$J,"t",'Villkor 1 år (2014)'!$A403:$J404) -> -285 | N76: =DSUM(Kontoutdrag_officiella!$A:$J,"t",'Villkor 1 år (2014)'!$A469:$J470) -> -285 | O76: =DSUM(Kontoutdrag_officiella!$A:$J,"t",'Villkor 1 år (2014)'!$A535:$J536) -> -285 | P76: =DSUM(Kontoutdrag_officiella!$A:$J,"t",'Villkor 1 år (2014)'!$A601:$J602) -> -285 | Q76: =DSUM(Kontoutdrag_officiella!$A:$J,"t",'Villkor 1 år (2014)'!$A667:$J668) -> -285 | R76: =DSUM(Kontoutdrag_officiella!$A:$J,"t",'Villkor 1 år (2014)'!$A733:$J734) -> -303 | S76: =SUM(G76:R76) -> -3438 | T76: liv- o sjukförsäkring etc | V76: =S76/$V$71 -> -286.5 | W76: =SUM(S76)/W$71 -> -286.5 | X76: =C28 -> 280 | Y76: =C28+V76 -> -6.5
A77: Ut | B77: stockholms stads bostadskö | G77: =DSUM(Kontoutdrag_officiella!$A:$J,"t",'Villkor 1 år (2014)'!$A9:$J10) -> 0 | H77: =DSUM(Kontoutdrag_officiella!$A:$J,"t",'Villkor 1 år (2014)'!$A75:$J76) -> 0 | I77: =DSUM(Kontoutdrag_officiella!$A:$J,"t",'Villkor 1 år (2014)'!$A141:$J142) -> 0 | J77: =DSUM(Kontoutdrag_officiella!$A:$J,"t",'Villkor 1 år (2014)'!$A207:$J208) -> 0 | K77: =DSUM(Kontoutdrag_officiella!$A:$J,"t",'Villkor 1 år (2014)'!$A273:$J274) -> -225 | L77: =DSUM(Kontoutdrag_officiella!$A:$J,"t",'Villkor 1 år (2014)'!$A339:$J340) -> 0 | M77: =DSUM(Kontoutdrag_officiella!$A:$J,"t",'Villkor 1 år (2014)'!$A405:$J406) -> 0 | N77: =DSUM(Kontoutdrag_officiella!$A:$J,"t",'Villkor 1 år (2014)'!$A471:$J472) -> 0 | O77: =DSUM(Kontoutdrag_officiella!$A:$J,"t",'Villkor 1 år (2014)'!$A537:$J538) -> 0 | P77: =DSUM(Kontoutdrag_officiella!$A:$J,"t",'Villkor 1 år (2014)'!$A603:$J604) -> 0 | Q77: =DSUM(Kontoutdrag_officiella!$A:$J,"t",'Villkor 1 år (2014)'!$A669:$J670) -> 0 | R77: =DSUM(Kontoutdrag_officiella!$A:$J,"t",'Villkor 1 år (2014)'!$A735:$J736) -> 0 | S77: =SUM(G77:R77) -> -225 | T77: stockholms stads bostadskö | V77: =S77/$V$71 -> -18.75 | W77: =SUM(S77)/W$71 -> -18.75 | X77: =C29 -> 18.75 | Y77: =C29+V77 -> 0
A78: Ut | B78: csn | G78: =DSUM(Kontoutdrag_officiella!$A:$J,"t",'Villkor 1 år (2014)'!$A11:$J12) -> 0 | H78: =DSUM(Kontoutdrag_officiella!$A:$J,"t",'Villkor 1 år (2014)'!$A77:$J78) -> -3032 | I78: =DSUM(Kontoutdrag_officiella!$A:$J,"t",'Villkor 1 år (2014)'!$A143:$J144) -> 0 | J78: =DSUM(Kontoutdrag_officiella!$A:$J,"t",'Villkor 1 år (2014)'!$A209:$J210) -> 0 | K78: =DSUM(Kontoutdrag_officiella!$A:$J,"t",'Villkor 1 år (2014)'!$A275:$J276) -> -3032 | L78: =DSUM(Kontoutdrag_officiella!$A:$J,"t",'Villkor 1 år (2014)'!$A341:$J342) -> 0 | M78: =DSUM(Kontoutdrag_officiella!$A:$J,"t",'Villkor 1 år (2014)'!$A407:$J408) -> 0 | N78: =DSUM(Kontoutdrag_officiella!$A:$J,"t",'Villkor 1 år (2014)'!$A473:$J474) -> -3032 | O78: =DSUM(Kontoutdrag_officiella!$A:$J,"t",'Villkor 1 år (2014)'!$A539:$J540) -> 0 | P78: =DSUM(Kontoutdrag_officiella!$A:$J,"t",'Villkor 1 år (2014)'!$A605:$J606) -> 0 | Q78: =DSUM(Kontoutdrag_officiella!$A:$J,"t",'Villkor 1 år (2014)'!$A671:$J672) -> -3032 | R78: =DSUM(Kontoutdrag_officiella!$A:$J,"t",'Villkor 1 år (2014)'!$A737:$J738) -> 0 | S78: =SUM(G78:R78) -> -12128 | T78: csn | V78: =S78/$V$71 -> -1010.6667 | W78: =SUM(S78)/W$71 -> -1010.6667 | X78: =C30 -> 1012.1667 | Y78: =C30+V78 -> 1.5
A79: Ut | B79: röda korset | G79: =DSUM(Kontoutdrag_officiella!$A:$J,"t",'Villkor 1 år (2014)'!$A13:$J14) -> -100 | H79: =DSUM(Kontoutdrag_officiella!$A:$J,"t",'Villkor 1 år (2014)'!$A79:$J80) -> -100 | I79: =DSUM(Kontoutdrag_officiella!$A:$J,"t",'Villkor 1 år (2014)'!$A145:$J146) -> -100 | J79: =DSUM(Kontoutdrag_officiella!$A:$J,"t",'Villkor 1 år (2014)'!$A211:$J212) -> -100 | K79: =DSUM(Kontoutdrag_officiella!$A:$J,"t",'Villkor 1 år (2014)'!$A277:$J278) -> -100 | L79: =DSUM(Kontoutdrag_officiella!$A:$J,"t",'Villkor 1 år (2014)'!$A343:$J344) -> -100 | M79: =DSUM(Kontoutdrag_officiella!$A:$J,"t",'Villkor 1 år (2014)'!$A409:$J410) -> -100 | N79: =DSUM(Kontoutdrag_officiella!$A:$J,"t",'Villkor 1 år (2014)'!$A475:$J476) -> -100 | O79: =DSUM(Kontoutdrag_officiella!$A:$J,"t",'Villkor 1 år (2014)'!$A541:$J542) -> -100 | P79: =DSUM(Kontoutdrag_officiella!$A:$J,"t",'Villkor 1 år (2014)'!$A607:$J608) -> -100 | Q79: =DSUM(Kontoutdrag_officiella!$A:$J,"t",'Villkor 1 år (2014)'!$A673:$J674) -> -100 | R79: =DSUM(Kontoutdrag_officiella!$A:$J,"t",'Villkor 1 år (2014)'!$A739:$J740) -> -100 | S79: =SUM(G79:R79) -> -1200 | T79: röda korset | V79: =S79/$V$71 -> -100 | W79: =SUM(S79)/W$71 -> -100 | X79: =C31 -> 150 | Y79: =C31+V79 -> 50
A80: Ut | B80: el | G80: =DSUM(Kontoutdrag_officiella!$A:$J,"t",'Villkor 1 år (2014)'!$A15:$J16) -> -433 | H80: =DSUM(Kontoutdrag_officiella!$A:$J,"t",'Villkor 1 år (2014)'!$A81:$J82) -> 0 | I80: =DSUM(Kontoutdrag_officiella!$A:$J,"t",'Villkor 1 år (2014)'!$A147:$J148) -> -413 | J80: =DSUM(Kontoutdrag_officiella!$A:$J,"t",'Villkor 1 år (2014)'!$A213:$J214) -> 0 | K80: =DSUM(Kontoutdrag_officiella!$A:$J,"t",'Villkor 1 år (2014)'!$A279:$J280) -> -203 | L80: =DSUM(Kontoutdrag_officiella!$A:$J,"t",'Villkor 1 år (2014)'!$A345:$J346) -> -247 | M80: =DSUM(Kontoutdrag_officiella!$A:$J,"t",'Villkor 1 år (2014)'!$A411:$J412) -> -163 | N80: =DSUM(Kontoutdrag_officiella!$A:$J,"t",'Villkor 1 år (2014)'!$A477:$J478) -> 0 | O80: =DSUM(Kontoutdrag_officiella!$A:$J,"t",'Villkor 1 år (2014)'!$A543:$J544) -> -405 | P80: =DSUM(Kontoutdrag_officiella!$A:$J,"t",'Villkor 1 år (2014)'!$A609:$J610) -> 0 | Q80: =DSUM(Kontoutdrag_officiella!$A:$J,"t",'Villkor 1 år (2014)'!$A675:$J676) -> -163 | R80: =DSUM(Kontoutdrag_officiella!$A:$J,"t",'Villkor 1 år (2014)'!$A741:$J742) -> 0 | S80: =SUM(G80:R80) -> -2027 | T80: el | V80: =S80/$V$71 -> -168.91667 | W80: =SUM(S80)/W$71 -> -168.91667 | X80: =C32 -> 200 | Y80: =C32+V80 -> 31.083333
A81: Ut | B81: internet | G81: =DSUM(Kontoutdrag_officiella!$A:$J,"t",'Villkor 1 år (2014)'!$A17:$J18) -> -299 | H81: =DSUM(Kontoutdrag_officiella!$A:$J,"t",'Villkor 1 år (2014)'!$A83:$J84) -> -299 | I81: =DSUM(Kontoutdrag_officiella!$A:$J,"t",'Villkor 1 år (2014)'!$A149:$J150) -> -299 | J81: =DSUM(Kontoutdrag_officiella!$A:$J,"t",'Villkor 1 år (2014)'!$A215:$J216) -> -299 | K81: =DSUM(Kontoutdrag_officiella!$A:$J,"t",'Villkor 1 år (2014)'!$A281:$J282) -> -299 | L81: =DSUM(Kontoutdrag_officiella!$A:$J,"t",'Villkor 1 år (2014)'!$A347:$J348) -> -299 | M81: =DSUM(Kontoutdrag_officiella!$A:$J,"t",'Villkor 1 år (2014)'!$A413:$J414) -> -299 | N81: =DSUM(Kontoutdrag_officiella!$A:$J,"t",'Villkor 1 år (2014)'!$A479:$J480) -> -299 | O81: =DSUM(Kontoutdrag_officiella!$A:$J,"t",'Villkor 1 år (2014)'!$A545:$J546) -> -299 | P81: =DSUM(Kontoutdrag_officiella!$A:$J,"t",'Villkor 1 år (2014)'!$A611:$J612) -> -299 | Q81: =DSUM(Kontoutdrag_officiella!$A:$J,"t",'Villkor 1 år (2014)'!$A677:$J678) -> -299 | R81: =DSUM(Kontoutdrag_officiella!$A:$J,"t",'Villkor 1 år (2014)'!$A743:$J744) -> -299 | S81: =SUM(G81:R81) -> -3588 | T81: internet | V81: =S81/$V$71 -> -299 | W81: =SUM(S81)/W$71 -> -299 | X81: =C33 -> 299 | Y81: =C33+V81 -> 0
A82: Ut | B82: telefonsamtal | G82: =DSUM(Kontoutdrag_officiella!$A:$J,"t",'Villkor 1 år (2014)'!$A19:$J20) -> -472 | H82: =DSUM(Kontoutdrag_officiella!$A:$J,"t",'Villkor 1 år (2014)'!$A85:$J86) -> 0 | I82: =DSUM(Kontoutdrag_officiella!$A:$J,"t",'Villkor 1 år (2014)'!$A151:$J152) -> -475 | J82: =DSUM(Kontoutdrag_officiella!$A:$J,"t",'Villkor 1 år (2014)'!$A217:$J218) -> -469 | K82: =DSUM(Kontoutdrag_officiella!$A:$J,"t",'Villkor 1 år (2014)'!$A283:$J284) -> -938 | L82: =DSUM(Kontoutdrag_officiella!$A:$J,"t",'Villkor 1 år (2014)'!$A349:$J350) -> 0 | M82: =DSUM(Kontoutdrag_officiella!$A:$J,"t",'Villkor 1 år (2014)'!$A415:$J416) -> -505 | N82: =DSUM(Kontoutdrag_officiella!$A:$J,"t",'Villkor 1 år (2014)'!$A481:$J482) -> -469 | O82: =DSUM(Kontoutdrag_officiella!$A:$J,"t",'Villkor 1 år (2014)'!$A547:$J548) -> -612 | P82: =DSUM(Kontoutdrag_officiella!$A:$J,"t",'Villkor 1 år (2014)'!$A613:$J614) -> -995 | Q82: =DSUM(Kontoutdrag_officiella!$A:$J,"t",'Villkor 1 år (2014)'!$A679:$J680) -> 0 | R82: =DSUM(Kontoutdrag_officiella!$A:$J,"t",'Villkor 1 år (2014)'!$A745:$J746) -> -938 | S82: =SUM(G82:R82) -> -5873 | T82: telefonsamtal | V82: =S82/$V$71 -> -489.41667 | W82: =SUM(S82)/W$71 -> -489.41667 | X82: =C34 -> 519 | Y82: =C34+V82 -> 29.583333
A83: Ut | B83: hygien (disk, tvätt o tvål etc) | G83: =DSUM(Kontoutdrag_officiella!$A:$J,"t",'Villkor 1 år (2014)'!$A21:$J22) -> 0 | H83: =DSUM(Kontoutdrag_officiella!$A:$J,"t",'Villkor 1 år (2014)'!$A87:$J88) -> 0 | I83: =DSUM(Kontoutdrag_officiella!$A:$J,"t",'Villkor 1 år (2014)'!$A153:$J154) -> 0 | J83: =DSUM(Kontoutdrag_officiella!$A:$J,"t",'Villkor 1 år (2014)'!$A219:$J220) -> 0 | K83: =DSUM(Kontoutdrag_officiella!$A:$J,"t",'Villkor 1 år (2014)'!$A285:$J286) -> 0 | L83: =DSUM(Kontoutdrag_officiella!$A:$J,"t",'Villkor 1 år (2014)'!$A351:$J352) -> 0 | M83: =DSUM(Kontoutdrag_officiella!$A:$J,"t",'Villkor 1 år (2014)'!$A417:$J418) -> 0 | N83: =DSUM(Kontoutdrag_officiella!$A:$J,"t",'Villkor 1 år (2014)'!$A483:$J484) -> 0 | O83: =DSUM(Kontoutdrag_officiella!$A:$J,"t",'Villkor 1 år (2014)'!$A549:$J550) -> 0 | P83: =DSUM(Kontoutdrag_officiella!$A:$J,"t",'Villkor 1 år (2014)'!$A615:$J616) -> 0 | Q83: =DSUM(Kontoutdrag_officiella!$A:$J,"t",'Villkor 1 år (2014)'!$A681:$J682) -> 0 | R83: =DSUM(Kontoutdrag_officiella!$A:$J,"t",'Villkor 1 år (2014)'!$A747:$J748) -> 0 | S83: =SUM(G83:R83) -> 0 | T83: hygien (disk, tvätt o tvål etc) | V83: =S83/$V$71 -> 0 | W83: =SUM(S83)/W$71 -> 0 | X83: =C35 -> 30 | Y83: =C35+V83 -> 30
A84: Ut | B84: hemlagad mat | G84: =DSUM(Kontoutdrag_officiella!$A:$J,"t",'Villkor 1 år (2014)'!$A23:$J24) -> -148.2 | H84: =DSUM(Kontoutdrag_officiella!$A:$J,"t",'Villkor 1 år (2014)'!$A89:$J90) -> 0 | I84: =DSUM(Kontoutdrag_officiella!$A:$J,"t",'Villkor 1 år (2014)'!$A155:$J156) -> -1680 | J84: =DSUM(Kontoutdrag_officiella!$A:$J,"t",'Villkor 1 år (2014)'!$A221:$J222) -> -204.7 | K84: =DSUM(Kontoutdrag_officiella!$A:$J,"t",'Villkor 1 år (2014)'!$A287:$J288) -> 0 | L84: =DSUM(Kontoutdrag_officiella!$A:$J,"t",'Villkor 1 år (2014)'!$A353:$J354) -> -1000 | M84: =DSUM(Kontoutdrag_officiella!$A:$J,"t",'Villkor 1 år (2014)'!$A419:$J420) -> 0 | N84: =DSUM(Kontoutdrag_officiella!$A:$J,"t",'Villkor 1 år (2014)'!$A485:$J486) -> 0 | O84: =DSUM(Kontoutdrag_officiella!$A:$J,"t",'Villkor 1 år (2014)'!$A551:$J552) -> -576.87 | P84: =DSUM(Kontoutdrag_officiella!$A:$J,"t",'Villkor 1 år (2014)'!$A617:$J618) -> -294.91 | Q84: =DSUM(Kontoutdrag_officiella!$A:$J,"t",'Villkor 1 år (2014)'!$A683:$J684) -> -35.75 | R84: =DSUM(Kontoutdrag_officiella!$A:$J,"t",'Villkor 1 år (2014)'!$A749:$J750) -> -366.64 | S84: =SUM(G84:R84) -> -4307.07 | T84: hemlagad mat | V84: =S84/$V$71 -> -358.9225 | W84: =SUM(S84)/W$71 -> -358.9225 | X84: =C36 -> 600 | Y84: =C36+V84 -> 241.0775
A85: Ut | B85: hemlagad lunch | G85: =DSUM(Kontoutdrag_officiella!$A:$J,"t",'Villkor 1 år (2014)'!$A25:$J26) -> 0 | H85: =DSUM(Kontoutdrag_officiella!$A:$J,"t",'Villkor 1 år (2014)'!$A91:$J92) -> 0 | I85: =DSUM(Kontoutdrag_officiella!$A:$J,"t",'Villkor 1 år (2014)'!$A157:$J158) -> 0 | J85: =DSUM(Kontoutdrag_officiella!$A:$J,"t",'Villkor 1 år (2014)'!$A223:$J224) -> 0 | K85: =DSUM(Kontoutdrag_officiella!$A:$J,"t",'Villkor 1 år (2014)'!$A289:$J290) -> 0 | L85: =DSUM(Kontoutdrag_officiella!$A:$J,"t",'Villkor 1 år (2014)'!$A355:$J356) -> 0 | M85: =DSUM(Kontoutdrag_officiella!$A:$J,"t",'Villkor 1 år (2014)'!$A421:$J422) -> 0 | N85: =DSUM(Kontoutdrag_officiella!$A:$J,"t",'Villkor 1 år (2014)'!$A487:$J488) -> 0 | O85: =DSUM(Kontoutdrag_officiella!$A:$J,"t",'Villkor 1 år (2014)'!$A553:$J554) -> 0 | P85: =DSUM(Kontoutdrag_officiella!$A:$J,"t",'Villkor 1 år (2014)'!$A619:$J620) -> 0 | Q85: =DSUM(Kontoutdrag_officiella!$A:$J,"t",'Villkor 1 år (2014)'!$A685:$J686) -> 0 | R85: =DSUM(Kontoutdrag_officiella!$A:$J,"t",'Villkor 1 år (2014)'!$A751:$J752) -> 0 | S85: =SUM(G85:R85) -> 0 | T85: hemlagad lunch | V85: =S85/$V$71 -> 0 | W85: =SUM(S85)/W$71 -> 0 | X85: =C37 -> 0 | Y85: =C37+V85 -> 0 | Z85: L ute okt+nov
A86: Ut | B86: lunch utemat | G86: =DSUM(Kontoutdrag_officiella!$A:$J,"t",'Villkor 1 år (2014)'!$A27:$J28) -> -1885 | H86: =DSUM(Kontoutdrag_officiella!$A:$J,"t",'Villkor 1 år (2014)'!$A93:$J94) -> -800 | I86: =DSUM(Kontoutdrag_officiella!$A:$J,"t",'Villkor 1 år (2014)'!$A159:$J160) -> -1755 | J86: =DSUM(Kontoutdrag_officiella!$A:$J,"t",'Villkor 1 år (2014)'!$A225:$J226) -> -1600 | K86: =DSUM(Kontoutdrag_officiella!$A:$J,"t",'Villkor 1 år (2014)'!$A291:$J292) -> -879 | L86: =DSUM(Kontoutdrag_officiella!$A:$J,"t",'Villkor 1 år (2014)'!$A357:$J358) -> -175 | M86: =DSUM(Kontoutdrag_officiella!$A:$J,"t",'Villkor 1 år (2014)'!$A423:$J424) -> 0 | N86: =DSUM(Kontoutdrag_officiella!$A:$J,"t",'Villkor 1 år (2014)'!$A489:$J490) -> -1498 | O86: =DSUM(Kontoutdrag_officiella!$A:$J,"t",'Villkor 1 år (2014)'!$A555:$J556) -> -1983 | P86: =DSUM(Kontoutdrag_officiella!$A:$J,"t",'Villkor 1 år (2014)'!$A621:$J622) -> -1125 | Q86: =DSUM(Kontoutdrag_officiella!$A:$J,"t",'Villkor 1 år (2014)'!$A687:$J688) -> -2010 | R86: =DSUM(Kontoutdrag_officiella!$A:$J,"t",'Villkor 1 år (2014)'!$A753:$J754) -> -964 | S86: =SUM(G86:R86) -> -14674 | T86: lunch utemat | V86: =S86/$V$71 -> -1222.8333 | W86: =SUM(S86)/W$71 -> -1222.8333 | X86: =C38 -> 1441.3636 | Y86: =C38+V86 -> 218.5303 | Z86: =0.5*(P86+Q86) -> -1567.5
A87: Ut | B87: nöjes utemat | G87: =DSUM(Kontoutdrag_officiella!$A:$J,"t",'Villkor 1 år (2014)'!$A29:$J30) -> -1827.96 | H87: =DSUM(Kontoutdrag_officiella!$A:$J,"t",'Villkor 1 år (2014)'!$A95:$J96) -> -2975.3 | I87: =DSUM(Kontoutdrag_officiella!$A:$J,"t",'Villkor 1 år (2014)'!$A161:$J162) -> -2165.34 | J87: =DSUM(Kontoutdrag_officiella!$A:$J,"t",'Villkor 1 år (2014)'!$A227:$J228) -> -2548.48 | K87: =DSUM(Kontoutdrag_officiella!$A:$J,"t",'Villkor 1 år (2014)'!$A293:$J294) -> -3314 | L87: =DSUM(Kontoutdrag_officiella!$A:$J,"t",'Villkor 1 år (2014)'!$A359:$J360) -> -1625.48 | M87: =DSUM(Kontoutdrag_officiella!$A:$J,"t",'Villkor 1 år (2014)'!$A425:$J426) -> -929 | N87: =DSUM(Kontoutdrag_officiella!$A:$J,"t",'Villkor 1 år (2014)'!$A491:$J492) -> -2559.8 | O87: =DSUM(Kontoutdrag_officiella!$A:$J,"t",'Villkor 1 år (2014)'!$A557:$J558) -> -2033.75 | P87: =DSUM(Kontoutdrag_officiella!$A:$J,"t",'Villkor 1 år (2014)'!$A623:$J624) -> -3345.55 | Q87: =DSUM(Kontoutdrag_officiella!$A:$J,"t",'Villkor 1 år (2014)'!$A689:$J690) -> -2480.03 | R87: =DSUM(Kontoutdrag_officiella!$A:$J,"t",'Villkor 1 år (2014)'!$A755:$J756) -> -1490.95 | S87: =SUM(G87:R87) -> -27295.64 | T87: nöjes utemat | V87: =S87/$V$71 -> -2274.6367 | W87: =SUM(S87)/W$71 -> -2274.6367 | X87: =C39 -> 2100 | Y87: =C39+V87 -> -174.63667
A88: Ut | B88: mat i samband med supa | G88: =DSUM(Kontoutdrag_officiella!$A:$J,"t",'Villkor 1 år (2014)'!$A31:$J32) -> 0 | H88: =DSUM(Kontoutdrag_officiella!$A:$J,"t",'Villkor 1 år (2014)'!$A97:$J98) -> 0 | I88: =DSUM(Kontoutdrag_officiella!$A:$J,"t",'Villkor 1 år (2014)'!$A163:$J164) -> 0 | J88: =DSUM(Kontoutdrag_officiella!$A:$J,"t",'Villkor 1 år (2014)'!$A229:$J230) -> 0 | K88: =DSUM(Kontoutdrag_officiella!$A:$J,"t",'Villkor 1 år (2014)'!$A295:$J296) -> -1917.5 | L88: =DSUM(Kontoutdrag_officiella!$A:$J,"t",'Villkor 1 år (2014)'!$A361:$J362) -> -626 | M88: =DSUM(Kontoutdrag_officiella!$A:$J,"t",'Villkor 1 år (2014)'!$A427:$J428) -> 0 | N88: =DSUM(Kontoutdrag_officiella!$A:$J,"t",'Villkor 1 år (2014)'!$A493:$J494) -> -1840 | O88: =DSUM(Kontoutdrag_officiella!$A:$J,"t",'Villkor 1 år (2014)'!$A559:$J560) -> -1305 | P88: =DSUM(Kontoutdrag_officiella!$A:$J,"t",'Villkor 1 år (2014)'!$A625:$J626) -> -458 | Q88: =DSUM(Kontoutdrag_officiella!$A:$J,"t",'Villkor 1 år (2014)'!$A691:$J692) -> -3034.3 | R88: =DSUM(Kontoutdrag_officiella!$A:$J,"t",'Villkor 1 år (2014)'!$A757:$J758) -> -1283 | S88: =SUM(G88:R88) -> -10463.8 | T88: mat i samband med supa | V88: =S88/$V$71 -> -871.98333 | W88: =SUM(S88)/W$71 -> -871.98333 | X88: =C40 -> 1477.4997 | Y88: =C40+V88 -> 605.51636
A89: Ut | B89: alkohol | G89: =DSUM(Kontoutdrag_officiella!$A:$J,"t",'Villkor 1 år (2014)'!$A33:$J34) -> 0 | H89: =DSUM(Kontoutdrag_officiella!$A:$J,"t",'Villkor 1 år (2014)'!$A99:$J100) -> -548 | I89: =DSUM(Kontoutdrag_officiella!$A:$J,"t",'Villkor 1 år (2014)'!$A165:$J166) -> -358 | J89: =DSUM(Kontoutdrag_officiella!$A:$J,"t",'Villkor 1 år (2014)'!$A231:$J232) -> -472 | K89: =DSUM(Kontoutdrag_officiella!$A:$J,"t",'Villkor 1 år (2014)'!$A297:$J298) -> -464 | L89: =DSUM(Kontoutdrag_officiella!$A:$J,"t",'Villkor 1 år (2014)'!$A363:$J364) -> -171 | M89: =DSUM(Kontoutdrag_officiella!$A:$J,"t",'Villkor 1 år (2014)'!$A429:$J430) -> -152 | N89: =DSUM(Kontoutdrag_officiella!$A:$J,"t",'Villkor 1 år (2014)'!$A495:$J496) -> -1143 | O89: =DSUM(Kontoutdrag_officiella!$A:$J,"t",'Villkor 1 år (2014)'!$A561:$J562) -> -262 | P89: =DSUM(Kontoutdrag_officiella!$A:$J,"t",'Villkor 1 år (2014)'!$A627:$J628) -> -424 | Q89: =DSUM(Kontoutdrag_officiella!$A:$J,"t",'Villkor 1 år (2014)'!$A693:$J694) -> -467 | R89: =DSUM(Kontoutdrag_officiella!$A:$J,"t",'Villkor 1 år (2014)'!$A759:$J760) -> -208 | S89: =SUM(G89:R89) -> -4669 | T89: alkohol | V89: =S89/$V$71 -> -389.08333 | W89: =SUM(S89)/W$71 -> -389.08333 | X89: =C41 -> 247.5 | Y89: =C41+V89 -> -141.58333
A90: Ut | B90: taxi efter supa | G90: =DSUM(Kontoutdrag_officiella!$A:$J,"t",'Villkor 1 år (2014)'!$A35:$J36) -> 0 | H90: =DSUM(Kontoutdrag_officiella!$A:$J,"t",'Villkor 1 år (2014)'!$A101:$J102) -> 0 | I90: =DSUM(Kontoutdrag_officiella!$A:$J,"t",'Villkor 1 år (2014)'!$A167:$J168) -> 0 | J90: =DSUM(Kontoutdrag_officiella!$A:$J,"t",'Villkor 1 år (2014)'!$A233:$J234) -> 0 | K90: =DSUM(Kontoutdrag_officiella!$A:$J,"t",'Villkor 1 år (2014)'!$A299:$J300) -> 0 | L90: =DSUM(Kontoutdrag_officiella!$A:$J,"t",'Villkor 1 år (2014)'!$A365:$J366) -> -118 | M90: =DSUM(Kontoutdrag_officiella!$A:$J,"t",'Villkor 1 år (2014)'!$A431:$J432) -> -300 | N90: =DSUM(Kontoutdrag_officiella!$A:$J,"t",'Villkor 1 år (2014)'!$A497:$J498) -> -70 | O90: =DSUM(Kontoutdrag_officiella!$A:$J,"t",'Villkor 1 år (2014)'!$A563:$J564) -> 0 | P90: =DSUM(Kontoutdrag_officiella!$A:$J,"t",'Villkor 1 år (2014)'!$A629:$J630) -> 0 | Q90: =DSUM(Kontoutdrag_officiella!$A:$J,"t",'Villkor 1 år (2014)'!$A695:$J696) -> 0 | R90: =DSUM(Kontoutdrag_officiella!$A:$J,"t",'Villkor 1 år (2014)'!$A761:$J762) -> 0 | S90: =SUM(G90:R90) -> -488 | T90: taxi efter supa | V90: =S90/$V$71 -> -40.666667 | W90: =SUM(S90)/W$71 -> -40.666667 | X90: =C42 -> 0 | Y90: =C42+V90 -> -40.666667
A91: Ut | B91: Buss etc i samband med supa | G91: =DSUM(Kontoutdrag_officiella!$A:$J,"t",'Villkor 1 år (2014)'!$A37:$J38) -> 0 | H91: =DSUM(Kontoutdrag_officiella!$A:$J,"t",'Villkor 1 år (2014)'!$A103:$J104) -> 0 | I91: =DSUM(Kontoutdrag_officiella!$A:$J,"t",'Villkor 1 år (2014)'!$A169:$J170) -> 0 | J91: =DSUM(Kontoutdrag_officiella!$A:$J,"t",'Villkor 1 år (2014)'!$A235:$J236) -> 0 | K91: =DSUM(Kontoutdrag_officiella!$A:$J,"t",'Villkor 1 år (2014)'!$A301:$J302) -> 0 | L91: =DSUM(Kontoutdrag_officiella!$A:$J,"t",'Villkor 1 år (2014)'!$A367:$J368) -> 0 | M91: =DSUM(Kontoutdrag_officiella!$A:$J,"t",'Villkor 1 år (2014)'!$A433:$J434) -> 0 | N91: =DSUM(Kontoutdrag_officiella!$A:$J,"t",'Villkor 1 år (2014)'!$A499:$J500) -> 0 | O91: =DSUM(Kontoutdrag_officiella!$A:$J,"t",'Villkor 1 år (2014)'!$A565:$J566) -> 0 | P91: =DSUM(Kontoutdrag_officiella!$A:$J,"t",'Villkor 1 år (2014)'!$A631:$J632) -> 0 | Q91: =DSUM(Kontoutdrag_officiella!$A:$J,"t",'Villkor 1 år (2014)'!$A697:$J698) -> 0 | R91: =DSUM(Kontoutdrag_officiella!$A:$J,"t",'Villkor 1 år (2014)'!$A763:$J764) -> 0 | S91: =SUM(G91:R91) -> 0 | T91: Buss etc i samband med supa | V91: =S91/$V$71 -> 0 | W91: =SUM(S91)/W$71 -> 0 | X91: =C43 -> 0 | Y91: =C43+V91 -> 0
A92: Ut | B92: oväntade utgifter | G92: =DSUM(Kontoutdrag_officiella!$A:$J,"t",'Villkor 1 år (2014)'!$A39:$J40) -> 0 | H92: =DSUM(Kontoutdrag_officiella!$A:$J,"t",'Villkor 1 år (2014)'!$A105:$J106) -> -124 | I92: =DSUM(Kontoutdrag_officiella!$A:$J,"t",'Villkor 1 år (2014)'!$A171:$J172) -> 0 | J92: =DSUM(Kontoutdrag_officiella!$A:$J,"t",'Villkor 1 år (2014)'!$A237:$J238) -> -126 | K92: =DSUM(Kontoutdrag_officiella!$A:$J,"t",'Villkor 1 år (2014)'!$A303:$J304) -> 0 | L92: =DSUM(Kontoutdrag_officiella!$A:$J,"t",'Villkor 1 år (2014)'!$A369:$J370) -> -652 | M92: =DSUM(Kontoutdrag_officiella!$A:$J,"t",'Villkor 1 år (2014)'!$A435:$J436) -> -315 | N92: =DSUM(Kontoutdrag_officiella!$A:$J,"t",'Villkor 1 år (2014)'!$A501:$J502) -> 366 | O92: =DSUM(Kontoutdrag_officiella!$A:$J,"t",'Villkor 1 år (2014)'!$A567:$J568) -> 0 | P92: =DSUM(Kontoutdrag_officiella!$A:$J,"t",'Villkor 1 år (2014)'!$A633:$J634) -> 0 | Q92: =DSUM(Kontoutdrag_officiella!$A:$J,"t",'Villkor 1 år (2014)'!$A699:$J700) -> 0 | R92: =DSUM(Kontoutdrag_officiella!$A:$J,"t",'Villkor 1 år (2014)'!$A765:$J766) -> -325 | S92: =SUM(G92:R92) -> -1176 | T92: oväntade utgifter | V92: =S92/$V$71 -> -98 | W92: =SUM(S92)/W$71 -> -98 | X92: =C44 -> 100 | Y92: =C44+V92 -> 2
A93: Ut | B93: Småresor ej supa | G93: =DSUM(Kontoutdrag_officiella!$A:$J,"t",'Villkor 1 år (2014)'!$A41:$J42) -> -1970 | H93: =DSUM(Kontoutdrag_officiella!$A:$J,"t",'Villkor 1 år (2014)'!$A107:$J108) -> 0 | I93: =DSUM(Kontoutdrag_officiella!$A:$J,"t",'Villkor 1 år (2014)'!$A173:$J174) -> 0 | J93: =DSUM(Kontoutdrag_officiella!$A:$J,"t",'Villkor 1 år (2014)'!$A239:$J240) -> -1521 | K93: =DSUM(Kontoutdrag_officiella!$A:$J,"t",'Villkor 1 år (2014)'!$A305:$J306) -> 0 | L93: =DSUM(Kontoutdrag_officiella!$A:$J,"t",'Villkor 1 år (2014)'!$A371:$J372) -> 0 | M93: =DSUM(Kontoutdrag_officiella!$A:$J,"t",'Villkor 1 år (2014)'!$A437:$J438) -> 0 | N93: =DSUM(Kontoutdrag_officiella!$A:$J,"t",'Villkor 1 år (2014)'!$A503:$J504) -> -1821 | O93: =DSUM(Kontoutdrag_officiella!$A:$J,"t",'Villkor 1 år (2014)'!$A569:$J570) -> 0 | P93: =DSUM(Kontoutdrag_officiella!$A:$J,"t",'Villkor 1 år (2014)'!$A635:$J636) -> -1470 | Q93: =DSUM(Kontoutdrag_officiella!$A:$J,"t",'Villkor 1 år (2014)'!$A701:$J702) -> 0 | R93: =DSUM(Kontoutdrag_officiella!$A:$J,"t",'Villkor 1 år (2014)'!$A767:$J768) -> 0 | S93: =SUM(G93:R93) -> -6782 | T93: Småresor ej supa | V93: =S93/$V$71 -> -565.16667 | W93: =SUM(S93)/W$71 -> -565.16667 | X93: =C45 -> 285 | Y93: =C45+V93 -> -280.16667
A94: Ut | B94: resor i samband med utflykt | G94: =DSUM(Kontoutdrag_officiella!$A:$J,"t",'Villkor 1 år (2014)'!$A43:$J44) -> 0 | H94: =DSUM(Kontoutdrag_officiella!$A:$J,"t",'Villkor 1 år (2014)'!$A109:$J110) -> 0 | I94: =DSUM(Kontoutdrag_officiella!$A:$J,"t",'Villkor 1 år (2014)'!$A175:$J176) -> 0 | J94: =DSUM(Kontoutdrag_officiella!$A:$J,"t",'Villkor 1 år (2014)'!$A241:$J242) -> 0 | K94: =DSUM(Kontoutdrag_officiella!$A:$J,"t",'Villkor 1 år (2014)'!$A307:$J308) -> 0 | L94: =DSUM(Kontoutdrag_officiella!$A:$J,"t",'Villkor 1 år (2014)'!$A373:$J374) -> 0 | M94: =DSUM(Kontoutdrag_officiella!$A:$J,"t",'Villkor 1 år (2014)'!$A439:$J440) -> -400 | N94: =DSUM(Kontoutdrag_officiella!$A:$J,"t",'Villkor 1 år (2014)'!$A505:$J506) -> -1397 | O94: =DSUM(Kontoutdrag_officiella!$A:$J,"t",'Villkor 1 år (2014)'!$A571:$J572) -> 0 | P94: =DSUM(Kontoutdrag_officiella!$A:$J,"t",'Villkor 1 år (2014)'!$A637:$J638) -> 0 | Q94: =DSUM(Kontoutdrag_officiella!$A:$J,"t",'Villkor 1 år (2014)'!$A703:$J704) -> 0 | R94: =DSUM(Kontoutdrag_officiella!$A:$J,"t",'Villkor 1 år (2014)'!$A769:$J770) -> 0 | S94: =SUM(G94:R94) -> -1797 | T94: resor i samband med utflykt | V94: =S94/$V$71 -> -149.75 | W94: =SUM(S94)/W$71 -> -149.75 | X94: =C46 -> 250 | Y94: =C46+V94 -> 100.25
A95: Ut | B95: värnamoresor+övriga | G95: =DSUM(Kontoutdrag_officiella!$A:$J,"t",'Villkor 1 år (2014)'!$A45:$J46) -> 0 | H95: =DSUM(Kontoutdrag_officiella!$A:$J,"t",'Villkor 1 år (2014)'!$A111:$J112) -> 0 | I95: =DSUM(Kontoutdrag_officiella!$A:$J,"t",'Villkor 1 år (2014)'!$A177:$J178) -> 0 | J95: =DSUM(Kontoutdrag_officiella!$A:$J,"t",'Villkor 1 år (2014)'!$A243:$J244) -> -977 | K95: =DSUM(Kontoutdrag_officiella!$A:$J,"t",'Villkor 1 år (2014)'!$A309:$J310) -> 0 | L95: =DSUM(Kontoutdrag_officiella!$A:$J,"t",'Villkor 1 år (2014)'!$A375:$J376) -> -1205 | M95: =DSUM(Kontoutdrag_officiella!$A:$J,"t",'Villkor 1 år (2014)'!$A441:$J442) -> 0 | N95: =DSUM(Kontoutdrag_officiella!$A:$J,"t",'Villkor 1 år (2014)'!$A507:$J508) -> 0 | O95: =DSUM(Kontoutdrag_officiella!$A:$J,"t",'Villkor 1 år (2014)'!$A573:$J574) -> 0 | P95: =DSUM(Kontoutdrag_officiella!$A:$J,"t",'Villkor 1 år (2014)'!$A639:$J640) -> 0 | Q95: =DSUM(Kontoutdrag_officiella!$A:$J,"t",'Villkor 1 år (2014)'!$A705:$J706) -> 0 | R95: =DSUM(Kontoutdrag_officiella!$A:$J,"t",'Villkor 1 år (2014)'!$A771:$J772) -> -435 | S95: =SUM(G95:R95) -> -2617 | T95: värnamoresor+övriga | V95: =S95/$V$71 -> -218.08333 | W95: =SUM(S95)/W$71 -> -218.08333 | X95: =C47 -> 200 | Y95: =C47+V95 -> -18.083333
A96: Ut | B96: spara almänt | G96: =DSUM(Kontoutdrag_officiella!$A:$J,"t",'Villkor 1 år (2014)'!$A47:$J48) -> 0 | H96: =DSUM(Kontoutdrag_officiella!$A:$J,"t",'Villkor 1 år (2014)'!$A113:$J114) -> -129 | I96: =DSUM(Kontoutdrag_officiella!$A:$J,"t",'Villkor 1 år (2014)'!$A179:$J180) -> 0 | J96: =DSUM(Kontoutdrag_officiella!$A:$J,"t",'Villkor 1 år (2014)'!$A245:$J246) -> -297.3 | K96: =DSUM(Kontoutdrag_officiella!$A:$J,"t",'Villkor 1 år (2014)'!$A311:$J312) -> 0 | L96: =DSUM(Kontoutdrag_officiella!$A:$J,"t",'Villkor 1 år (2014)'!$A377:$J378) -> 0 | M96: =DSUM(Kontoutdrag_officiella!$A:$J,"t",'Villkor 1 år (2014)'!$A443:$J444) -> -7480.5 | N96: =DSUM(Kontoutdrag_officiella!$A:$J,"t",'Villkor 1 år (2014)'!$A509:$J510) -> 0 | O96: =DSUM(Kontoutdrag_officiella!$A:$J,"t",'Villkor 1 år (2014)'!$A575:$J576) -> -200 | P96: =DSUM(Kontoutdrag_officiella!$A:$J,"t",'Villkor 1 år (2014)'!$A641:$J642) -> -41 | Q96: =DSUM(Kontoutdrag_officiella!$A:$J,"t",'Villkor 1 år (2014)'!$A707:$J708) -> 0 | R96: =DSUM(Kontoutdrag_officiella!$A:$J,"t",'Villkor 1 år (2014)'!$A773:$J774) -> 939 | S96: =SUM(G96:R96) -> -7208.8 | T96: spara almänt | V96: =S96/$V$71 -> -600.73333 | W96: =SUM(S96)/W$71 -> -600.73333 | X96: =C48 -> 1131.72 | Y96: =C48+V96 -> 530.98667
A97: Ut | B97: spara till amortering | G97: =DSUM(Kontoutdrag_officiella!$A:$J,"t",'Villkor 1 år (2014)'!$A49:$J50) -> -250 | H97: =DSUM(Kontoutdrag_officiella!$A:$J,"t",'Villkor 1 år (2014)'!$A115:$J116) -> -250 | I97: =DSUM(Kontoutdrag_officiella!$A:$J,"t",'Villkor 1 år (2014)'!$A181:$J182) -> -250 | J97: =DSUM(Kontoutdrag_officiella!$A:$J,"t",'Villkor 1 år (2014)'!$A247:$J248) -> -250 | K97: =DSUM(Kontoutdrag_officiella!$A:$J,"t",'Villkor 1 år (2014)'!$A313:$J314) -> -250 | L97: =DSUM(Kontoutdrag_officiella!$A:$J,"t",'Villkor 1 år (2014)'!$A379:$J380) -> 22961 | M97: =DSUM(Kontoutdrag_officiella!$A:$J,"t",'Villkor 1 år (2014)'!$A445:$J446) -> -250 | N97: =DSUM(Kontoutdrag_officiella!$A:$J,"t",'Villkor 1 år (2014)'!$A511:$J512) -> -250 | O97: =DSUM(Kontoutdrag_officiella!$A:$J,"t",'Villkor 1 år (2014)'!$A577:$J578) -> -250 | P97: =DSUM(Kontoutdrag_officiella!$A:$J,"t",'Villkor 1 år (2014)'!$A643:$J644) -> -250 | Q97: =DSUM(Kontoutdrag_officiella!$A:$J,"t",'Villkor 1 år (2014)'!$A709:$J710) -> -250 | R97: =DSUM(Kontoutdrag_officiella!$A:$J,"t",'Villkor 1 år (2014)'!$A775:$J776) -> -250 | S97: =SUM(G97:R97) -> 20211 | T97: spara till amortering | V97: =S97/$V$71 -> 1684.25 | W97: =SUM(S97)/W$71 -> 1684.25 | X97: =C49 -> 2507 | Y97: =C49+V97 -> 4191.25
A98: Ut | B98: spara till sommarrussel | G98: =DSUM(Kontoutdrag_officiella!$A:$J,"t",'Villkor 1 år (2014)'!$A51:$J52) -> 0 | H98: =DSUM(Kontoutdrag_officiella!$A:$J,"t",'Villkor 1 år (2014)'!$A117:$J118) -> 0 | I98: =DSUM(Kontoutdrag_officiella!$A:$J,"t",'Villkor 1 år (2014)'!$A183:$J184) -> 0 | J98: =DSUM(Kontoutdrag_officiella!$A:$J,"t",'Villkor 1 år (2014)'!$A249:$J250) -> -5085 | K98: =DSUM(Kontoutdrag_officiella!$A:$J,"t",'Villkor 1 år (2014)'!$A315:$J316) -> 0 | L98: =DSUM(Kontoutdrag_officiella!$A:$J,"t",'Villkor 1 år (2014)'!$A381:$J382) -> -255.95 | M98: =DSUM(Kontoutdrag_officiella!$A:$J,"t",'Villkor 1 år (2014)'!$A447:$J448) -> -18146.42 | N98: =DSUM(Kontoutdrag_officiella!$A:$J,"t",'Villkor 1 år (2014)'!$A513:$J514) -> -3615.31 | O98: =DSUM(Kontoutdrag_officiella!$A:$J,"t",'Villkor 1 år (2014)'!$A579:$J580) -> 137.96 | P98: =DSUM(Kontoutdrag_officiella!$A:$J,"t",'Villkor 1 år (2014)'!$A645:$J646) -> 121 | Q98: =DSUM(Kontoutdrag_officiella!$A:$J,"t",'Villkor 1 år (2014)'!$A711:$J712) -> 0 | R98: =DSUM(Kontoutdrag_officiella!$A:$J,"t",'Villkor 1 år (2014)'!$A777:$J778) -> 0 | S98: =SUM(G98:R98) -> -26843.72 | T98: spara till sommarrussel | V98: =S98/$V$71 -> -2236.9767 | W98: =SUM(S98)/W$71 -> -2236.9767 | X98: =C50 -> 1250 | Y98: =C50+V98 -> -986.97667
A99: Ut | B99: spara till dator | G99: =DSUM(Kontoutdrag_officiella!$A:$J,"t",'Villkor 1 år (2014)'!$A53:$J54) -> 0 | H99: =DSUM(Kontoutdrag_officiella!$A:$J,"t",'Villkor 1 år (2014)'!$A119:$J120) -> 0 | I99: =DSUM(Kontoutdrag_officiella!$A:$J,"t",'Villkor 1 år (2014)'!$A185:$J186) -> 0 | J99: =DSUM(Kontoutdrag_officiella!$A:$J,"t",'Villkor 1 år (2014)'!$A251:$J252) -> 0 | K99: =DSUM(Kontoutdrag_officiella!$A:$J,"t",'Villkor 1 år (2014)'!$A317:$J318) -> 0 | L99: =DSUM(Kontoutdrag_officiella!$A:$J,"t",'Villkor 1 år (2014)'!$A383:$J384) -> 0 | M99: =DSUM(Kontoutdrag_officiella!$A:$J,"t",'Villkor 1 år (2014)'!$A449:$J450) -> 0 | N99: =DSUM(Kontoutdrag_officiella!$A:$J,"t",'Villkor 1 år (2014)'!$A515:$J516) -> 0 | O99: =DSUM(Kontoutdrag_officiella!$A:$J,"t",'Villkor 1 år (2014)'!$A581:$J582) -> 0 | P99: =DSUM(Kontoutdrag_officiella!$A:$J,"t",'Villkor 1 år (2014)'!$A647:$J648) -> 0 | Q99: =DSUM(Kontoutdrag_officiella!$A:$J,"t",'Villkor 1 år (2014)'!$A713:$J714) -> 0 | R99: =DSUM(Kontoutdrag_officiella!$A:$J,"t",'Villkor 1 år (2014)'!$A779:$J780) -> 0 | S99: =SUM(G99:R99) -> 0 | T99: spara till dator | V99: =S99/$V$71 -> 0 | W99: =SUM(S99)/W$71 -> 0 | X99: =C51 -> 350 | Y99: =C51+V99 -> 350
A100: Ut | B100: spara till russel övrigt | G100: =DSUM(Kontoutdrag_officiella!$A:$J,"t",'Villkor 1 år (2014)'!$A55:$J56) -> 635 | H100: =DSUM(Kontoutdrag_officiella!$A:$J,"t",'Villkor 1 år (2014)'!$A121:$J122) -> 0 | I100: =DSUM(Kontoutdrag_officiella!$A:$J,"t",'Villkor 1 år (2014)'!$A187:$J188) -> -150 | J100: =DSUM(Kontoutdrag_officiella!$A:$J,"t",'Villkor 1 år (2014)'!$A253:$J254) -> 2390 | K100: =DSUM(Kontoutdrag_officiella!$A:$J,"t",'Villkor 1 år (2014)'!$A319:$J320) -> -8332 | L100: =DSUM(Kontoutdrag_officiella!$A:$J,"t",'Villkor 1 år (2014)'!$A385:$J386) -> -1203 | M100: =DSUM(Kontoutdrag_officiella!$A:$J,"t",'Villkor 1 år (2014)'!$A451:$J452) -> 0 | N100: =DSUM(Kontoutdrag_officiella!$A:$J,"t",'Villkor 1 år (2014)'!$A517:$J518) -> 0 | O100: =DSUM(Kontoutdrag_officiella!$A:$J,"t",'Villkor 1 år (2014)'!$A583:$J584) -> -530 | P100: =DSUM(Kontoutdrag_officiella!$A:$J,"t",'Villkor 1 år (2014)'!$A649:$J650) -> 0 | Q100: =DSUM(Kontoutdrag_officiella!$A:$J,"t",'Villkor 1 år (2014)'!$A715:$J716) -> -169.9 | R100: =DSUM(Kontoutdrag_officiella!$A:$J,"t",'Villkor 1 år (2014)'!$A781:$J782) -> -364.11 | S100: =SUM(G100:R100) -> -7724.01 | T100: spara till russel övrigt | V100: =S100/$V$71 -> -643.6675 | W100: =SUM(S100)/W$71 -> -643.6675 | X100: =C52 -> 450 | Y100: =C52+V100 -> -193.6675
A101: Ut | B101: kläder | G101: =DSUM(Kontoutdrag_officiella!$A:$J,"t",'Villkor 1 år (2014)'!$A57:$J58) -> -399 | H101: =DSUM(Kontoutdrag_officiella!$A:$J,"t",'Villkor 1 år (2014)'!$A123:$J124) -> 0 | I101: =DSUM(Kontoutdrag_officiella!$A:$J,"t",'Villkor 1 år (2014)'!$A189:$J190) -> 0 | J101: =DSUM(Kontoutdrag_officiella!$A:$J,"t",'Villkor 1 år (2014)'!$A255:$J256) -> 0 | K101: =DSUM(Kontoutdrag_officiella!$A:$J,"t",'Villkor 1 år (2014)'!$A321:$J322) -> -499 | L101: =DSUM(Kontoutdrag_officiella!$A:$J,"t",'Villkor 1 år (2014)'!$A387:$J388) -> -2674 | M101: =DSUM(Kontoutdrag_officiella!$A:$J,"t",'Villkor 1 år (2014)'!$A453:$J454) -> 0 | N101: =DSUM(Kontoutdrag_officiella!$A:$J,"t",'Villkor 1 år (2014)'!$A519:$J520) -> 0 | O101: =DSUM(Kontoutdrag_officiella!$A:$J,"t",'Villkor 1 år (2014)'!$A585:$J586) -> 0 | P101: =DSUM(Kontoutdrag_officiella!$A:$J,"t",'Villkor 1 år (2014)'!$A651:$J652) -> 0 | Q101: =DSUM(Kontoutdrag_officiella!$A:$J,"t",'Villkor 1 år (2014)'!$A717:$J718) -> 0 | R101: =DSUM(Kontoutdrag_officiella!$A:$J,"t",'Villkor 1 år (2014)'!$A783:$J784) -> 0 | S101: =SUM(G101:R101) -> -3572 | T101: kläder | V101: =S101/$V$71 -> -297.66667 | W101: =SUM(S101)/W$71 -> -297.66667 | X101: =C53 -> 150 | Y101: =C53+V101 -> -147.66667
A102: Ut | B102: presenter | G102: =DSUM(Kontoutdrag_officiella!$A:$J,"t",'Villkor 1 år (2014)'!$A59:$J60) -> 2561 | H102: =DSUM(Kontoutdrag_officiella!$A:$J,"t",'Villkor 1 år (2014)'!$A125:$J126) -> -1712.74 | I102: =DSUM(Kontoutdrag_officiella!$A:$J,"t",'Villkor 1 år (2014)'!$A191:$J192) -> -849 | J102: =DSUM(Kontoutdrag_officiella!$A:$J,"t",'Villkor 1 år (2014)'!$A257:$J258) -> -1526 | K102: =DSUM(Kontoutdrag_officiella!$A:$J,"t",'Villkor 1 år (2014)'!$A323:$J324) -> -717.5 | L102: =DSUM(Kontoutdrag_officiella!$A:$J,"t",'Villkor 1 år (2014)'!$A389:$J390) -> -317.6 | M102: =DSUM(Kontoutdrag_officiella!$A:$J,"t",'Villkor 1 år (2014)'!$A455:$J456) -> 0 | N102: =DSUM(Kontoutdrag_officiella!$A:$J,"t",'Villkor 1 år (2014)'!$A521:$J522) -> 3000 | O102: =DSUM(Kontoutdrag_officiella!$A:$J,"t",'Villkor 1 år (2014)'!$A587:$J588) -> -9008 | P102: =DSUM(Kontoutdrag_officiella!$A:$J,"t",'Villkor 1 år (2014)'!$A653:$J654) -> -71.9 | Q102: =DSUM(Kontoutdrag_officiella!$A:$J,"t",'Villkor 1 år (2014)'!$A719:$J720) -> -6565 | R102: =DSUM(Kontoutdrag_officiella!$A:$J,"t",'Villkor 1 år (2014)'!$A785:$J786) -> -300 | S102: =SUM(G102:R102) -> -15506.74 | T102: presenter | V102: =S102/$V$71 -> -1292.2283 | W102: =SUM(S102)/W$71 -> -1292.2283 | X102: =C54 -> 1000 | Y102: =C54+V102 -> -292.22833
...

Sheet Villkor 1 år (2014)
A1: y | B1: m | D1: d | E1: n | F1: e | G1: t | J1: b | L1: år | M1: =2014 -> 2014 | N1: Steg mellan varje | O1: =21-1 -> 20
A2: =$M$1 -> 2014 | B2: 1 | J2: hyra (inkl. 1k amortering)
A3: y | B3: m | D3: d | E3: n | F3: e | G3: t | J3: b
A4: =$M$1 -> 2014 | B4: 1 | J4: si och akassa
A5: y | B5: m | D5: d | E5: n | F5: e | G5: t | J5: b
A6: =$M$1 -> 2014 | B6: 1 | J6: hemförsäkring
A7: y | B7: m | D7: d | E7: n | F7: e | G7: t | J7: b
A8: =$M$1 -> 2014 | B8: 1 | J8: liv- o sjukförsäkring etc
A9: y | B9: m | D9: d | E9: n | F9: e | G9: t | J9: b
A10: =$M$1 -> 2014 | B10: 1 | J10: stockholms stads bostadskö
A11: y | B11: m | D11: d | E11: n | F11: e | G11: t | J11: b
A12: =$M$1 -> 2014 | B12: 1 | J12: csn
A13: y | B13: m | D13: d | E13: n | F13: e | G13: t | J13: b
A14: =$M$1 -> 2014 | B14: 1 | J14: röda korset
A15: y | B15: m | D15: d | E15: n | F15: e | G15: t | J15: b
A16: =$M$1 -> 2014 | B16: 1 | J16: el
A17: y | B17: m | D17: d | E17: n | F17: e | G17: t | J17: b
A18: =$M$1 -> 2014 | B18: 1 | J18: internet
A19: y | B19: m | D19: d | E19: n | F19: e | G19: t | J19: b
A20: =$M$1 -> 2014 | B20: 1 | J20: telefonsamtal
A21: y | B21: m | D21: d | E21: n | F21: e | G21: t | J21: b
A22: =$M$1 -> 2014 | B22: 1 | J22: hygien (disk, tvätt o tvål etc)
A23: y | B23: m | D23: d | E23: n | F23: e | G23: t | J23: b
A24: =$M$1 -> 2014 | B24: 1 | J24: hemlagad mat
A25: y | B25: m | D25: d | E25: n | F25: e | G25: t | J25: b
A26: =$M$1 -> 2014 | B26: 1 | J26: hemlagad lunch
A27: y | B27: m | D27: d | E27: n | F27: e | G27: t | J27: b
A28: =$M$1 -> 2014 | B28: 1 | J28: lunch utemat
A29: y | B29: m | D29: d | E29: n | F29: e | G29: t | J29: b
A30: =$M$1 -> 2014 | B30: 1 | J30: nöjes utemat
A31: y | B31: m | D31: d | E31: n | F31: e | G31: t | J31: b
A32: =$M$1 -> 2014 | B32: 1 | J32: mat i samband med supa
A33: y | B33: m | D33: d | E33: n | F33: e | G33: t | J33: b
A34: =$M$1 -> 2014 | B34: 1 | J34: alkohol
A35: y | B35: m | D35: d | E35: n | F35: e | G35: t | J35: b
A36: =$M$1 -> 2014 | B36: 1 | J36: taxi efter supa
A37: y | B37: m | D37: d | E37: n | F37: e | G37: t | J37: b
A38: =$M$1 -> 2014 | B38: 1 | J38: Buss etc i samband med supa
A39: y | B39: m | D39: d | E39: n | F39: e | G39: t | J39: b
A40: =$M$1 -> 2014 | B40: 1 | J40: oväntade utgifter
A41: y | B41: m | D41: d | E41: n | F41: e | G41: t | J41: b
A42: =$M$1 -> 2014 | B42: 1 | J42: Småresor ej supa
A43: y | B43: m | D43: d | E43: n | F43: e | G43: t | J43: b
A44: =$M$1 -> 2014 | B44: 1 | J44: resor i samband med utflykt
A45: y | B45: m | D45: d | E45: n | F45: e | G45: t | J45: b
A46: =$M$1 -> 2014 | B46: 1 | J46: värnamoresor+övriga
A47: y | B47: m | D47: d | E47: n | F47: e | G47: t | J47: b
A48: =$M$1 -> 2014 | B48: 1 | J48: spara almänt
A49: y | B49: m | D49: d | E49: n | F49: e | G49: t | J49: b
A50: =$M$1 -> 2014 | B50: 1 | J50: spara till amortering
A51: y | B51: m | D51: d | E51: n | F51: e | G51: t | J51: b
A52: =$M$1 -> 2014 | B52: 1 | J52: spara till sommarrussel
A53: y | B53: m | D53: d | E53: n | F53: e | G53: t | J53: b
A54: =$M$1 -> 2014 | B54: 1 | J54: spara till dator
A55: y | B55: m | D55: d | E55: n | F55: e | G55: t | J55: b
A56: =$M$1 -> 2014 | B56: 1 | J56: spara till russel övrigt
A57: y | B57: m | D57: d | E57: n | F57: e | G57: t | J57: b
A58: =$M$1 -> 2014 | B58: 1 | J58: kläder
A59: y | B59: m | D59: d | E59: n | F59: e | G59: t | J59: b
A60: =$M$1 -> 2014 | B60: 1 | J60: presenter
A61: y | B61: m | D61: d | E61: n | F61: e | G61: t | J61: b
A62: =$M$1 -> 2014 | B62: 1 | J62: Inträde i samband med supa
A63: y | B63: m | D63: d | E63: n | F63: e | G63: t | J63: b
A64: =$M$1 -> 2014 | B64: 1 | J64: övrigt i samband med supa
A65: y | B65: m | D65: d | E65: n | F65: e | G65: t | J65: b
A66: =$M$1 -> 2014 | B66: 1 | J66: hushåll, reparationer etc inköp av nya husshållsmaskiner
A67: y | B67: m | D67: d | E67: n | F67: e | G67: t | J67: b
A68: =$M$1 -> 2014 | B68: 2 | J68: hyra (inkl. 1k amortering)
A69: y | B69: m | D69: d | E69: n | F69: e | G69: t | J69: b
A70: =$M$1 -> 2014 | B70: 2 | J70: si och akassa
A71: y | B71: m | D71: d | E71: n | F71: e | G71: t | J71: b
A72: =$M$1 -> 2014 | B72: 2 | J72: hemförsäkring
A73: y | B73: m | D73: d | E73: n | F73: e | G73: t | J73: b
A74: =$M$1 -> 2014 | B74: 2 | J74: liv- o sjukförsäkring etc
A75: y | B75: m | D75: d | E75: n | F75: e | G75: t | J75: b
A76: =$M$1 -> 2014 | B76: 2 | J76: stockholms stads bostadskö
A77: y | B77: m | D77: d | E77: n | F77: e | G77: t | J77: b
A78: =$M$1 -> 2014 | B78: 2 | J78: csn
A79: y | B79: m | D79: d | E79: n | F79: e | G79: t | J79: b
A80: =$M$1 -> 2014 | B80: 2 | J80: röda korset
A81: y | B81: m | D81: d | E81: n | F81: e | G81: t | J81: b
A82: =$M$1 -> 2014 | B82: 2 | J82: el
A83: y | B83: m | D83: d | E83: n | F83: e | G83: t | J83: b
A84: =$M$1 -> 2014 | B84: 2 | J84: internet
A85: y | B85: m | D85: d | E85: n | F85: e | G85: t | J85: b
A86: =$M$1 -> 2014 | B86: 2 | J86: telefonsamtal
A87: y | B87: m | D87: d | E87: n | F87: e | G87: t | J87: b
A88: =$M$1 -> 2014 | B88: 2 | J88: hygien (disk, tvätt o tvål etc)
A89: y | B89: m | D89: d | E89: n | F89: e | G89: t | J89: b
A90: =$M$1 -> 2014 | B90: 2 | J90: hemlagad mat
A91: y | B91: m | D91: d | E91: n | F91: e | G91: t | J91: b
A92: =$M$1 -> 2014 | B92: 2 | J92: hemlagad lunch
A93: y | B93: m | D93: d | E93: n | F93: e | G93: t | J93: b
A94: =$M$1 -> 2014 | B94: 2 | J94: lunch utemat
A95: y | B95: m | D95: d | E95: n | F95: e | G95: t | J95: b
A96: =$M$1 -> 2014 | B96: 2 | J96: nöjes utemat
A97: y | B97: m | D97: d | E97: n | F97: e | G97: t | J97: b
A98: =$M$1 -> 2014 | B98: 2 | J98: mat i samband med supa
A99: y | B99: m | D99: d | E99: n | F99: e | G99: t | J99: b
A100: =$M$1 -> 2014 | B100: 2 | J100: alkohol
...
